Workbook

Sheet Readme
A1: Objais formal revenue model
A3: Evidence status | B3: ALL numerical inputs are illustrative assumptions, not Objais results, prices, contracts or forecasts.
A4: Mathematical source | B4: Objais Revenue Model.tex contains definitions, derivations and limits. revenue_model.py is the executable reference.
A5: What this file does | B5: Six synthetic architectures, editable parameters and live 36-month expected-value formulas; native currency EUR for every example.
A6: Edit | B6: Blue cells on Parameters are inputs. Formula-derived initial payments are not blue. Each S sheet has calendar and single-acquired-owner blocks.
A7: Opportunity states | B7: E: retained owner with one unexhausted opportunity. M: retained owner after monetisation. State continuation is distinct from policy survival and billing continuation.
A8: q definition | B8: Probability of the first payable monetary event per eligible owner-month; lead acceptance in S1-S5 and policy binding in S6. Do not reuse an observed rate across these definitions.
A9: Repeat eligibility | B9: Reset probability is a genuinely new payable opportunity, not another app visit, record, scan or automatic policy revaluation.
A10: Initial payment | B10: Lead case: stated fee. Binding case: eligible premium times commission rate times retained share. Architectures are alternatives; no lead+binding double counting.
A11: Other streams | B11: Software and annual renewal hypotheses are separate. Lead-only architecture does not earn renewal income. Service-referral events exist in the formal specification but are not simulated here.
A12: Time convention | B12: Acquisition and monetisation during month; retention and eligibility reset at month end. New software pays in month of acquisition; first annual renewal is month 13.
A13: Cost convention | B13: Eligible/completed month cost plus event processing, subscription and policy costs. Acquisition charged once, fixed costs kept separate.
A14: Customer value | B14: Cohort block acquires one owner in month 1, no further acquisition, no CAC or fixed cost. Its discounted contribution is V36 before CAC; Summary subtracts CAC once.
... A24: Updated finite model | B24: Advanced Results, Inputs and Monthly contain labelled Python snapshots of the episodic model. Acquisition Curve has live nonlinear cost formulas. Run build_extension_examples.py before rebuilding advanced snapshots.

Sheet Parameters
A1: Illustrative assumptions — no empirical calibration
A2: q and payment are defined by the event basis. A renewal-rights switch is a hypothetical scenario, not a verified contract.
A4: Parameter | B4: Symbol | C4: Unit | D4: S1 | E4: S2 | F4: S3 | G4: S4 | H4: S5 | I4: S6 | J4: Definition / evidence
A5: Architecture selector | B5: z_N | C5: 0 lead; 1 bound policy | D5: 0 | E5: 0 | F5: 0 | G5: 0 | H5: 0 | I5: 1 | J5: Alternatives, not simultaneous initial remuneration; ILLUSTRATIVE
A6: Payable-event probability | B6: q | C6: fraction | D6: 0.1 | E6: 0.1 | F6: 0.1 | G6: 0.1 | H6: 0.1 | I6: 0.1 | J6: Lead acceptance or binding depending on selector; ILLUSTRATIVE
A7: Pre-event continuation | B7: rho_E | C7: fraction | D7: 0 | E7: 0 | F7: 0.8 | G7: 0.8 | H7: 0 | I7: 0 | J7: Unexhausted opportunity continuation; ILLUSTRATIVE
A8: Post-event continuation | B8: rho_M | C8: fraction | D8: 0 | E8: 0.8 | F8: 0.8 | G8: 0.8 | H8: 0.8 | I8: 0 | J8: Completed opportunity continuation; ILLUSTRATIVE
A9: New eligibility | B9: lambda | C9: fraction | D9: 0 | E9: 0 | F9: 0 | G9: 0.1 | H9: 0 | I9: 0 | J9: Genuine new payable episode; ILLUSTRATIVE
A10: Lead fee | B10: f_L | C10: EUR per lead | D10: 20 | E10: 20 | F10: 20 | G10: 20 | H10: 20 | I10: 20 | J10: Synthetic lead fee; ILLUSTRATIVE
A11: Eligible policy premium | B11: P | C11: EUR per policy | D11: 300 | E11: 300 | F11: 300 | G11: 300 | H11: 300 | I11: 300 | J11: Synthetic commission basis; ILLUSTRATIVE
A12: Initial commission rate | B12: nu_N | C12: fraction | D12: 0.1 | E12: 0.1 | F12: 0.1 | G12: 0.1 | H12: 0.1 | I12: 0.1 | J12: Synthetic rate; ILLUSTRATIVE
A13: Retained commission share | B13: s_N | C13: fraction | D13: 1 | E13: 1 | F13: 1 | G13: 1 | H13: 1 | I13: 1 | J13: Synthetic share; ILLUSTRATIVE
A14: Initial payment derived | B14: f | C14: EUR per event | D14: =IF(Parameters!$D$5=1,Parameters!$D$11*Parameters!$D$12*Parameters!$D$13,Parameters!$D$10) -> 20 | E14: =IF(Parameters!$E$5=1,Parameters!$E$11*Parameters!$E$12*Parameters!$E$13,Parameters!$E$10) -> 20 | F14: =IF(Parameters!$F$5=1,Parameters!$F$11*Parameters!$F$12*Parameters!$F$13,Parameters!$F$10) -> 20 | G14: =IF(Parameters!$G$5=1,Parameters!$G$11*Parameters!$G$12*Parameters!$G$13,Parameters!$G$10) -> 20 | H14: =IF(Parameters!$H$5=1,Parameters!$H$11*Parameters!$H$12*Parameters!$H$13,Parameters!$H$10) -> 20 | I14: =IF(Parameters!$I$5=1,Parameters!$I$11*Parameters!$I$12*Parameters!$I$13,Parameters!$I$10) -> 30 | J14: Lead fee OR premium × rate × share; ILLUSTRATIVE
A15: Payment reversal fraction | B15: omega | C15: fraction | D15: 0.05 | E15: 0.05 | F15: 0.05 | G15: 0.05 | H15: 0.05 | I15: 0 | J15: Expected current-period credit; not policy survival; ILLUSTRATIVE
A16: Processing cost per event | B16: h | C16: EUR per event | D16: 1 | E16: 1 | F16: 1 | G16: 1 | H16: 1 | I16: 1 | J16: Synthetic event processing cost; ILLUSTRATIVE
A17: Eligible-owner monthly cost | B17: v_E | C17: EUR per owner-month | D17: 0.2 | E17: 0.2 | F17: 0.2 | G17: 0.2 | H17: 0.2 | I17: 0.2 | J17: Synthetic cost before event; ILLUSTRATIVE
A18: Completed-owner monthly cost | B18: v_M | C18: EUR per owner-month | D18: 0.3 | E18: 0.3 | F18: 0.3 | G18: 0.3 | H18: 0.3 | I18: 0.3 | J18: Synthetic cost after event; ILLUSTRATIVE
A19: Acquisition cost | B19: k | C19: EUR per acquired owner | D19: 4 | E19: 4 | F19: 4 | G19: 4 | H19: 4 | I19: 4 | J19: Synthetic CAC; ILLUSTRATIVE
A20: New owners per month | B20: A_t | C20: owners | D20: 1000 | E20: 1000 | F20: 1000 | G20: 1000 | H20: 1000 | I20: 1000 | J20: Synthetic calendar inflow; ILLUSTRATIVE
A21: Fixed monthly cost | B21: F | C21: EUR per month | D21: 1000 | E21: 1000 | F21: 1000 | G21: 1000 | H21: 1000 | I21: 1000 | J21: Synthetic fixed operating expense; ILLUSTRATIVE
A22: New software paid conversion | B22: kappa | C22: fraction | D22: 0 | E22: 0 | F22: 0 | G22: 0 | H22: 0.05 | I22: 0 | J22: Synthetic paid conversion; ILLUSTRATIVE
A23: Software billed continuation | B23: eta | C23: fraction | D23: 0.95 | E23: 0.95 | F23: 0.95 | G23: 0.95 | H23: 0.95 | I23: 0.95 | J23: Independent billing-cohort marginal; ILLUSTRATIVE
A24: Software monthly payment | B24: b | C24: EUR per billed month | D24: 3 | E24: 3 | F24: 3 | G24: 3 | H24: 3 | I24: 3 | J24: Synthetic monthly price; ILLUSTRATIVE
A25: Software monthly cost | B25: v_S | C25: EUR per billed month | D25: 0.5 | E25: 0.5 | F25: 0.5 | G25: 0.5 | H25: 0.5 | I25: 0.5 | J25: Synthetic incremental cost; ILLUSTRATIVE
A26: Renewal remuneration switch | B26: z_pi | C26: 0 or 1 | D26: 0 | E26: 0 | F26: 0 | G26: 0 | H26: 0 | I26: 1 | J26: Hypothetical rights; requires policy architecture; ILLUSTRATIVE
... A32: Monthly discount rate | B32: i | C32: fraction | D32: 0.01 | E32: 0.01 | F32: 0.01 | G32: 0.01 | H32: 0.01 | I32: 0.01 | J32: Synthetic time-value convention; ILLUSTRATIVE

Sheet Summary
A1: Counterfactual model outputs — illustrative only
A2: V36 is per one acquired owner. Calendar totals use 1,000 new owners per month and separate fixed costs. EUR in all examples.
A4: Case | B4: Architecture | C4: V36 before CAC | D4: V36 minus CAC | E4: Revenue 36 months | F4: Contribution 36 months | G4: Operating result 36 months | H4: Cash surplus 36 months | I4: Closing receivables | J4: Break-even CAC V36 | K4: Structural input check
A5: S1 | B5: Illustrative one-visit lead sales | C5: =SUM(S1!Z45:Z80) -> 1.6 | D5: =C5-Parameters!$D$19 -> -2.4 | E5: =SUM(S1!M5:M40) -> 68400 | F5: =SUM(S1!P5:P40) -> -86400 | G5: =SUM(S1!R5:R40) -> -122400 | H5: =SUM(S1!U5:U40) -> -124300 | I5: =S1!T40 -> 1900 | J5: =C5 -> 1.6 | K5: =IF(AND(Parameters!$D$5=0,Parameters!$D$26=1),"INVALID RIGHTS COMBINATION","OK: assumptions only") -> OK: assumptions only
A6: S2 | B6: Retain after first lead only | C6: =SUM(S2!Z45:Z80) -> 1.485747 | D6: =C6-Parameters!$E$19 -> -2.514253 | E6: =SUM(S2!M5:M40) -> 68400 | F6: =SUM(S2!P5:P40) -> -90120.195 | G6: =SUM(S2!R5:R40) -> -126120.19 | H6: =SUM(S2!U5:U40) -> -128020.19 | I6: =S2!T40 -> 1900 | J6: =C6 -> 1.485747 | K6: =IF(AND(Parameters!$E$5=0,Parameters!$E$26=1),"INVALID RIGHTS COMBINATION","OK: assumptions only") -> OK: assumptions only
A7: S3 | B7: Retain before and after first lead | C7: =SUM(S3!Z45:Z80) -> 5.1746777 | D7: =C7-Parameters!$F$19 -> 1.1746777 | E7: =SUM(S3!M5:M40) -> 226836.86 | F7: =SUM(S3!P5:P40) -> 34834.915 | G7: =SUM(S3!R5:R40) -> -1165.0848 | H7: =SUM(S3!U5:U40) -> -7950.7495 | I7: =S3!T40 -> 6785.6647 | J7: =C7 -> 5.1746777 | K7: =IF(AND(Parameters!$F$5=0,Parameters!$F$26=1),"INVALID RIGHTS COMBINATION","OK: assumptions only") -> OK: assumptions only
A8: S4 | B8: New eligible opportunities | C8: =SUM(S4!Z45:Z80) -> 5.8769525 | D8: =C8-Parameters!$G$19 -> 1.8769525 | E8: =SUM(S4!M5:M40) -> 247345.08 | F8: =SUM(S4!P5:P40) -> 55343.129 | G8: =SUM(S4!R5:R40) -> 19343.129 | H8: =SUM(S4!U5:U40) -> 11787.934 | I8: =S4!T40 -> 7555.1952 | J8: =C8 -> 5.8769525 | K8: =IF(AND(Parameters!$G$5=0,Parameters!$G$26=1),"INVALID RIGHTS COMBINATION","OK: assumptions only") -> OK: assumptions only
A9: S5 | B9: Paid tools with post-lead retention | C9: =SUM(S5!Z45:Z80) -> 3.357875 | D9: =C9-Parameters!$H$19 -> -0.64212505 | E9: =SUM(S5!M5:M40) -> 128393.42 | F9: =SUM(S5!P5:P40) -> -40125.682 | G9: =SUM(S5!R5:R40) -> -76125.682 | H9: =SUM(S5!U5:U40) -> -80552.344 | I9: =S5!T40 -> 4426.6624 | J9: =C9 -> 3.357875 | K9: =IF(AND(Parameters!$H$5=0,Parameters!$H$26=1),"INVALID RIGHTS COMBINATION","OK: assumptions only") -> OK: assumptions only
A10: S6 | B10: Policy commission and renewal hypothesis | C10: =SUM(S6!Z45:Z80) -> 4.2490816 | D10: =C10-Parameters!$I$19 -> 0.24908164 | E10: =SUM(S6!M5:M40) -> 147333.85 | F10: =SUM(S6!P5:P40) -> -12804.874 | G10: =SUM(S6!R5:R40) -> -48804.874 | H10: =SUM(S6!U5:U40) -> -53905.619 | I10: =S6!T40 -> 5100.7456 | J10: =C10 -> 4.2490816 | K10: =IF(AND(Parameters!$I$5=0,Parameters!$I$26=1),"INVALID RIGHTS COMBINATION","OK: assumptions only") -> OK: assumptions only

Sheet S1
A1: S1 — Illustrative one-visit lead sales
A2: All parameters are illustrative. Top block: calendar cohorts. Lower block: one acquired owner, no CAC/fixed cost, for customer-value calculation.
A4: Month | B4: Acquired | C4: E eligible | D4: M completed active | E4: Payable events | F4: New policies | G4: Active policies | H4: Renewed policies | I4: Billed subscribers | J4: Initial revenue | K4: Renewal revenue | L4: Software revenue | M4: Total revenue | N4: Variable cost | O4: Acquisition cost | P4: Contribution | Q4: Fixed cost | R4: Operating result | S4: Cash receipts | T4: Receivables | U4: Cash surplus | V4: Cumulative cash | W4: Churned opportunity owners | X4: Next E | Y4: Next M | Z4: Discounted contribution before CAC
A5: 1 | B5: =Parameters!$D$20 -> 1000 | C5: =B5 -> 1000 | D5: =0 -> 0 | E5: =Parameters!$D$6*C5 -> 100 | F5: =IF(Parameters!$D$5=1,E5,0) -> 0 | G5: =F5 -> 0 | H5: =IF(AND(Parameters!$D$5=1,Parameters!$D$26=1),SUMPRODUCT(--($A$5:A5<A5),--(MOD(A5-$A$5:A5,Parameters!$D$28)=0),$F$5:F5,POWER(Parameters!$D$27,IF(A5-$A$5:A5=0,1,A5-$A$5:A5))),0) -> 0 | I5: =B5*Parameters!$D$22 -> 0 | J5: =E5*Parameters!$D$14*(1-Parameters!$D$15) -> 1900 | K5: =H5*Parameters!$D$29 -> 0 | L5: =I5*Parameters!$D$24 -> 0 | M5: =J5+K5+L5 -> 1900 | N5: =C5*Parameters!$D$17+D5*Parameters!$D$18+E5*Parameters!$D$16+I5*Parameters!$D$25+G5*Parameters!$D$30 -> 300 | O5: =B5*Parameters!$D$19 -> 4000 | P5: =M5-N5-O5 -> -2400 | Q5: =Parameters!$D$21 -> 1000 | R5: =P5-Q5 -> -3400 | S5: =IF(A5<1+Parameters!$D$31,0,INDEX($M$5:$M$40,A5-Parameters!$D$31)) -> 0 | T5: =M5-S5 -> 1900 | U5: =S5-N5-O5-Q5 -> -5300 | V5: =U5 -> -5300 | W5: =(1-Parameters!$D$7)*(C5-E5)+(1-Parameters!$D$8)*(D5+E5) -> 1000 | X5: =Parameters!$D$7*(C5-E5)+Parameters!$D$8*Parameters!$D$9*(D5+E5) -> 0 | Y5: =Parameters!$D$8*(1-Parameters!$D$9)*(D5+E5) -> 0 | Z5: =POWER(1/(1+Parameters!$D$32),A5-1)*(M5-N5) -> 1600
A6: 2 | B6: =Parameters!$D$20 -> 1000 | C6: =X5+B6 -> 1000 | D6: =Y5 -> 0 | E6: =Parameters!$D$6*C6 -> 100 | F6: =IF(Parameters!$D$5=1,E6,0) -> 0 | G6: =Parameters!$D$27*G5+F6 -> 0 | H6: =IF(AND(Parameters!$D$5=1,Parameters!$D$26=1),SUMPRODUCT(--($A$5:A6<A6),--(MOD(A6-$A$5:A6,Parameters!$D$28)=0),$F$5:F6,POWER(Parameters!$D$27,IF(A6-$A$5:A6=0,1,A6-$A$5:A6))),0) -> 0 | I6: =Parameters!$D$23*I5+B6*Parameters!$D$22 -> 0 | J6: =E6*Parameters!$D$14*(1-Parameters!$D$15) -> 1900 | K6: =H6*Parameters!$D$29 -> 0 | L6: =I6*Parameters!$D$24 -> 0 | M6: =J6+K6+L6 -> 1900 | N6: =C6*Parameters!$D$17+D6*Parameters!$D$18+E6*Parameters!$D$16+I6*Parameters!$D$25+G6*Parameters!$D$30 -> 300 | O6: =B6*Parameters!$D$19 -> 4000 | P6: =M6-N6-O6 -> -2400 | Q6: =Parameters!$D$21 -> 1000 | R6: =P6-Q6 -> -3400 | S6: =IF(A6<1+Parameters!$D$31,0,INDEX($M$5:$M$40,A6-Parameters!$D$31)) -> 1900 | T6: =T5+M6-S6 -> 1900 | U6: =S6-N6-O6-Q6 -> -3400 | V6: =V5+U6 -> -8700 | W6: =(1-Parameters!$D$7)*(C6-E6)+(1-Parameters!$D$8)*(D6+E6) -> 1000 | X6: =Parameters!$D$7*(C6-E6)+Parameters!$D$8*Parameters!$D$9*(D6+E6) -> 0 | Y6: =Parameters!$D$8*(1-Parameters!$D$9)*(D6+E6) -> 0 | Z6: =POWER(1/(1+Parameters!$D$32),A6-1)*(M6-N6) -> 1584.1584
A7: 3 | B7: =Parameters!$D$20 -> 1000 | C7: =X6+B7 -> 1000 | D7: =Y6 -> 0 | E7: =Parameters!$D$6*C7 -> 100 | F7: =IF(Parameters!$D$5=1,E7,0) -> 0 | G7: =Parameters!$D$27*G6+F7 -> 0 | H7: =IF(AND(Parameters!$D$5=1,Parameters!$D$26=1),SUMPRODUCT(--($A$5:A7<A7),--(MOD(A7-$A$5:A7,Parameters!$D$28)=0),$F$5:F7,POWER(Parameters!$D$27,IF(A7-$A$5:A7=0,1,A7-$A$5:A7))),0) -> 0 | I7: =Parameters!$D$23*I6+B7*Parameters!$D$22 -> 0 | J7: =E7*Parameters!$D$14*(1-Parameters!$D$15) -> 1900 | K7: =H7*Parameters!$D$29 -> 0 | L7: =I7*Parameters!$D$24 -> 0 | M7: =J7+K7+L7 -> 1900 | N7: =C7*Parameters!$D$17+D7*Parameters!$D$18+E7*Parameters!$D$16+I7*Parameters!$D$25+G7*Parameters!$D$30 -> 300 | O7: =B7*Parameters!$D$19 -> 4000 | P7: =M7-N7-O7 -> -2400 | Q7: =Parameters!$D$21 -> 1000 | R7: =P7-Q7 -> -3400 | S7: =IF(A7<1+Parameters!$D$31,0,INDEX($M$5:$M$40,A7-Parameters!$D$31)) -> 1900 | T7: =T6+M7-S7 -> 1900 | U7: =S7-N7-O7-Q7 -> -3400 | V7: =V6+U7 -> -12100 | W7: =(1-Parameters!$D$7)*(C7-E7)+(1-Parameters!$D$8)*(D7+E7) -> 1000 | X7: =Parameters!$D$7*(C7-E7)+Parameters!$D$8*Parameters!$D$9*(D7+E7) -> 0 | Y7: =Parameters!$D$8*(1-Parameters!$D$9)*(D7+E7) -> 0 | Z7: =POWER(1/(1+Parameters!$D$32),A7-1)*(M7-N7) -> 1568.4737
A8: 4 | B8: =Parameters!$D$20 -> 1000 | C8: =X7+B8 -> 1000 | D8: =Y7 -> 0 | E8: =Parameters!$D$6*C8 -> 100 | F8: =IF(Parameters!$D$5=1,E8,0) -> 0 | G8: =Parameters!$D$27*G7+F8 -> 0 | H8: =IF(AND(Parameters!$D$5=1,Parameters!$D$26=1),SUMPRODUCT(--($A$5:A8<A8),--(MOD(A8-$A$5:A8,Parameters!$D$28)=0),$F$5:F8,POWER(Parameters!$D$27,IF(A8-$A$5:A8=0,1,A8-$A$5:A8))),0) -> 0 | I8: =Parameters!$D$23*I7+B8*Parameters!$D$22 -> 0 | J8: =E8*Parameters!$D$14*(1-Parameters!$D$15) -> 1900 | K8: =H8*Parameters!$D$29 -> 0 | L8: =I8*Parameters!$D$24 -> 0 | M8: =J8+K8+L8 -> 1900 | N8: =C8*Parameters!$D$17+D8*Parameters!$D$18+E8*Parameters!$D$16+I8*Parameters!$D$25+G8*Parameters!$D$30 -> 300 | O8: =B8*Parameters!$D$19 -> 4000 | P8: =M8-N8-O8 -> -2400 | Q8: =Parameters!$D$21 -> 1000 | R8: =P8-Q8 -> -3400 | S8: =IF(A8<1+Parameters!$D$31,0,INDEX($M$5:$M$40,A8-Parameters!$D$31)) -> 1900 | T8: =T7+M8-S8 -> 1900 | U8: =S8-N8-O8-Q8 -> -3400 | V8: =V7+U8 -> -15500 | W8: =(1-Parameters!$D$7)*(C8-E8)+(1-Parameters!$D$8)*(D8+E8) -> 1000 | X8: =Parameters!$D$7*(C8-E8)+Parameters!$D$8*Parameters!$D$9*(D8+E8) -> 0 | Y8: =Parameters!$D$8*(1-Parameters!$D$9)*(D8+E8) -> 0 | Z8: =POWER(1/(1+Parameters!$D$32),A8-1)*(M8-N8) -> 1552.9442
A9: 5 | B9: =Parameters!$D$20 -> 1000 | C9: =X8+B9 -> 1000 | D9: =Y8 -> 0 | E9: =Parameters!$D$6*C9 -> 100 | F9: =IF(Parameters!$D$5=1,E9,0) -> 0 | G9: =Parameters!$D$27*G8+F9 -> 0 | H9: =IF(AND(Parameters!$D$5=1,Parameters!$D$26=1),SUMPRODUCT(--($A$5:A9<A9),--(MOD(A9-$A$5:A9,Parameters!$D$28)=0),$F$5:F9,POWER(Parameters!$D$27,IF(A9-$A$5:A9=0,1,A9-$A$5:A9))),0) -> 0 | I9: =Parameters!$D$23*I8+B9*Parameters!$D$22 -> 0 | J9: =E9*Parameters!$D$14*(1-Parameters!$D$15) -> 1900 | K9: =H9*Parameters!$D$29 -> 0 | L9: =I9*Parameters!$D$24 -> 0 | M9: =J9+K9+L9 -> 1900 | N9: =C9*Parameters!$D$17+D9*Parameters!$D$18+E9*Parameters!$D$16+I9*Parameters!$D$25+G9*Parameters!$D$30 -> 300 | O9: =B9*Parameters!$D$19 -> 4000 | P9: =M9-N9-O9 -> -2400 | Q9: =Parameters!$D$21 -> 1000 | R9: =P9-Q9 -> -3400 | S9: =IF(A9<1+Parameters!$D$31,0,INDEX($M$5:$M$40,A9-Parameters!$D$31)) -> 1900 | T9: =T8+M9-S9 -> 1900 | U9: =S9-N9-O9-Q9 -> -3400 | V9: =V8+U9 -> -18900 | W9: =(1-Parameters!$D$7)*(C9-E9)+(1-Parameters!$D$8)*(D9+E9) -> 1000 | X9: =Parameters!$D$7*(C9-E9)+Parameters!$D$8*Parameters!$D$9*(D9+E9) -> 0 | Y9: =Parameters!$D$8*(1-Parameters!$D$9)*(D9+E9) -> 0 | Z9: =POWER(1/(1+Parameters!$D$32),A9-1)*(M9-N9) -> 1537.5686
A10: 6 | B10: =Parameters!$D$20 -> 1000 | C10: =X9+B10 -> 1000 | D10: =Y9 -> 0 | E10: =Parameters!$D$6*C10 -> 100 | F10: =IF(Parameters!$D$5=1,E10,0) -> 0 | G10: =Parameters!$D$27*G9+F10 -> 0 | H10: =IF(AND(Parameters!$D$5=1,Parameters!$D$26=1),SUMPRODUCT(--($A$5:A10<A10),--(MOD(A10-$A$5:A10,Parameters!$D$28)=0),$F$5:F10,POWER(Parameters!$D$27,IF(A10-$A$5:A10=0,1,A10-$A$5:A10))),0) -> 0 | I10: =Parameters!$D$23*I9+B10*Parameters!$D$22 -> 0 | J10: =E10*Parameters!$D$14*(1-Parameters!$D$15) -> 1900 | K10: =H10*Parameters!$D$29 -> 0 | L10: =I10*Parameters!$D$24 -> 0 | M10: =J10+K10+L10 -> 1900 | N10: =C10*Parameters!$D$17+D10*Parameters!$D$18+E10*Parameters!$D$16+I10*Parameters!$D$25+G10*Parameters!$D$30 -> 300 | O10: =B10*Parameters!$D$19 -> 4000 | P10: =M10-N10-O10 -> -2400 | Q10: =Parameters!$D$21 -> 1000 | R10: =P10-Q10 -> -3400 | S10: =IF(A10<1+Parameters!$D$31,0,INDEX($M$5:$M$40,A10-Parameters!$D$31)) -> 1900 | T10: =T9+M10-S10 -> 1900 | U10: =S10-N10-O10-Q10 -> -3400 | V10: =V9+U10 -> -22300 | W10: =(1-Parameters!$D$7)*(C10-E10)+(1-Parameters!$D$8)*(D10+E10) -> 1000 | X10: =Parameters!$D$7*(C10-E10)+Parameters!$D$8*Parameters!$D$9*(D10+E10) -> 0 | Y10: =Parameters!$D$8*(1-Parameters!$D$9)*(D10+E10) -> 0 | Z10: =POWER(1/(1+Parameters!$D$32),A10-1)*(M10-N10) -> 1522.3451
A11: 7 | B11: =Parameters!$D$20 -> 1000 | C11: =X10+B11 -> 1000 | D11: =Y10 -> 0 | E11: =Parameters!$D$6*C11 -> 100 | F11: =IF(Parameters!$D$5=1,E11,0) -> 0 | G11: =Parameters!$D$27*G10+F11 -> 0 | H11: =IF(AND(Parameters!$D$5=1,Parameters!$D$26=1),SUMPRODUCT(--($A$5:A11<A11),--(MOD(A11-$A$5:A11,Parameters!$D$28)=0),$F$5:F11,POWER(Parameters!$D$27,IF(A11-$A$5:A11=0,1,A11-$A$5:A11))),0) -> 0 | I11: =Parameters!$D$23*I10+B11*Parameters!$D$22 -> 0 | J11: =E11*Parameters!$D$14*(1-Parameters!$D$15) -> 1900 | K11: =H11*Parameters!$D$29 -> 0 | L11: =I11*Parameters!$D$24 -> 0 | M11: =J11+K11+L11 -> 1900 | N11: =C11*Parameters!$D$17+D11*Parameters!$D$18+E11*Parameters!$D$16+I11*Parameters!$D$25+G11*Parameters!$D$30 -> 300 | O11: =B11*Parameters!$D$19 -> 4000 | P11: =M11-N11-O11 -> -2400 | Q11: =Parameters!$D$21 -> 1000 | R11: =P11-Q11 -> -3400 | S11: =IF(A11<1+Parameters!$D$31,0,INDEX($M$5:$M$40,A11-Parameters!$D$31)) -> 1900 | T11: =T10+M11-S11 -> 1900 | U11: =S11-N11-O11-Q11 -> -3400 | V11: =V10+U11 -> -25700 | W11: =(1-Parameters!$D$7)*(C11-E11)+(1-Parameters!$D$8)*(D11+E11) -> 1000 | X11: =Parameters!$D$7*(C11-E11)+Parameters!$D$8*Parameters!$D$9*(D11+E11) -> 0 | Y11: =Parameters!$D$8*(1-Parameters!$D$9)*(D11+E11) -> 0 | Z11: =POWER(1/(1+Parameters!$D$32),A11-1)*(M11-N11) -> 1507.2724
A12: 8 | B12: =Parameters!$D$20 -> 1000 | C12: =X11+B12 -> 1000 | D12: =Y11 -> 0 | E12: =Parameters!$D$6*C12 -> 100 | F12: =IF(Parameters!$D$5=1,E12,0) -> 0 | G12: =Parameters!$D$27*G11+F12 -> 0 | H12: =IF(AND(Parameters!$D$5=1,Parameters!$D$26=1),SUMPRODUCT(--($A$5:A12<A12),--(MOD(A12-$A$5:A12,Parameters!$D$28)=0),$F$5:F12,POWER(Parameters!$D$27,IF(A12-$A$5:A12=0,1,A12-$A$5:A12))),0) -> 0 | I12: =Parameters!$D$23*I11+B12*Parameters!$D$22 -> 0 | J12: =E12*Parameters!$D$14*(1-Parameters!$D$15) -> 1900 | K12: =H12*Parameters!$D$29 -> 0 | L12: =I12*Parameters!$D$24 -> 0 | M12: =J12+K12+L12 -> 1900 | N12: =C12*Parameters!$D$17+D12*Parameters!$D$18+E12*Parameters!$D$16+I12*Parameters!$D$25+G12*Parameters!$D$30 -> 300 | O12: =B12*Parameters!$D$19 -> 4000 | P12: =M12-N12-O12 -> -2400 | Q12: =Parameters!$D$21 -> 1000 | R12: =P12-Q12 -> -3400 | S12: =IF(A12<1+Parameters!$D$31,0,INDEX($M$5:$M$40,A12-Parameters!$D$31)) -> 1900 | T12: =T11+M12-S12 -> 1900 | U12: =S12-N12-O12-Q12 -> -3400 | V12: =V11+U12 -> -29100 | W12: =(1-Parameters!$D$7)*(C12-E12)+(1-Parameters!$D$8)*(D12+E12) -> 1000 | X12: =Parameters!$D$7*(C12-E12)+Parameters!$D$8*Parameters!$D$9*(D12+E12) -> 0 | Y12: =Parameters!$D$8*(1-Parameters!$D$9)*(D12+E12) -> 0 | Z12: =POWER(1/(1+Parameters!$D$32),A12-1)*(M12-N12) -> 1492.3489
A13: 9 | B13: =Parameters!$D$20 -> 1000 | C13: =X12+B13 -> 1000 | D13: =Y12 -> 0 | E13: =Parameters!$D$6*C13 -> 100 | F13: =IF(Parameters!$D$5=1,E13,0) -> 0 | G13: =Parameters!$D$27*G12+F13 -> 0 | H13: =IF(AND(Parameters!$D$5=1,Parameters!$D$26=1),SUMPRODUCT(--($A$5:A13<A13),--(MOD(A13-$A$5:A13,Parameters!$D$28)=0),$F$5:F13,POWER(Parameters!$D$27,IF(A13-$A$5:A13=0,1,A13-$A$5:A13))),0) -> 0 | I13: =Parameters!$D$23*I12+B13*Parameters!$D$22 -> 0 | J13: =E13*Parameters!$D$14*(1-Parameters!$D$15) -> 1900 | K13: =H13*Parameters!$D$29 -> 0 | L13: =I13*Parameters!$D$24 -> 0 | M13: =J13+K13+L13 -> 1900 | N13: =C13*Parameters!$D$17+D13*Parameters!$D$18+E13*Parameters!$D$16+I13*Parameters!$D$25+G13*Parameters!$D$30 -> 300 | O13: =B13*Parameters!$D$19 -> 4000 | P13: =M13-N13-O13 -> -2400 | Q13: =Parameters!$D$21 -> 1000 | R13: =P13-Q13 -> -3400 | S13: =IF(A13<1+Parameters!$D$31,0,INDEX($M$5:$M$40,A13-Parameters!$D$31)) -> 1900 | T13: =T12+M13-S13 -> 1900 | U13: =S13-N13-O13-Q13 -> -3400 | V13: =V12+U13 -> -32500 | W13: =(1-Parameters!$D$7)*(C13-E13)+(1-Parameters!$D$8)*(D13+E13) -> 1000 | X13: =Parameters!$D$7*(C13-E13)+Parameters!$D$8*Parameters!$D$9*(D13+E13) -> 0 | Y13: =Parameters!$D$8*(1-Parameters!$D$9)*(D13+E13) -> 0 | Z13: =POWER(1/(1+Parameters!$D$32),A13-1)*(M13-N13) -> 1477.5732
A14: 10 | B14: =Parameters!$D$20 -> 1000 | C14: =X13+B14 -> 1000 | D14: =Y13 -> 0 | E14: =Parameters!$D$6*C14 -> 100 | F14: =IF(Parameters!$D$5=1,E14,0) -> 0 | G14: =Parameters!$D$27*G13+F14 -> 0 | H14: =IF(AND(Parameters!$D$5=1,Parameters!$D$26=1),SUMPRODUCT(--($A$5:A14<A14),--(MOD(A14-$A$5:A14,Parameters!$D$28)=0),$F$5:F14,POWER(Parameters!$D$27,IF(A14-$A$5:A14=0,1,A14-$A$5:A14))),0) -> 0 | I14: =Parameters!$D$23*I13+B14*Parameters!$D$22 -> 0 | J14: =E14*Parameters!$D$14*(1-Parameters!$D$15) -> 1900 | K14: =H14*Parameters!$D$29 -> 0 | L14: =I14*Parameters!$D$24 -> 0 | M14: =J14+K14+L14 -> 1900 | N14: =C14*Parameters!$D$17+D14*Parameters!$D$18+E14*Parameters!$D$16+I14*Parameters!$D$25+G14*Parameters!$D$30 -> 300 | O14: =B14*Parameters!$D$19 -> 4000 | P14: =M14-N14-O14 -> -2400 | Q14: =Parameters!$D$21 -> 1000 | R14: =P14-Q14 -> -3400 | S14: =IF(A14<1+Parameters!$D$31,0,INDEX($M$5:$M$40,A14-Parameters!$D$31)) -> 1900 | T14: =T13+M14-S14 -> 1900 | U14: =S14-N14-O14-Q14 -> -3400 | V14: =V13+U14 -> -35900 | W14: =(1-Parameters!$D$7)*(C14-E14)+(1-Parameters!$D$8)*(D14+E14) -> 1000 | X14: =Parameters!$D$7*(C14-E14)+Parameters!$D$8*Parameters!$D$9*(D14+E14) -> 0 | Y14: =Parameters!$D$8*(1-Parameters!$D$9)*(D14+E14) -> 0 | Z14: =POWER(1/(1+Parameters!$D$32),A14-1)*(M14-N14) -> 1462.9437
A15: 11 | B15: =Parameters!$D$20 -> 1000 | C15: =X14+B15 -> 1000 | D15: =Y14 -> 0 | E15: =Parameters!$D$6*C15 -> 100 | F15: =IF(Parameters!$D$5=1,E15,0) -> 0 | G15: =Parameters!$D$27*G14+F15 -> 0 | H15: =IF(AND(Parameters!$D$5=1,Parameters!$D$26=1),SUMPRODUCT(--($A$5:A15<A15),--(MOD(A15-$A$5:A15,Parameters!$D$28)=0),$F$5:F15,POWER(Parameters!$D$27,IF(A15-$A$5:A15=0,1,A15-$A$5:A15))),0) -> 0 | I15: =Parameters!$D$23*I14+B15*Parameters!$D$22 -> 0 | J15: =E15*Parameters!$D$14*(1-Parameters!$D$15) -> 1900 | K15: =H15*Parameters!$D$29 -> 0 | L15: =I15*Parameters!$D$24 -> 0 | M15: =J15+K15+L15 -> 1900 | N15: =C15*Parameters!$D$17+D15*Parameters!$D$18+E15*Parameters!$D$16+I15*Parameters!$D$25+G15*Parameters!$D$30 -> 300 | O15: =B15*Parameters!$D$19 -> 4000 | P15: =M15-N15-O15 -> -2400 | Q15: =Parameters!$D$21 -> 1000 | R15: =P15-Q15 -> -3400 | S15: =IF(A15<1+Parameters!$D$31,0,INDEX($M$5:$M$40,A15-Parameters!$D$31)) -> 1900 | T15: =T14+M15-S15 -> 1900 | U15: =S15-N15-O15-Q15 -> -3400 | V15: =V14+U15 -> -39300 | W15: =(1-Parameters!$D$7)*(C15-E15)+(1-Parameters!$D$8)*(D15+E15) -> 1000 | X15: =Parameters!$D$7*(C15-E15)+Parameters!$D$8*Parameters!$D$9*(D15+E15) -> 0 | Y15: =Parameters!$D$8*(1-Parameters!$D$9)*(D15+E15) -> 0 | Z15: =POWER(1/(1+Parameters!$D$32),A15-1)*(M15-N15) -> 1448.4591
A16: 12 | B16: =Parameters!$D$20 -> 1000 | C16: =X15+B16 -> 1000 | D16: =Y15 -> 0 | E16: =Parameters!$D$6*C16 -> 100 | F16: =IF(Parameters!$D$5=1,E16,0) -> 0 | G16: =Parameters!$D$27*G15+F16 -> 0 | H16: =IF(AND(Parameters!$D$5=1,Parameters!$D$26=1),SUMPRODUCT(--($A$5:A16<A16),--(MOD(A16-$A$5:A16,Parameters!$D$28)=0),$F$5:F16,POWER(Parameters!$D$27,IF(A16-$A$5:A16=0,1,A16-$A$5:A16))),0) -> 0 | I16: =Parameters!$D$23*I15+B16*Parameters!$D$22 -> 0 | J16: =E16*Parameters!$D$14*(1-Parameters!$D$15) -> 1900 | K16: =H16*Parameters!$D$29 -> 0 | L16: =I16*Parameters!$D$24 -> 0 | M16: =J16+K16+L16 -> 1900 | N16: =C16*Parameters!$D$17+D16*Parameters!$D$18+E16*Parameters!$D$16+I16*Parameters!$D$25+G16*Parameters!$D$30 -> 300 | O16: =B16*Parameters!$D$19 -> 4000 | P16: =M16-N16-O16 -> -2400 | Q16: =Parameters!$D$21 -> 1000 | R16: =P16-Q16 -> -3400 | S16: =IF(A16<1+Parameters!$D$31,0,INDEX($M$5:$M$40,A16-Parameters!$D$31)) -> 1900 | T16: =T15+M16-S16 -> 1900 | U16: =S16-N16-O16-Q16 -> -3400 | V16: =V15+U16 -> -42700 | W16: =(1-Parameters!$D$7)*(C16-E16)+(1-Parameters!$D$8)*(D16+E16) -> 1000 | X16: =Parameters!$D$7*(C16-E16)+Parameters!$D$8*Parameters!$D$9*(D16+E16) -> 0 | Y16: =Parameters!$D$8*(1-Parameters!$D$9)*(D16+E16) -> 0 | Z16: =POWER(1/(1+Parameters!$D$32),A16-1)*(M16-N16) -> 1434.1179
A17: 13 | B17: =Parameters!$D$20 -> 1000 | C17: =X16+B17 -> 1000 | D17: =Y16 -> 0 | E17: =Parameters!$D$6*C17 -> 100 | F17: =IF(Parameters!$D$5=1,E17,0) -> 0 | G17: =Parameters!$D$27*G16+F17 -> 0 | H17: =IF(AND(Parameters!$D$5=1,Parameters!$D$26=1),SUMPRODUCT(--($A$5:A17<A17),--(MOD(A17-$A$5:A17,Parameters!$D$28)=0),$F$5:F17,POWER(Parameters!$D$27,IF(A17-$A$5:A17=0,1,A17-$A$5:A17))),0) -> 0 | I17: =Parameters!$D$23*I16+B17*Parameters!$D$22 -> 0 | J17: =E17*Parameters!$D$14*(1-Parameters!$D$15) -> 1900 | K17: =H17*Parameters!$D$29 -> 0 | L17: =I17*Parameters!$D$24 -> 0 | M17: =J17+K17+L17 -> 1900 | N17: =C17*Parameters!$D$17+D17*Parameters!$D$18+E17*Parameters!$D$16+I17*Parameters!$D$25+G17*Parameters!$D$30 -> 300 | O17: =B17*Parameters!$D$19 -> 4000 | P17: =M17-N17-O17 -> -2400 | Q17: =Parameters!$D$21 -> 1000 | R17: =P17-Q17 -> -3400 | S17: =IF(A17<1+Parameters!$D$31,0,INDEX($M$5:$M$40,A17-Parameters!$D$31)) -> 1900 | T17: =T16+M17-S17 -> 1900 | U17: =S17-N17-O17-Q17 -> -3400 | V17: =V16+U17 -> -46100 | W17: =(1-Parameters!$D$7)*(C17-E17)+(1-Parameters!$D$8)*(D17+E17) -> 1000 | X17: =Parameters!$D$7*(C17-E17)+Parameters!$D$8*Parameters!$D$9*(D17+E17) -> 0 | Y17: =Parameters!$D$8*(1-Parameters!$D$9)*(D17+E17) -> 0 | Z17: =POWER(1/(1+Parameters!$D$32),A17-1)*(M17-N17) -> 1419.9188
... A40: 36 | B40: =Parameters!$D$20 -> 1000 | C40: =X39+B40 -> 1000 | D40: =Y39 -> 0 | E40: =Parameters!$D$6*C40 -> 100 | F40: =IF(Parameters!$D$5=1,E40,0) -> 0 | G40: =Parameters!$D$27*G39+F40 -> 0 | H40: =IF(AND(Parameters!$D$5=1,Parameters!$D$26=1),SUMPRODUCT(--($A$5:A40<A40),--(MOD(A40-$A$5:A40,Parameters!$D$28)=0),$F$5:F40,POWER(Parameters!$D$27,IF(A40-$A$5:A40=0,1,A40-$A$5:A40))),0) -> 0 | I40: =Parameters!$D$23*I39+B40*Parameters!$D$22 -> 0 | J40: =E40*Parameters!$D$14*(1-Parameters!$D$15) -> 1900 | K40: =H40*Parameters!$D$29 -> 0 | L40: =I40*Parameters!$D$24 -> 0 | M40: =J40+K40+L40 -> 1900 | N40: =C40*Parameters!$D$17+D40*Parameters!$D$18+E40*Parameters!$D$16+I40*Parameters!$D$25+G40*Parameters!$D$30 -> 300 | O40: =B40*Parameters!$D$19 -> 4000 | P40: =M40-N40-O40 -> -2400 | Q40: =Parameters!$D$21 -> 1000 | R40: =P40-Q40 -> -3400 | S40: =IF(A40<1+Parameters!$D$31,0,INDEX($M$5:$M$40,A40-Parameters!$D$31)) -> 1900 | T40: =T39+M40-S40 -> 1900 | U40: =S40-N40-O40-Q40 -> -3400 | V40: =V39+U40 -> -124300 | W40: =(1-Parameters!$D$7)*(C40-E40)+(1-Parameters!$D$8)*(D40+E40) -> 1000 | X40: =Parameters!$D$7*(C40-E40)+Parameters!$D$8*Parameters!$D$9*(D40+E40) -> 0 | Y40: =Parameters!$D$8*(1-Parameters!$D$9)*(D40+E40) -> 0 | Z40: =POWER(1/(1+Parameters!$D$32),A40-1)*(M40-N40) -> 1129.4627
A43: One acquired-owner cohort: V36 before acquisition/fixed costs. This isolates the mathematical unit value.
A44: Month | B44: Acquired | C44: E eligible | D44: M completed active | E44: Payable events | F44: New policies | G44: Active policies | H44: Renewed policies | I44: Billed subscribers | J44: Initial revenue | K44: Renewal revenue | L44: Software revenue | M44: Total revenue | N44: Variable cost | O44: Acquisition cost | P44: Contribution | Q44: Fixed cost | R44: Operating result | S44: Cash receipts | T44: Receivables | U44: Cash surplus | V44: Cumulative cash | W44: Churned opportunity owners | X44: Next E | Y44: Next M | Z44: Discounted contribution before CAC
A45: 1 | B45: =1 -> 1 | C45: =B45 -> 1 | D45: =0 -> 0 | E45: =Parameters!$D$6*C45 -> 0.1 | F45: =IF(Parameters!$D$5=1,E45,0) -> 0 | G45: =F45 -> 0 | H45: =IF(AND(Parameters!$D$5=1,Parameters!$D$26=1),SUMPRODUCT(--($A$45:A45<A45),--(MOD(A45-$A$45:A45,Parameters!$D$28)=0),$F$45:F45,POWER(Parameters!$D$27,IF(A45-$A$45:A45=0,1,A45-$A$45:A45))),0) -> 0 | I45: =B45*Parameters!$D$22 -> 0 | J45: =E45*Parameters!$D$14*(1-Parameters!$D$15) -> 1.9 | K45: =H45*Parameters!$D$29 -> 0 | L45: =I45*Parameters!$D$24 -> 0 | M45: =J45+K45+L45 -> 1.9 | N45: =C45*Parameters!$D$17+D45*Parameters!$D$18+E45*Parameters!$D$16+I45*Parameters!$D$25+G45*Parameters!$D$30 -> 0.3 | O45: =0 -> 0 | P45: =M45-N45-O45 -> 1.6 | Q45: =0 -> 0 | R45: =P45-Q45 -> 1.6 | S45: =IF(A45<1+Parameters!$D$31,0,INDEX($M$45:$M$80,A45-Parameters!$D$31)) -> 0 | T45: =M45-S45 -> 1.9 | U45: =S45-N45-O45-Q45 -> -0.3 | V45: =U45 -> -0.3 | W45: =(1-Parameters!$D$7)*(C45-E45)+(1-Parameters!$D$8)*(D45+E45) -> 1 | X45: =Parameters!$D$7*(C45-E45)+Parameters!$D$8*Parameters!$D$9*(D45+E45) -> 0 | Y45: =Parameters!$D$8*(1-Parameters!$D$9)*(D45+E45) -> 0 | Z45: =POWER(1/(1+Parameters!$D$32),A45-1)*(M45-N45) -> 1.6
A46: 2 | B46: =0 -> 0 | C46: =X45+B46 -> 0 | D46: =Y45 -> 0 | E46: =Parameters!$D$6*C46 -> 0 | F46: =IF(Parameters!$D$5=1,E46,0) -> 0 | G46: =Parameters!$D$27*G45+F46 -> 0 | H46: =IF(AND(Parameters!$D$5=1,Parameters!$D$26=1),SUMPRODUCT(--($A$45:A46<A46),--(MOD(A46-$A$45:A46,Parameters!$D$28)=0),$F$45:F46,POWER(Parameters!$D$27,IF(A46-$A$45:A46=0,1,A46-$A$45:A46))),0) -> 0 | I46: =Parameters!$D$23*I45+B46*Parameters!$D$22 -> 0 | J46: =E46*Parameters!$D$14*(1-Parameters!$D$15) -> 0 | K46: =H46*Parameters!$D$29 -> 0 | L46: =I46*Parameters!$D$24 -> 0 | M46: =J46+K46+L46 -> 0 | N46: =C46*Parameters!$D$17+D46*Parameters!$D$18+E46*Parameters!$D$16+I46*Parameters!$D$25+G46*Parameters!$D$30 -> 0 | O46: =0 -> 0 | P46: =M46-N46-O46 -> 0 | Q46: =0 -> 0 | R46: =P46-Q46 -> 0 | S46: =IF(A46<1+Parameters!$D$31,0,INDEX($M$45:$M$80,A46-Parameters!$D$31)) -> 1.9 | T46: =T45+M46-S46 -> 0 | U46: =S46-N46-O46-Q46 -> 1.9 | V46: =V45+U46 -> 1.6 | W46: =(1-Parameters!$D$7)*(C46-E46)+(1-Parameters!$D$8)*(D46+E46) -> 0 | X46: =Parameters!$D$7*(C46-E46)+Parameters!$D$8*Parameters!$D$9*(D46+E46) -> 0 | Y46: =Parameters!$D$8*(1-Parameters!$D$9)*(D46+E46) -> 0 | Z46: =POWER(1/(1+Parameters!$D$32),A46-1)*(M46-N46) -> 0
A47: 3 | B47: =0 -> 0 | C47: =X46+B47 -> 0 | D47: =Y46 -> 0 | E47: =Parameters!$D$6*C47 -> 0 | F47: =IF(Parameters!$D$5=1,E47,0) -> 0 | G47: =Parameters!$D$27*G46+F47 -> 0 | H47: =IF(AND(Parameters!$D$5=1,Parameters!$D$26=1),SUMPRODUCT(--($A$45:A47<A47),--(MOD(A47-$A$45:A47,Parameters!$D$28)=0),$F$45:F47,POWER(Parameters!$D$27,IF(A47-$A$45:A47=0,1,A47-$A$45:A47))),0) -> 0 | I47: =Parameters!$D$23*I46+B47*Parameters!$D$22 -> 0 | J47: =E47*Parameters!$D$14*(1-Parameters!$D$15) -> 0 | K47: =H47*Parameters!$D$29 -> 0 | L47: =I47*Parameters!$D$24 -> 0 | M47: =J47+K47+L47 -> 0 | N47: =C47*Parameters!$D$17+D47*Parameters!$D$18+E47*Parameters!$D$16+I47*Parameters!$D$25+G47*Parameters!$D$30 -> 0 | O47: =0 -> 0 | P47: =M47-N47-O47 -> 0 | Q47: =0 -> 0 | R47: =P47-Q47 -> 0 | S47: =IF(A47<1+Parameters!$D$31,0,INDEX($M$45:$M$80,A47-Parameters!$D$31)) -> 0 | T47: =T46+M47-S47 -> 0 | U47: =S47-N47-O47-Q47 -> 0 | V47: =V46+U47 -> 1.6 | W47: =(1-Parameters!$D$7)*(C47-E47)+(1-Parameters!$D$8)*(D47+E47) -> 0 | X47: =Parameters!$D$7*(C47-E47)+Parameters!$D$8*Parameters!$D$9*(D47+E47) -> 0 | Y47: =Parameters!$D$8*(1-Parameters!$D$9)*(D47+E47) -> 0 | Z47: =POWER(1/(1+Parameters!$D$32),A47-1)*(M47-N47) -> 0
A48: 4 | B48: =0 -> 0 | C48: =X47+B48 -> 0 | D48: =Y47 -> 0 | E48: =Parameters!$D$6*C48 -> 0 | F48: =IF(Parameters!$D$5=1,E48,0) -> 0 | G48: =Parameters!$D$27*G47+F48 -> 0 | H48: =IF(AND(Parameters!$D$5=1,Parameters!$D$26=1),SUMPRODUCT(--($A$45:A48<A48),--(MOD(A48-$A$45:A48,Parameters!$D$28)=0),$F$45:F48,POWER(Parameters!$D$27,IF(A48-$A$45:A48=0,1,A48-$A$45:A48))),0) -> 0 | I48: =Parameters!$D$23*I47+B48*Parameters!$D$22 -> 0 | J48: =E48*Parameters!$D$14*(1-Parameters!$D$15) -> 0 | K48: =H48*Parameters!$D$29 -> 0 | L48: =I48*Parameters!$D$24 -> 0 | M48: =J48+K48+L48 -> 0 | N48: =C48*Parameters!$D$17+D48*Parameters!$D$18+E48*Parameters!$D$16+I48*Parameters!$D$25+G48*Parameters!$D$30 -> 0 | O48: =0 -> 0 | P48: =M48-N48-O48 -> 0 | Q48: =0 -> 0 | R48: =P48-Q48 -> 0 | S48: =IF(A48<1+Parameters!$D$31,0,INDEX($M$45:$M$80,A48-Parameters!$D$31)) -> 0 | T48: =T47+M48-S48 -> 0 | U48: =S48-N48-O48-Q48 -> 0 | V48: =V47+U48 -> 1.6 | W48: =(1-Parameters!$D$7)*(C48-E48)+(1-Parameters!$D$8)*(D48+E48) -> 0 | X48: =Parameters!$D$7*(C48-E48)+Parameters!$D$8*Parameters!$D$9*(D48+E48) -> 0 | Y48: =Parameters!$D$8*(1-Parameters!$D$9)*(D48+E48) -> 0 | Z48: =POWER(1/(1+Parameters!$D$32),A48-1)*(M48-N48) -> 0
A49: 5 | B49: =0 -> 0 | C49: =X48+B49 -> 0 | D49: =Y48 -> 0 | E49: =Parameters!$D$6*C49 -> 0 | F49: =IF(Parameters!$D$5=1,E49,0) -> 0 | G49: =Parameters!$D$27*G48+F49 -> 0 | H49: =IF(AND(Parameters!$D$5=1,Parameters!$D$26=1),SUMPRODUCT(--($A$45:A49<A49),--(MOD(A49-$A$45:A49,Parameters!$D$28)=0),$F$45:F49,POWER(Parameters!$D$27,IF(A49-$A$45:A49=0,1,A49-$A$45:A49))),0) -> 0 | I49: =Parameters!$D$23*I48+B49*Parameters!$D$22 -> 0 | J49: =E49*Parameters!$D$14*(1-Parameters!$D$15) -> 0 | K49: =H49*Parameters!$D$29 -> 0 | L49: =I49*Parameters!$D$24 -> 0 | M49: =J49+K49+L49 -> 0 | N49: =C49*Parameters!$D$17+D49*Parameters!$D$18+E49*Parameters!$D$16+I49*Parameters!$D$25+G49*Parameters!$D$30 -> 0 | O49: =0 -> 0 | P49: =M49-N49-O49 -> 0 | Q49: =0 -> 0 | R49: =P49-Q49 -> 0 | S49: =IF(A49<1+Parameters!$D$31,0,INDEX($M$45:$M$80,A49-Parameters!$D$31)) -> 0 | T49: =T48+M49-S49 -> 0 | U49: =S49-N49-O49-Q49 -> 0 | V49: =V48+U49 -> 1.6 | W49: =(1-Parameters!$D$7)*(C49-E49)+(1-Parameters!$D$8)*(D49+E49) -> 0 | X49: =Parameters!$D$7*(C49-E49)+Parameters!$D$8*Parameters!$D$9*(D49+E49) -> 0 | Y49: =Parameters!$D$8*(1-Parameters!$D$9)*(D49+E49) -> 0 | Z49: =POWER(1/(1+Parameters!$D$32),A49-1)*(M49-N49) -> 0
A50: 6 | B50: =0 -> 0 | C50: =X49+B50 -> 0 | D50: =Y49 -> 0 | E50: =Parameters!$D$6*C50 -> 0 | F50: =IF(Parameters!$D$5=1,E50,0) -> 0 | G50: =Parameters!$D$27*G49+F50 -> 0 | H50: =IF(AND(Parameters!$D$5=1,Parameters!$D$26=1),SUMPRODUCT(--($A$45:A50<A50),--(MOD(A50-$A$45:A50,Parameters!$D$28)=0),$F$45:F50,POWER(Parameters!$D$27,IF(A50-$A$45:A50=0,1,A50-$A$45:A50))),0) -> 0 | I50: =Parameters!$D$23*I49+B50*Parameters!$D$22 -> 0 | J50: =E50*Parameters!$D$14*(1-Parameters!$D$15) -> 0 | K50: =H50*Parameters!$D$29 -> 0 | L50: =I50*Parameters!$D$24 -> 0 | M50: =J50+K50+L50 -> 0 | N50: =C50*Parameters!$D$17+D50*Parameters!$D$18+E50*Parameters!$D$16+I50*Parameters!$D$25+G50*Parameters!$D$30 -> 0 | O50: =0 -> 0 | P50: =M50-N50-O50 -> 0 | Q50: =0 -> 0 | R50: =P50-Q50 -> 0 | S50: =IF(A50<1+Parameters!$D$31,0,INDEX($M$45:$M$80,A50-Parameters!$D$31)) -> 0 | T50: =T49+M50-S50 -> 0 | U50: =S50-N50-O50-Q50 -> 0 | V50: =V49+U50 -> 1.6 | W50: =(1-Parameters!$D$7)*(C50-E50)+(1-Parameters!$D$8)*(D50+E50) -> 0 | X50: =Parameters!$D$7*(C50-E50)+Parameters!$D$8*Parameters!$D$9*(D50+E50) -> 0 | Y50: =Parameters!$D$8*(1-Parameters!$D$9)*(D50+E50) -> 0 | Z50: =POWER(1/(1+Parameters!$D$32),A50-1)*(M50-N50) -> 0
A51: 7 | B51: =0 -> 0 | C51: =X50+B51 -> 0 | D51: =Y50 -> 0 | E51: =Parameters!$D$6*C51 -> 0 | F51: =IF(Parameters!$D$5=1,E51,0) -> 0 | G51: =Parameters!$D$27*G50+F51 -> 0 | H51: =IF(AND(Parameters!$D$5=1,Parameters!$D$26=1),SUMPRODUCT(--($A$45:A51<A51),--(MOD(A51-$A$45:A51,Parameters!$D$28)=0),$F$45:F51,POWER(Parameters!$D$27,IF(A51-$A$45:A51=0,1,A51-$A$45:A51))),0) -> 0 | I51: =Parameters!$D$23*I50+B51*Parameters!$D$22 -> 0 | J51: =E51*Parameters!$D$14*(1-Parameters!$D$15) -> 0 | K51: =H51*Parameters!$D$29 -> 0 | L51: =I51*Parameters!$D$24 -> 0 | M51: =J51+K51+L51 -> 0 | N51: =C51*Parameters!$D$17+D51*Parameters!$D$18+E51*Parameters!$D$16+I51*Parameters!$D$25+G51*Parameters!$D$30 -> 0 | O51: =0 -> 0 | P51: =M51-N51-O51 -> 0 | Q51: =0 -> 0 | R51: =P51-Q51 -> 0 | S51: =IF(A51<1+Parameters!$D$31,0,INDEX($M$45:$M$80,A51-Parameters!$D$31)) -> 0 | T51: =T50+M51-S51 -> 0 | U51: =S51-N51-O51-Q51 -> 0 | V51: =V50+U51 -> 1.6 | W51: =(1-Parameters!$D$7)*(C51-E51)+(1-Parameters!$D$8)*(D51+E51) -> 0 | X51: =Parameters!$D$7*(C51-E51)+Parameters!$D$8*Parameters!$D$9*(D51+E51) -> 0 | Y51: =Parameters!$D$8*(1-Parameters!$D$9)*(D51+E51) -> 0 | Z51: =POWER(1/(1+Parameters!$D$32),A51-1)*(M51-N51) -> 0
A52: 8 | B52: =0 -> 0 | C52: =X51+B52 -> 0 | D52: =Y51 -> 0 | E52: =Parameters!$D$6*C52 -> 0 | F52: =IF(Parameters!$D$5=1,E52,0) -> 0 | G52: =Parameters!$D$27*G51+F52 -> 0 | H52: =IF(AND(Parameters!$D$5=1,Parameters!$D$26=1),SUMPRODUCT(--($A$45:A52<A52),--(MOD(A52-$A$45:A52,Parameters!$D$28)=0),$F$45:F52,POWER(Parameters!$D$27,IF(A52-$A$45:A52=0,1,A52-$A$45:A52))),0) -> 0 | I52: =Parameters!$D$23*I51+B52*Parameters!$D$22 -> 0 | J52: =E52*Parameters!$D$14*(1-Parameters!$D$15) -> 0 | K52: =H52*Parameters!$D$29 -> 0 | L52: =I52*Parameters!$D$24 -> 0 | M52: =J52+K52+L52 -> 0 | N52: =C52*Parameters!$D$17+D52*Parameters!$D$18+E52*Parameters!$D$16+I52*Parameters!$D$25+G52*Parameters!$D$30 -> 0 | O52: =0 -> 0 | P52: =M52-N52-O52 -> 0 | Q52: =0 -> 0 | R52: =P52-Q52 -> 0 | S52: =IF(A52<1+Parameters!$D$31,0,INDEX($M$45:$M$80,A52-Parameters!$D$31)) -> 0 | T52: =T51+M52-S52 -> 0 | U52: =S52-N52-O52-Q52 -> 0 | V52: =V51+U52 -> 1.6 | W52: =(1-Parameters!$D$7)*(C52-E52)+(1-Parameters!$D$8)*(D52+E52) -> 0 | X52: =Parameters!$D$7*(C52-E52)+Parameters!$D$8*Parameters!$D$9*(D52+E52) -> 0 | Y52: =Parameters!$D$8*(1-Parameters!$D$9)*(D52+E52) -> 0 | Z52: =POWER(1/(1+Parameters!$D$32),A52-1)*(M52-N52) -> 0
A53: 9 | B53: =0 -> 0 | C53: =X52+B53 -> 0 | D53: =Y52 -> 0 | E53: =Parameters!$D$6*C53 -> 0 | F53: =IF(Parameters!$D$5=1,E53,0) -> 0 | G53: =Parameters!$D$27*G52+F53 -> 0 | H53: =IF(AND(Parameters!$D$5=1,Parameters!$D$26=1),SUMPRODUCT(--($A$45:A53<A53),--(MOD(A53-$A$45:A53,Parameters!$D$28)=0),$F$45:F53,POWER(Parameters!$D$27,IF(A53-$A$45:A53=0,1,A53-$A$45:A53))),0) -> 0 | I53: =Parameters!$D$23*I52+B53*Parameters!$D$22 -> 0 | J53: =E53*Parameters!$D$14*(1-Parameters!$D$15) -> 0 | K53: =H53*Parameters!$D$29 -> 0 | L53: =I53*Parameters!$D$24 -> 0 | M53: =J53+K53+L53 -> 0 | N53: =C53*Parameters!$D$17+D53*Parameters!$D$18+E53*Parameters!$D$16+I53*Parameters!$D$25+G53*Parameters!$D$30 -> 0 | O53: =0 -> 0 | P53: =M53-N53-O53 -> 0 | Q53: =0 -> 0 | R53: =P53-Q53 -> 0 | S53: =IF(A53<1+Parameters!$D$31,0,INDEX($M$45:$M$80,A53-Parameters!$D$31)) -> 0 | T53: =T52+M53-S53 -> 0 | U53: =S53-N53-O53-Q53 -> 0 | V53: =V52+U53 -> 1.6 | W53: =(1-Parameters!$D$7)*(C53-E53)+(1-Parameters!$D$8)*(D53+E53) -> 0 | X53: =Parameters!$D$7*(C53-E53)+Parameters!$D$8*Parameters!$D$9*(D53+E53) -> 0 | Y53: =Parameters!$D$8*(1-Parameters!$D$9)*(D53+E53) -> 0 | Z53: =POWER(1/(1+Parameters!$D$32),A53-1)*(M53-N53) -> 0
A54: 10 | B54: =0 -> 0 | C54: =X53+B54 -> 0 | D54: =Y53 -> 0 | E54: =Parameters!$D$6*C54 -> 0 | F54: =IF(Parameters!$D$5=1,E54,0) -> 0 | G54: =Parameters!$D$27*G53+F54 -> 0 | H54: =IF(AND(Parameters!$D$5=1,Parameters!$D$26=1),SUMPRODUCT(--($A$45:A54<A54),--(MOD(A54-$A$45:A54,Parameters!$D$28)=0),$F$45:F54,POWER(Parameters!$D$27,IF(A54-$A$45:A54=0,1,A54-$A$45:A54))),0) -> 0 | I54: =Parameters!$D$23*I53+B54*Parameters!$D$22 -> 0 | J54: =E54*Parameters!$D$14*(1-Parameters!$D$15) -> 0 | K54: =H54*Parameters!$D$29 -> 0 | L54: =I54*Parameters!$D$24 -> 0 | M54: =J54+K54+L54 -> 0 | N54: =C54*Parameters!$D$17+D54*Parameters!$D$18+E54*Parameters!$D$16+I54*Parameters!$D$25+G54*Parameters!$D$30 -> 0 | O54: =0 -> 0 | P54: =M54-N54-O54 -> 0 | Q54: =0 -> 0 | R54: =P54-Q54 -> 0 | S54: =IF(A54<1+Parameters!$D$31,0,INDEX($M$45:$M$80,A54-Parameters!$D$31)) -> 0 | T54: =T53+M54-S54 -> 0 | U54: =S54-N54-O54-Q54 -> 0 | V54: =V53+U54 -> 1.6 | W54: =(1-Parameters!$D$7)*(C54-E54)+(1-Parameters!$D$8)*(D54+E54) -> 0 | X54: =Parameters!$D$7*(C54-E54)+Parameters!$D$8*Parameters!$D$9*(D54+E54) -> 0 | Y54: =Parameters!$D$8*(1-Parameters!$D$9)*(D54+E54) -> 0 | Z54: =POWER(1/(1+Parameters!$D$32),A54-1)*(M54-N54) -> 0
A55: 11 | B55: =0 -> 0 | C55: =X54+B55 -> 0 | D55: =Y54 -> 0 | E55: =Parameters!$D$6*C55 -> 0 | F55: =IF(Parameters!$D$5=1,E55,0) -> 0 | G55: =Parameters!$D$27*G54+F55 -> 0 | H55: =IF(AND(Parameters!$D$5=1,Parameters!$D$26=1),SUMPRODUCT(--($A$45:A55<A55),--(MOD(A55-$A$45:A55,Parameters!$D$28)=0),$F$45:F55,POWER(Parameters!$D$27,IF(A55-$A$45:A55=0,1,A55-$A$45:A55))),0) -> 0 | I55: =Parameters!$D$23*I54+B55*Parameters!$D$22 -> 0 | J55: =E55*Parameters!$D$14*(1-Parameters!$D$15) -> 0 | K55: =H55*Parameters!$D$29 -> 0 | L55: =I55*Parameters!$D$24 -> 0 | M55: =J55+K55+L55 -> 0 | N55: =C55*Parameters!$D$17+D55*Parameters!$D$18+E55*Parameters!$D$16+I55*Parameters!$D$25+G55*Parameters!$D$30 -> 0 | O55: =0 -> 0 | P55: =M55-N55-O55 -> 0 | Q55: =0 -> 0 | R55: =P55-Q55 -> 0 | S55: =IF(A55<1+Parameters!$D$31,0,INDEX($M$45:$M$80,A55-Parameters!$D$31)) -> 0 | T55: =T54+M55-S55 -> 0 | U55: =S55-N55-O55-Q55 -> 0 | V55: =V54+U55 -> 1.6 | W55: =(1-Parameters!$D$7)*(C55-E55)+(1-Parameters!$D$8)*(D55+E55) -> 0 | X55: =Parameters!$D$7*(C55-E55)+Parameters!$D$8*Parameters!$D$9*(D55+E55) -> 0 | Y55: =Parameters!$D$8*(1-Parameters!$D$9)*(D55+E55) -> 0 | Z55: =POWER(1/(1+Parameters!$D$32),A55-1)*(M55-N55) -> 0
A56: 12 | B56: =0 -> 0 | C56: =X55+B56 -> 0 | D56: =Y55 -> 0 | E56: =Parameters!$D$6*C56 -> 0 | F56: =IF(Parameters!$D$5=1,E56,0) -> 0 | G56: =Parameters!$D$27*G55+F56 -> 0 | H56: =IF(AND(Parameters!$D$5=1,Parameters!$D$26=1),SUMPRODUCT(--($A$45:A56<A56),--(MOD(A56-$A$45:A56,Parameters!$D$28)=0),$F$45:F56,POWER(Parameters!$D$27,IF(A56-$A$45:A56=0,1,A56-$A$45:A56))),0) -> 0 | I56: =Parameters!$D$23*I55+B56*Parameters!$D$22 -> 0 | J56: =E56*Parameters!$D$14*(1-Parameters!$D$15) -> 0 | K56: =H56*Parameters!$D$29 -> 0 | L56: =I56*Parameters!$D$24 -> 0 | M56: =J56+K56+L56 -> 0 | N56: =C56*Parameters!$D$17+D56*Parameters!$D$18+E56*Parameters!$D$16+I56*Parameters!$D$25+G56*Parameters!$D$30 -> 0 | O56: =0 -> 0 | P56: =M56-N56-O56 -> 0 | Q56: =0 -> 0 | R56: =P56-Q56 -> 0 | S56: =IF(A56<1+Parameters!$D$31,0,INDEX($M$45:$M$80,A56-Parameters!$D$31)) -> 0 | T56: =T55+M56-S56 -> 0 | U56: =S56-N56-O56-Q56 -> 0 | V56: =V55+U56 -> 1.6 | W56: =(1-Parameters!$D$7)*(C56-E56)+(1-Parameters!$D$8)*(D56+E56) -> 0 | X56: =Parameters!$D$7*(C56-E56)+Parameters!$D$8*Parameters!$D$9*(D56+E56) -> 0 | Y56: =Parameters!$D$8*(1-Parameters!$D$9)*(D56+E56) -> 0 | Z56: =POWER(1/(1+Parameters!$D$32),A56-1)*(M56-N56) -> 0
A57: 13 | B57: =0 -> 0 | C57: =X56+B57 -> 0 | D57: =Y56 -> 0 | E57: =Parameters!$D$6*C57 -> 0 | F57: =IF(Parameters!$D$5=1,E57,0) -> 0 | G57: =Parameters!$D$27*G56+F57 -> 0 | H57: =IF(AND(Parameters!$D$5=1,Parameters!$D$26=1),SUMPRODUCT(--($A$45:A57<A57),--(MOD(A57-$A$45:A57,Parameters!$D$28)=0),$F$45:F57,POWER(Parameters!$D$27,IF(A57-$A$45:A57=0,1,A57-$A$45:A57))),0) -> 0 | I57: =Parameters!$D$23*I56+B57*Parameters!$D$22 -> 0 | J57: =E57*Parameters!$D$14*(1-Parameters!$D$15) -> 0 | K57: =H57*Parameters!$D$29 -> 0 | L57: =I57*Parameters!$D$24 -> 0 | M57: =J57+K57+L57 -> 0 | N57: =C57*Parameters!$D$17+D57*Parameters!$D$18+E57*Parameters!$D$16+I57*Parameters!$D$25+G57*Parameters!$D$30 -> 0 | O57: =0 -> 0 | P57: =M57-N57-O57 -> 0 | Q57: =0 -> 0 | R57: =P57-Q57 -> 0 | S57: =IF(A57<1+Parameters!$D$31,0,INDEX($M$45:$M$80,A57-Parameters!$D$31)) -> 0 | T57: =T56+M57-S57 -> 0 | U57: =S57-N57-O57-Q57 -> 0 | V57: =V56+U57 -> 1.6 | W57: =(1-Parameters!$D$7)*(C57-E57)+(1-Parameters!$D$8)*(D57+E57) -> 0 | X57: =Parameters!$D$7*(C57-E57)+Parameters!$D$8*Parameters!$D$9*(D57+E57) -> 0 | Y57: =Parameters!$D$8*(1-Parameters!$D$9)*(D57+E57) -> 0 | Z57: =POWER(1/(1+Parameters!$D$32),A57-1)*(M57-N57) -> 0
... A80: 36 | B80: =0 -> 0 | C80: =X79+B80 -> 0 | D80: =Y79 -> 0 | E80: =Parameters!$D$6*C80 -> 0 | F80: =IF(Parameters!$D$5=1,E80,0) -> 0 | G80: =Parameters!$D$27*G79+F80 -> 0 | H80: =IF(AND(Parameters!$D$5=1,Parameters!$D$26=1),SUMPRODUCT(--($A$45:A80<A80),--(MOD(A80-$A$45:A80,Parameters!$D$28)=0),$F$45:F80,POWER(Parameters!$D$27,IF(A80-$A$45:A80=0,1,A80-$A$45:A80))),0) -> 0 | I80: =Parameters!$D$23*I79+B80*Parameters!$D$22 -> 0 | J80: =E80*Parameters!$D$14*(1-Parameters!$D$15) -> 0 | K80: =H80*Parameters!$D$29 -> 0 | L80: =I80*Parameters!$D$24 -> 0 | M80: =J80+K80+L80 -> 0 | N80: =C80*Parameters!$D$17+D80*Parameters!$D$18+E80*Parameters!$D$16+I80*Parameters!$D$25+G80*Parameters!$D$30 -> 0 | O80: =0 -> 0 | P80: =M80-N80-O80 -> 0 | Q80: =0 -> 0 | R80: =P80-Q80 -> 0 | S80: =IF(A80<1+Parameters!$D$31,0,INDEX($M$45:$M$80,A80-Parameters!$D$31)) -> 0 | T80: =T79+M80-S80 -> 0 | U80: =S80-N80-O80-Q80 -> 0 | V80: =V79+U80 -> 1.6 | W80: =(1-Parameters!$D$7)*(C80-E80)+(1-Parameters!$D$8)*(D80+E80) -> 0 | X80: =Parameters!$D$7*(C80-E80)+Parameters!$D$8*Parameters!$D$9*(D80+E80) -> 0 | Y80: =Parameters!$D$8*(1-Parameters!$D$9)*(D80+E80) -> 0 | Z80: =POWER(1/(1+Parameters!$D$32),A80-1)*(M80-N80) -> 0

Sheet S2
A1: S2 — Retain after first lead only
A2: All parameters are illustrative. Top block: calendar cohorts. Lower block: one acquired owner, no CAC/fixed cost, for customer-value calculation.
A4: Month | B4: Acquired | C4: E eligible | D4: M completed active | E4: Payable events | F4: New policies | G4: Active policies | H4: Renewed policies | I4: Billed subscribers | J4: Initial revenue | K4: Renewal revenue | L4: Software revenue | M4: Total revenue | N4: Variable cost | O4: Acquisition cost | P4: Contribution | Q4: Fixed cost | R4: Operating result | S4: Cash receipts | T4: Receivables | U4: Cash surplus | V4: Cumulative cash | W4: Churned opportunity owners | X4: Next E | Y4: Next M | Z4: Discounted contribution before CAC
A5: 1 | B5: =Parameters!$E$20 -> 1000 | C5: =B5 -> 1000 | D5: =0 -> 0 | E5: =Parameters!$E$6*C5 -> 100 | F5: =IF(Parameters!$E$5=1,E5,0) -> 0 | G5: =F5 -> 0 | H5: =IF(AND(Parameters!$E$5=1,Parameters!$E$26=1),SUMPRODUCT(--($A$5:A5<A5),--(MOD(A5-$A$5:A5,Parameters!$E$28)=0),$F$5:F5,POWER(Parameters!$E$27,IF(A5-$A$5:A5=0,1,A5-$A$5:A5))),0) -> 0 | I5: =B5*Parameters!$E$22 -> 0 | J5: =E5*Parameters!$E$14*(1-Parameters!$E$15) -> 1900 | K5: =H5*Parameters!$E$29 -> 0 | L5: =I5*Parameters!$E$24 -> 0 | M5: =J5+K5+L5 -> 1900 | N5: =C5*Parameters!$E$17+D5*Parameters!$E$18+E5*Parameters!$E$16+I5*Parameters!$E$25+G5*Parameters!$E$30 -> 300 | O5: =B5*Parameters!$E$19 -> 4000 | P5: =M5-N5-O5 -> -2400 | Q5: =Parameters!$E$21 -> 1000 | R5: =P5-Q5 -> -3400 | S5: =IF(A5<1+Parameters!$E$31,0,INDEX($M$5:$M$40,A5-Parameters!$E$31)) -> 0 | T5: =M5-S5 -> 1900 | U5: =S5-N5-O5-Q5 -> -5300 | V5: =U5 -> -5300 | W5: =(1-Parameters!$E$7)*(C5-E5)+(1-Parameters!$E$8)*(D5+E5) -> 920 | X5: =Parameters!$E$7*(C5-E5)+Parameters!$E$8*Parameters!$E$9*(D5+E5) -> 0 | Y5: =Parameters!$E$8*(1-Parameters!$E$9)*(D5+E5) -> 80 | Z5: =POWER(1/(1+Parameters!$E$32),A5-1)*(M5-N5) -> 1600
A6: 2 | B6: =Parameters!$E$20 -> 1000 | C6: =X5+B6 -> 1000 | D6: =Y5 -> 80 | E6: =Parameters!$E$6*C6 -> 100 | F6: =IF(Parameters!$E$5=1,E6,0) -> 0 | G6: =Parameters!$E$27*G5+F6 -> 0 | H6: =IF(AND(Parameters!$E$5=1,Parameters!$E$26=1),SUMPRODUCT(--($A$5:A6<A6),--(MOD(A6-$A$5:A6,Parameters!$E$28)=0),$F$5:F6,POWER(Parameters!$E$27,IF(A6-$A$5:A6=0,1,A6-$A$5:A6))),0) -> 0 | I6: =Parameters!$E$23*I5+B6*Parameters!$E$22 -> 0 | J6: =E6*Parameters!$E$14*(1-Parameters!$E$15) -> 1900 | K6: =H6*Parameters!$E$29 -> 0 | L6: =I6*Parameters!$E$24 -> 0 | M6: =J6+K6+L6 -> 1900 | N6: =C6*Parameters!$E$17+D6*Parameters!$E$18+E6*Parameters!$E$16+I6*Parameters!$E$25+G6*Parameters!$E$30 -> 324 | O6: =B6*Parameters!$E$19 -> 4000 | P6: =M6-N6-O6 -> -2424 | Q6: =Parameters!$E$21 -> 1000 | R6: =P6-Q6 -> -3424 | S6: =IF(A6<1+Parameters!$E$31,0,INDEX($M$5:$M$40,A6-Parameters!$E$31)) -> 1900 | T6: =T5+M6-S6 -> 1900 | U6: =S6-N6-O6-Q6 -> -3424 | V6: =V5+U6 -> -8724 | W6: =(1-Parameters!$E$7)*(C6-E6)+(1-Parameters!$E$8)*(D6+E6) -> 936 | X6: =Parameters!$E$7*(C6-E6)+Parameters!$E$8*Parameters!$E$9*(D6+E6) -> 0 | Y6: =Parameters!$E$8*(1-Parameters!$E$9)*(D6+E6) -> 144 | Z6: =POWER(1/(1+Parameters!$E$32),A6-1)*(M6-N6) -> 1560.396
A7: 3 | B7: =Parameters!$E$20 -> 1000 | C7: =X6+B7 -> 1000 | D7: =Y6 -> 144 | E7: =Parameters!$E$6*C7 -> 100 | F7: =IF(Parameters!$E$5=1,E7,0) -> 0 | G7: =Parameters!$E$27*G6+F7 -> 0 | H7: =IF(AND(Parameters!$E$5=1,Parameters!$E$26=1),SUMPRODUCT(--($A$5:A7<A7),--(MOD(A7-$A$5:A7,Parameters!$E$28)=0),$F$5:F7,POWER(Parameters!$E$27,IF(A7-$A$5:A7=0,1,A7-$A$5:A7))),0) -> 0 | I7: =Parameters!$E$23*I6+B7*Parameters!$E$22 -> 0 | J7: =E7*Parameters!$E$14*(1-Parameters!$E$15) -> 1900 | K7: =H7*Parameters!$E$29 -> 0 | L7: =I7*Parameters!$E$24 -> 0 | M7: =J7+K7+L7 -> 1900 | N7: =C7*Parameters!$E$17+D7*Parameters!$E$18+E7*Parameters!$E$16+I7*Parameters!$E$25+G7*Parameters!$E$30 -> 343.2 | O7: =B7*Parameters!$E$19 -> 4000 | P7: =M7-N7-O7 -> -2443.2 | Q7: =Parameters!$E$21 -> 1000 | R7: =P7-Q7 -> -3443.2 | S7: =IF(A7<1+Parameters!$E$31,0,INDEX($M$5:$M$40,A7-Parameters!$E$31)) -> 1900 | T7: =T6+M7-S7 -> 1900 | U7: =S7-N7-O7-Q7 -> -3443.2 | V7: =V6+U7 -> -12167.2 | W7: =(1-Parameters!$E$7)*(C7-E7)+(1-Parameters!$E$8)*(D7+E7) -> 948.8 | X7: =Parameters!$E$7*(C7-E7)+Parameters!$E$8*Parameters!$E$9*(D7+E7) -> 0 | Y7: =Parameters!$E$8*(1-Parameters!$E$9)*(D7+E7) -> 195.2 | Z7: =POWER(1/(1+Parameters!$E$32),A7-1)*(M7-N7) -> 1526.1249
A8: 4 | B8: =Parameters!$E$20 -> 1000 | C8: =X7+B8 -> 1000 | D8: =Y7 -> 195.2 | E8: =Parameters!$E$6*C8 -> 100 | F8: =IF(Parameters!$E$5=1,E8,0) -> 0 | G8: =Parameters!$E$27*G7+F8 -> 0 | H8: =IF(AND(Parameters!$E$5=1,Parameters!$E$26=1),SUMPRODUCT(--($A$5:A8<A8),--(MOD(A8-$A$5:A8,Parameters!$E$28)=0),$F$5:F8,POWER(Parameters!$E$27,IF(A8-$A$5:A8=0,1,A8-$A$5:A8))),0) -> 0 | I8: =Parameters!$E$23*I7+B8*Parameters!$E$22 -> 0 | J8: =E8*Parameters!$E$14*(1-Parameters!$E$15) -> 1900 | K8: =H8*Parameters!$E$29 -> 0 | L8: =I8*Parameters!$E$24 -> 0 | M8: =J8+K8+L8 -> 1900 | N8: =C8*Parameters!$E$17+D8*Parameters!$E$18+E8*Parameters!$E$16+I8*Parameters!$E$25+G8*Parameters!$E$30 -> 358.56 | O8: =B8*Parameters!$E$19 -> 4000 | P8: =M8-N8-O8 -> -2458.56 | Q8: =Parameters!$E$21 -> 1000 | R8: =P8-Q8 -> -3458.56 | S8: =IF(A8<1+Parameters!$E$31,0,INDEX($M$5:$M$40,A8-Parameters!$E$31)) -> 1900 | T8: =T7+M8-S8 -> 1900 | U8: =S8-N8-O8-Q8 -> -3458.56 | V8: =V7+U8 -> -15625.76 | W8: =(1-Parameters!$E$7)*(C8-E8)+(1-Parameters!$E$8)*(D8+E8) -> 959.04 | X8: =Parameters!$E$7*(C8-E8)+Parameters!$E$8*Parameters!$E$9*(D8+E8) -> 0 | Y8: =Parameters!$E$8*(1-Parameters!$E$9)*(D8+E8) -> 236.16 | Z8: =POWER(1/(1+Parameters!$E$32),A8-1)*(M8-N8) -> 1496.1065
A9: 5 | B9: =Parameters!$E$20 -> 1000 | C9: =X8+B9 -> 1000 | D9: =Y8 -> 236.16 | E9: =Parameters!$E$6*C9 -> 100 | F9: =IF(Parameters!$E$5=1,E9,0) -> 0 | G9: =Parameters!$E$27*G8+F9 -> 0 | H9: =IF(AND(Parameters!$E$5=1,Parameters!$E$26=1),SUMPRODUCT(--($A$5:A9<A9),--(MOD(A9-$A$5:A9,Parameters!$E$28)=0),$F$5:F9,POWER(Parameters!$E$27,IF(A9-$A$5:A9=0,1,A9-$A$5:A9))),0) -> 0 | I9: =Parameters!$E$23*I8+B9*Parameters!$E$22 -> 0 | J9: =E9*Parameters!$E$14*(1-Parameters!$E$15) -> 1900 | K9: =H9*Parameters!$E$29 -> 0 | L9: =I9*Parameters!$E$24 -> 0 | M9: =J9+K9+L9 -> 1900 | N9: =C9*Parameters!$E$17+D9*Parameters!$E$18+E9*Parameters!$E$16+I9*Parameters!$E$25+G9*Parameters!$E$30 -> 370.848 | O9: =B9*Parameters!$E$19 -> 4000 | P9: =M9-N9-O9 -> -2470.848 | Q9: =Parameters!$E$21 -> 1000 | R9: =P9-Q9 -> -3470.848 | S9: =IF(A9<1+Parameters!$E$31,0,INDEX($M$5:$M$40,A9-Parameters!$E$31)) -> 1900 | T9: =T8+M9-S9 -> 1900 | U9: =S9-N9-O9-Q9 -> -3470.848 | V9: =V8+U9 -> -19096.608 | W9: =(1-Parameters!$E$7)*(C9-E9)+(1-Parameters!$E$8)*(D9+E9) -> 967.232 | X9: =Parameters!$E$7*(C9-E9)+Parameters!$E$8*Parameters!$E$9*(D9+E9) -> 0 | Y9: =Parameters!$E$8*(1-Parameters!$E$9)*(D9+E9) -> 268.928 | Z9: =POWER(1/(1+Parameters!$E$32),A9-1)*(M9-N9) -> 1469.485
A10: 6 | B10: =Parameters!$E$20 -> 1000 | C10: =X9+B10 -> 1000 | D10: =Y9 -> 268.928 | E10: =Parameters!$E$6*C10 -> 100 | F10: =IF(Parameters!$E$5=1,E10,0) -> 0 | G10: =Parameters!$E$27*G9+F10 -> 0 | H10: =IF(AND(Parameters!$E$5=1,Parameters!$E$26=1),SUMPRODUCT(--($A$5:A10<A10),--(MOD(A10-$A$5:A10,Parameters!$E$28)=0),$F$5:F10,POWER(Parameters!$E$27,IF(A10-$A$5:A10=0,1,A10-$A$5:A10))),0) -> 0 | I10: =Parameters!$E$23*I9+B10*Parameters!$E$22 -> 0 | J10: =E10*Parameters!$E$14*(1-Parameters!$E$15) -> 1900 | K10: =H10*Parameters!$E$29 -> 0 | L10: =I10*Parameters!$E$24 -> 0 | M10: =J10+K10+L10 -> 1900 | N10: =C10*Parameters!$E$17+D10*Parameters!$E$18+E10*Parameters!$E$16+I10*Parameters!$E$25+G10*Parameters!$E$30 -> 380.6784 | O10: =B10*Parameters!$E$19 -> 4000 | P10: =M10-N10-O10 -> -2480.6784 | Q10: =Parameters!$E$21 -> 1000 | R10: =P10-Q10 -> -3480.6784 | S10: =IF(A10<1+Parameters!$E$31,0,INDEX($M$5:$M$40,A10-Parameters!$E$31)) -> 1900 | T10: =T9+M10-S10 -> 1900 | U10: =S10-N10-O10-Q10 -> -3480.6784 | V10: =V9+U10 -> -22577.286 | W10: =(1-Parameters!$E$7)*(C10-E10)+(1-Parameters!$E$8)*(D10+E10) -> 973.7856 | X10: =Parameters!$E$7*(C10-E10)+Parameters!$E$8*Parameters!$E$9*(D10+E10) -> 0 | Y10: =Parameters!$E$8*(1-Parameters!$E$9)*(D10+E10) -> 295.1424 | Z10: =POWER(1/(1+Parameters!$E$32),A10-1)*(M10-N10) -> 1445.5824
A11: 7 | B11: =Parameters!$E$20 -> 1000 | C11: =X10+B11 -> 1000 | D11: =Y10 -> 295.1424 | E11: =Parameters!$E$6*C11 -> 100 | F11: =IF(Parameters!$E$5=1,E11,0) -> 0 | G11: =Parameters!$E$27*G10+F11 -> 0 | H11: =IF(AND(Parameters!$E$5=1,Parameters!$E$26=1),SUMPRODUCT(--($A$5:A11<A11),--(MOD(A11-$A$5:A11,Parameters!$E$28)=0),$F$5:F11,POWER(Parameters!$E$27,IF(A11-$A$5:A11=0,1,A11-$A$5:A11))),0) -> 0 | I11: =Parameters!$E$23*I10+B11*Parameters!$E$22 -> 0 | J11: =E11*Parameters!$E$14*(1-Parameters!$E$15) -> 1900 | K11: =H11*Parameters!$E$29 -> 0 | L11: =I11*Parameters!$E$24 -> 0 | M11: =J11+K11+L11 -> 1900 | N11: =C11*Parameters!$E$17+D11*Parameters!$E$18+E11*Parameters!$E$16+I11*Parameters!$E$25+G11*Parameters!$E$30 -> 388.54272 | O11: =B11*Parameters!$E$19 -> 4000 | P11: =M11-N11-O11 -> -2488.5427 | Q11: =Parameters!$E$21 -> 1000 | R11: =P11-Q11 -> -3488.5427 | S11: =IF(A11<1+Parameters!$E$31,0,INDEX($M$5:$M$40,A11-Parameters!$E$31)) -> 1900 | T11: =T10+M11-S11 -> 1900 | U11: =S11-N11-O11-Q11 -> -3488.5427 | V11: =V10+U11 -> -26065.829 | W11: =(1-Parameters!$E$7)*(C11-E11)+(1-Parameters!$E$8)*(D11+E11) -> 979.02848 | X11: =Parameters!$E$7*(C11-E11)+Parameters!$E$8*Parameters!$E$9*(D11+E11) -> 0 | Y11: =Parameters!$E$8*(1-Parameters!$E$9)*(D11+E11) -> 316.11392 | Z11: =POWER(1/(1+Parameters!$E$32),A11-1)*(M11-N11) -> 1423.8611
A12: 8 | B12: =Parameters!$E$20 -> 1000 | C12: =X11+B12 -> 1000 | D12: =Y11 -> 316.11392 | E12: =Parameters!$E$6*C12 -> 100 | F12: =IF(Parameters!$E$5=1,E12,0) -> 0 | G12: =Parameters!$E$27*G11+F12 -> 0 | H12: =IF(AND(Parameters!$E$5=1,Parameters!$E$26=1),SUMPRODUCT(--($A$5:A12<A12),--(MOD(A12-$A$5:A12,Parameters!$E$28)=0),$F$5:F12,POWER(Parameters!$E$27,IF(A12-$A$5:A12=0,1,A12-$A$5:A12))),0) -> 0 | I12: =Parameters!$E$23*I11+B12*Parameters!$E$22 -> 0 | J12: =E12*Parameters!$E$14*(1-Parameters!$E$15) -> 1900 | K12: =H12*Parameters!$E$29 -> 0 | L12: =I12*Parameters!$E$24 -> 0 | M12: =J12+K12+L12 -> 1900 | N12: =C12*Parameters!$E$17+D12*Parameters!$E$18+E12*Parameters!$E$16+I12*Parameters!$E$25+G12*Parameters!$E$30 -> 394.83418 | O12: =B12*Parameters!$E$19 -> 4000 | P12: =M12-N12-O12 -> -2494.8342 | Q12: =Parameters!$E$21 -> 1000 | R12: =P12-Q12 -> -3494.8342 | S12: =IF(A12<1+Parameters!$E$31,0,INDEX($M$5:$M$40,A12-Parameters!$E$31)) -> 1900 | T12: =T11+M12-S12 -> 1900 | U12: =S12-N12-O12-Q12 -> -3494.8342 | V12: =V11+U12 -> -29560.663 | W12: =(1-Parameters!$E$7)*(C12-E12)+(1-Parameters!$E$8)*(D12+E12) -> 983.22278 | X12: =Parameters!$E$7*(C12-E12)+Parameters!$E$8*Parameters!$E$9*(D12+E12) -> 0 | Y12: =Parameters!$E$8*(1-Parameters!$E$9)*(D12+E12) -> 332.89114 | Z12: =POWER(1/(1+Parameters!$E$32),A12-1)*(M12-N12) -> 1403.8953
A13: 9 | B13: =Parameters!$E$20 -> 1000 | C13: =X12+B13 -> 1000 | D13: =Y12 -> 332.89114 | E13: =Parameters!$E$6*C13 -> 100 | F13: =IF(Parameters!$E$5=1,E13,0) -> 0 | G13: =Parameters!$E$27*G12+F13 -> 0 | H13: =IF(AND(Parameters!$E$5=1,Parameters!$E$26=1),SUMPRODUCT(--($A$5:A13<A13),--(MOD(A13-$A$5:A13,Parameters!$E$28)=0),$F$5:F13,POWER(Parameters!$E$27,IF(A13-$A$5:A13=0,1,A13-$A$5:A13))),0) -> 0 | I13: =Parameters!$E$23*I12+B13*Parameters!$E$22 -> 0 | J13: =E13*Parameters!$E$14*(1-Parameters!$E$15) -> 1900 | K13: =H13*Parameters!$E$29 -> 0 | L13: =I13*Parameters!$E$24 -> 0 | M13: =J13+K13+L13 -> 1900 | N13: =C13*Parameters!$E$17+D13*Parameters!$E$18+E13*Parameters!$E$16+I13*Parameters!$E$25+G13*Parameters!$E$30 -> 399.86734 | O13: =B13*Parameters!$E$19 -> 4000 | P13: =M13-N13-O13 -> -2499.8673 | Q13: =Parameters!$E$21 -> 1000 | R13: =P13-Q13 -> -3499.8673 | S13: =IF(A13<1+Parameters!$E$31,0,INDEX($M$5:$M$40,A13-Parameters!$E$31)) -> 1900 | T13: =T12+M13-S13 -> 1900 | U13: =S13-N13-O13-Q13 -> -3499.8673 | V13: =V12+U13 -> -33060.531 | W13: =(1-Parameters!$E$7)*(C13-E13)+(1-Parameters!$E$8)*(D13+E13) -> 986.57823 | X13: =Parameters!$E$7*(C13-E13)+Parameters!$E$8*Parameters!$E$9*(D13+E13) -> 0 | Y13: =Parameters!$E$8*(1-Parameters!$E$9)*(D13+E13) -> 346.31291 | Z13: =POWER(1/(1+Parameters!$E$32),A13-1)*(M13-N13) -> 1385.3473
A14: 10 | B14: =Parameters!$E$20 -> 1000 | C14: =X13+B14 -> 1000 | D14: =Y13 -> 346.31291 | E14: =Parameters!$E$6*C14 -> 100 | F14: =IF(Parameters!$E$5=1,E14,0) -> 0 | G14: =Parameters!$E$27*G13+F14 -> 0 | H14: =IF(AND(Parameters!$E$5=1,Parameters!$E$26=1),SUMPRODUCT(--($A$5:A14<A14),--(MOD(A14-$A$5:A14,Parameters!$E$28)=0),$F$5:F14,POWER(Parameters!$E$27,IF(A14-$A$5:A14=0,1,A14-$A$5:A14))),0) -> 0 | I14: =Parameters!$E$23*I13+B14*Parameters!$E$22 -> 0 | J14: =E14*Parameters!$E$14*(1-Parameters!$E$15) -> 1900 | K14: =H14*Parameters!$E$29 -> 0 | L14: =I14*Parameters!$E$24 -> 0 | M14: =J14+K14+L14 -> 1900 | N14: =C14*Parameters!$E$17+D14*Parameters!$E$18+E14*Parameters!$E$16+I14*Parameters!$E$25+G14*Parameters!$E$30 -> 403.89387 | O14: =B14*Parameters!$E$19 -> 4000 | P14: =M14-N14-O14 -> -2503.8939 | Q14: =Parameters!$E$21 -> 1000 | R14: =P14-Q14 -> -3503.8939 | S14: =IF(A14<1+Parameters!$E$31,0,INDEX($M$5:$M$40,A14-Parameters!$E$31)) -> 1900 | T14: =T13+M14-S14 -> 1900 | U14: =S14-N14-O14-Q14 -> -3503.8939 | V14: =V13+U14 -> -36564.425 | W14: =(1-Parameters!$E$7)*(C14-E14)+(1-Parameters!$E$8)*(D14+E14) -> 989.26258 | X14: =Parameters!$E$7*(C14-E14)+Parameters!$E$8*Parameters!$E$9*(D14+E14) -> 0 | Y14: =Parameters!$E$8*(1-Parameters!$E$9)*(D14+E14) -> 357.05033 | Z14: =POWER(1/(1+Parameters!$E$32),A14-1)*(M14-N14) -> 1367.9494
A15: 11 | B15: =Parameters!$E$20 -> 1000 | C15: =X14+B15 -> 1000 | D15: =Y14 -> 357.05033 | E15: =Parameters!$E$6*C15 -> 100 | F15: =IF(Parameters!$E$5=1,E15,0) -> 0 | G15: =Parameters!$E$27*G14+F15 -> 0 | H15: =IF(AND(Parameters!$E$5=1,Parameters!$E$26=1),SUMPRODUCT(--($A$5:A15<A15),--(MOD(A15-$A$5:A15,Parameters!$E$28)=0),$F$5:F15,POWER(Parameters!$E$27,IF(A15-$A$5:A15=0,1,A15-$A$5:A15))),0) -> 0 | I15: =Parameters!$E$23*I14+B15*Parameters!$E$22 -> 0 | J15: =E15*Parameters!$E$14*(1-Parameters!$E$15) -> 1900 | K15: =H15*Parameters!$E$29 -> 0 | L15: =I15*Parameters!$E$24 -> 0 | M15: =J15+K15+L15 -> 1900 | N15: =C15*Parameters!$E$17+D15*Parameters!$E$18+E15*Parameters!$E$16+I15*Parameters!$E$25+G15*Parameters!$E$30 -> 407.1151 | O15: =B15*Parameters!$E$19 -> 4000 | P15: =M15-N15-O15 -> -2507.1151 | Q15: =Parameters!$E$21 -> 1000 | R15: =P15-Q15 -> -3507.1151 | S15: =IF(A15<1+Parameters!$E$31,0,INDEX($M$5:$M$40,A15-Parameters!$E$31)) -> 1900 | T15: =T14+M15-S15 -> 1900 | U15: =S15-N15-O15-Q15 -> -3507.1151 | V15: =V14+U15 -> -40071.54 | W15: =(1-Parameters!$E$7)*(C15-E15)+(1-Parameters!$E$8)*(D15+E15) -> 991.41007 | X15: =Parameters!$E$7*(C15-E15)+Parameters!$E$8*Parameters!$E$9*(D15+E15) -> 0 | Y15: =Parameters!$E$8*(1-Parameters!$E$9)*(D15+E15) -> 365.64026 | Z15: =POWER(1/(1+Parameters!$E$32),A15-1)*(M15-N15) -> 1351.4892
A16: 12 | B16: =Parameters!$E$20 -> 1000 | C16: =X15+B16 -> 1000 | D16: =Y15 -> 365.64026 | E16: =Parameters!$E$6*C16 -> 100 | F16: =IF(Parameters!$E$5=1,E16,0) -> 0 | G16: =Parameters!$E$27*G15+F16 -> 0 | H16: =IF(AND(Parameters!$E$5=1,Parameters!$E$26=1),SUMPRODUCT(--($A$5:A16<A16),--(MOD(A16-$A$5:A16,Parameters!$E$28)=0),$F$5:F16,POWER(Parameters!$E$27,IF(A16-$A$5:A16=0,1,A16-$A$5:A16))),0) -> 0 | I16: =Parameters!$E$23*I15+B16*Parameters!$E$22 -> 0 | J16: =E16*Parameters!$E$14*(1-Parameters!$E$15) -> 1900 | K16: =H16*Parameters!$E$29 -> 0 | L16: =I16*Parameters!$E$24 -> 0 | M16: =J16+K16+L16 -> 1900 | N16: =C16*Parameters!$E$17+D16*Parameters!$E$18+E16*Parameters!$E$16+I16*Parameters!$E$25+G16*Parameters!$E$30 -> 409.69208 | O16: =B16*Parameters!$E$19 -> 4000 | P16: =M16-N16-O16 -> -2509.6921 | Q16: =Parameters!$E$21 -> 1000 | R16: =P16-Q16 -> -3509.6921 | S16: =IF(A16<1+Parameters!$E$31,0,INDEX($M$5:$M$40,A16-Parameters!$E$31)) -> 1900 | T16: =T15+M16-S16 -> 1900 | U16: =S16-N16-O16-Q16 -> -3509.6921 | V16: =V15+U16 -> -43581.232 | W16: =(1-Parameters!$E$7)*(C16-E16)+(1-Parameters!$E$8)*(D16+E16) -> 993.12805 | X16: =Parameters!$E$7*(C16-E16)+Parameters!$E$8*Parameters!$E$9*(D16+E16) -> 0 | Y16: =Parameters!$E$8*(1-Parameters!$E$9)*(D16+E16) -> 372.51221 | Z16: =POWER(1/(1+Parameters!$E$32),A16-1)*(M16-N16) -> 1335.7983
A17: 13 | B17: =Parameters!$E$20 -> 1000 | C17: =X16+B17 -> 1000 | D17: =Y16 -> 372.51221 | E17: =Parameters!$E$6*C17 -> 100 | F17: =IF(Parameters!$E$5=1,E17,0) -> 0 | G17: =Parameters!$E$27*G16+F17 -> 0 | H17: =IF(AND(Parameters!$E$5=1,Parameters!$E$26=1),SUMPRODUCT(--($A$5:A17<A17),--(MOD(A17-$A$5:A17,Parameters!$E$28)=0),$F$5:F17,POWER(Parameters!$E$27,IF(A17-$A$5:A17=0,1,A17-$A$5:A17))),0) -> 0 | I17: =Parameters!$E$23*I16+B17*Parameters!$E$22 -> 0 | J17: =E17*Parameters!$E$14*(1-Parameters!$E$15) -> 1900 | K17: =H17*Parameters!$E$29 -> 0 | L17: =I17*Parameters!$E$24 -> 0 | M17: =J17+K17+L17 -> 1900 | N17: =C17*Parameters!$E$17+D17*Parameters!$E$18+E17*Parameters!$E$16+I17*Parameters!$E$25+G17*Parameters!$E$30 -> 411.75366 | O17: =B17*Parameters!$E$19 -> 4000 | P17: =M17-N17-O17 -> -2511.7537 | Q17: =Parameters!$E$21 -> 1000 | R17: =P17-Q17 -> -3511.7537 | S17: =IF(A17<1+Parameters!$E$31,0,INDEX($M$5:$M$40,A17-Parameters!$E$31)) -> 1900 | T17: =T16+M17-S17 -> 1900 | U17: =S17-N17-O17-Q17 -> -3511.7537 | V17: =V16+U17 -> -47092.985 | W17: =(1-Parameters!$E$7)*(C17-E17)+(1-Parameters!$E$8)*(D17+E17) -> 994.50244 | X17: =Parameters!$E$7*(C17-E17)+Parameters!$E$8*Parameters!$E$9*(D17+E17) -> 0 | Y17: =Parameters!$E$8*(1-Parameters!$E$9)*(D17+E17) -> 378.00977 | Z17: =POWER(1/(1+Parameters!$E$32),A17-1)*(M17-N17) -> 1320.7431
... A40: 36 | B40: =Parameters!$E$20 -> 1000 | C40: =X39+B40 -> 1000 | D40: =Y39 -> 399.83774 | E40: =Parameters!$E$6*C40 -> 100 | F40: =IF(Parameters!$E$5=1,E40,0) -> 0 | G40: =Parameters!$E$27*G39+F40 -> 0 | H40: =IF(AND(Parameters!$E$5=1,Parameters!$E$26=1),SUMPRODUCT(--($A$5:A40<A40),--(MOD(A40-$A$5:A40,Parameters!$E$28)=0),$F$5:F40,POWER(Parameters!$E$27,IF(A40-$A$5:A40=0,1,A40-$A$5:A40))),0) -> 0 | I40: =Parameters!$E$23*I39+B40*Parameters!$E$22 -> 0 | J40: =E40*Parameters!$E$14*(1-Parameters!$E$15) -> 1900 | K40: =H40*Parameters!$E$29 -> 0 | L40: =I40*Parameters!$E$24 -> 0 | M40: =J40+K40+L40 -> 1900 | N40: =C40*Parameters!$E$17+D40*Parameters!$E$18+E40*Parameters!$E$16+I40*Parameters!$E$25+G40*Parameters!$E$30 -> 419.95132 | O40: =B40*Parameters!$E$19 -> 4000 | P40: =M40-N40-O40 -> -2519.9513 | Q40: =Parameters!$E$21 -> 1000 | R40: =P40-Q40 -> -3519.9513 | S40: =IF(A40<1+Parameters!$E$31,0,INDEX($M$5:$M$40,A40-Parameters!$E$31)) -> 1900 | T40: =T39+M40-S40 -> 1900 | U40: =S40-N40-O40-Q40 -> -3519.9513 | V40: =V39+U40 -> -128020.19 | W40: =(1-Parameters!$E$7)*(C40-E40)+(1-Parameters!$E$8)*(D40+E40) -> 999.96755 | X40: =Parameters!$E$7*(C40-E40)+Parameters!$E$8*Parameters!$E$9*(D40+E40) -> 0 | Y40: =Parameters!$E$8*(1-Parameters!$E$9)*(D40+E40) -> 399.87019 | Z40: =POWER(1/(1+Parameters!$E$32),A40-1)*(M40-N40) -> 1044.7874
A43: One acquired-owner cohort: V36 before acquisition/fixed costs. This isolates the mathematical unit value.
A44: Month | B44: Acquired | C44: E eligible | D44: M completed active | E44: Payable events | F44: New policies | G44: Active policies | H44: Renewed policies | I44: Billed subscribers | J44: Initial revenue | K44: Renewal revenue | L44: Software revenue | M44: Total revenue | N44: Variable cost | O44: Acquisition cost | P44: Contribution | Q44: Fixed cost | R44: Operating result | S44: Cash receipts | T44: Receivables | U44: Cash surplus | V44: Cumulative cash | W44: Churned opportunity owners | X44: Next E | Y44: Next M | Z44: Discounted contribution before CAC
A45: 1 | B45: =1 -> 1 | C45: =B45 -> 1 | D45: =0 -> 0 | E45: =Parameters!$E$6*C45 -> 0.1 | F45: =IF(Parameters!$E$5=1,E45,0) -> 0 | G45: =F45 -> 0 | H45: =IF(AND(Parameters!$E$5=1,Parameters!$E$26=1),SUMPRODUCT(--($A$45:A45<A45),--(MOD(A45-$A$45:A45,Parameters!$E$28)=0),$F$45:F45,POWER(Parameters!$E$27,IF(A45-$A$45:A45=0,1,A45-$A$45:A45))),0) -> 0 | I45: =B45*Parameters!$E$22 -> 0 | J45: =E45*Parameters!$E$14*(1-Parameters!$E$15) -> 1.9 | K45: =H45*Parameters!$E$29 -> 0 | L45: =I45*Parameters!$E$24 -> 0 | M45: =J45+K45+L45 -> 1.9 | N45: =C45*Parameters!$E$17+D45*Parameters!$E$18+E45*Parameters!$E$16+I45*Parameters!$E$25+G45*Parameters!$E$30 -> 0.3 | O45: =0 -> 0 | P45: =M45-N45-O45 -> 1.6 | Q45: =0 -> 0 | R45: =P45-Q45 -> 1.6 | S45: =IF(A45<1+Parameters!$E$31,0,INDEX($M$45:$M$80,A45-Parameters!$E$31)) -> 0 | T45: =M45-S45 -> 1.9 | U45: =S45-N45-O45-Q45 -> -0.3 | V45: =U45 -> -0.3 | W45: =(1-Parameters!$E$7)*(C45-E45)+(1-Parameters!$E$8)*(D45+E45) -> 0.92 | X45: =Parameters!$E$7*(C45-E45)+Parameters!$E$8*Parameters!$E$9*(D45+E45) -> 0 | Y45: =Parameters!$E$8*(1-Parameters!$E$9)*(D45+E45) -> 0.08 | Z45: =POWER(1/(1+Parameters!$E$32),A45-1)*(M45-N45) -> 1.6
A46: 2 | B46: =0 -> 0 | C46: =X45+B46 -> 0 | D46: =Y45 -> 0.08 | E46: =Parameters!$E$6*C46 -> 0 | F46: =IF(Parameters!$E$5=1,E46,0) -> 0 | G46: =Parameters!$E$27*G45+F46 -> 0 | H46: =IF(AND(Parameters!$E$5=1,Parameters!$E$26=1),SUMPRODUCT(--($A$45:A46<A46),--(MOD(A46-$A$45:A46,Parameters!$E$28)=0),$F$45:F46,POWER(Parameters!$E$27,IF(A46-$A$45:A46=0,1,A46-$A$45:A46))),0) -> 0 | I46: =Parameters!$E$23*I45+B46*Parameters!$E$22 -> 0 | J46: =E46*Parameters!$E$14*(1-Parameters!$E$15) -> 0 | K46: =H46*Parameters!$E$29 -> 0 | L46: =I46*Parameters!$E$24 -> 0 | M46: =J46+K46+L46 -> 0 | N46: =C46*Parameters!$E$17+D46*Parameters!$E$18+E46*Parameters!$E$16+I46*Parameters!$E$25+G46*Parameters!$E$30 -> 0.024 | O46: =0 -> 0 | P46: =M46-N46-O46 -> -0.024 | Q46: =0 -> 0 | R46: =P46-Q46 -> -0.024 | S46: =IF(A46<1+Parameters!$E$31,0,INDEX($M$45:$M$80,A46-Parameters!$E$31)) -> 1.9 | T46: =T45+M46-S46 -> 0 | U46: =S46-N46-O46-Q46 -> 1.876 | V46: =V45+U46 -> 1.576 | W46: =(1-Parameters!$E$7)*(C46-E46)+(1-Parameters!$E$8)*(D46+E46) -> 0.016 | X46: =Parameters!$E$7*(C46-E46)+Parameters!$E$8*Parameters!$E$9*(D46+E46) -> 0 | Y46: =Parameters!$E$8*(1-Parameters!$E$9)*(D46+E46) -> 0.064 | Z46: =POWER(1/(1+Parameters!$E$32),A46-1)*(M46-N46) -> -0.023762376
A47: 3 | B47: =0 -> 0 | C47: =X46+B47 -> 0 | D47: =Y46 -> 0.064 | E47: =Parameters!$E$6*C47 -> 0 | F47: =IF(Parameters!$E$5=1,E47,0) -> 0 | G47: =Parameters!$E$27*G46+F47 -> 0 | H47: =IF(AND(Parameters!$E$5=1,Parameters!$E$26=1),SUMPRODUCT(--($A$45:A47<A47),--(MOD(A47-$A$45:A47,Parameters!$E$28)=0),$F$45:F47,POWER(Parameters!$E$27,IF(A47-$A$45:A47=0,1,A47-$A$45:A47))),0) -> 0 | I47: =Parameters!$E$23*I46+B47*Parameters!$E$22 -> 0 | J47: =E47*Parameters!$E$14*(1-Parameters!$E$15) -> 0 | K47: =H47*Parameters!$E$29 -> 0 | L47: =I47*Parameters!$E$24 -> 0 | M47: =J47+K47+L47 -> 0 | N47: =C47*Parameters!$E$17+D47*Parameters!$E$18+E47*Parameters!$E$16+I47*Parameters!$E$25+G47*Parameters!$E$30 -> 0.0192 | O47: =0 -> 0 | P47: =M47-N47-O47 -> -0.0192 | Q47: =0 -> 0 | R47: =P47-Q47 -> -0.0192 | S47: =IF(A47<1+Parameters!$E$31,0,INDEX($M$45:$M$80,A47-Parameters!$E$31)) -> 0 | T47: =T46+M47-S47 -> 0 | U47: =S47-N47-O47-Q47 -> -0.0192 | V47: =V46+U47 -> 1.5568 | W47: =(1-Parameters!$E$7)*(C47-E47)+(1-Parameters!$E$8)*(D47+E47) -> 0.0128 | X47: =Parameters!$E$7*(C47-E47)+Parameters!$E$8*Parameters!$E$9*(D47+E47) -> 0 | Y47: =Parameters!$E$8*(1-Parameters!$E$9)*(D47+E47) -> 0.0512 | Z47: =POWER(1/(1+Parameters!$E$32),A47-1)*(M47-N47) -> -0.018821684
A48: 4 | B48: =0 -> 0 | C48: =X47+B48 -> 0 | D48: =Y47 -> 0.0512 | E48: =Parameters!$E$6*C48 -> 0 | F48: =IF(Parameters!$E$5=1,E48,0) -> 0 | G48: =Parameters!$E$27*G47+F48 -> 0 | H48: =IF(AND(Parameters!$E$5=1,Parameters!$E$26=1),SUMPRODUCT(--($A$45:A48<A48),--(MOD(A48-$A$45:A48,Parameters!$E$28)=0),$F$45:F48,POWER(Parameters!$E$27,IF(A48-$A$45:A48=0,1,A48-$A$45:A48))),0) -> 0 | I48: =Parameters!$E$23*I47+B48*Parameters!$E$22 -> 0 | J48: =E48*Parameters!$E$14*(1-Parameters!$E$15) -> 0 | K48: =H48*Parameters!$E$29 -> 0 | L48: =I48*Parameters!$E$24 -> 0 | M48: =J48+K48+L48 -> 0 | N48: =C48*Parameters!$E$17+D48*Parameters!$E$18+E48*Parameters!$E$16+I48*Parameters!$E$25+G48*Parameters!$E$30 -> 0.01536 | O48: =0 -> 0 | P48: =M48-N48-O48 -> -0.01536 | Q48: =0 -> 0 | R48: =P48-Q48 -> -0.01536 | S48: =IF(A48<1+Parameters!$E$31,0,INDEX($M$45:$M$80,A48-Parameters!$E$31)) -> 0 | T48: =T47+M48-S48 -> 0 | U48: =S48-N48-O48-Q48 -> -0.01536 | V48: =V47+U48 -> 1.54144 | W48: =(1-Parameters!$E$7)*(C48-E48)+(1-Parameters!$E$8)*(D48+E48) -> 0.01024 | X48: =Parameters!$E$7*(C48-E48)+Parameters!$E$8*Parameters!$E$9*(D48+E48) -> 0 | Y48: =Parameters!$E$8*(1-Parameters!$E$9)*(D48+E48) -> 0.04096 | Z48: =POWER(1/(1+Parameters!$E$32),A48-1)*(M48-N48) -> -0.014908265
A49: 5 | B49: =0 -> 0 | C49: =X48+B49 -> 0 | D49: =Y48 -> 0.04096 | E49: =Parameters!$E$6*C49 -> 0 | F49: =IF(Parameters!$E$5=1,E49,0) -> 0 | G49: =Parameters!$E$27*G48+F49 -> 0 | H49: =IF(AND(Parameters!$E$5=1,Parameters!$E$26=1),SUMPRODUCT(--($A$45:A49<A49),--(MOD(A49-$A$45:A49,Parameters!$E$28)=0),$F$45:F49,POWER(Parameters!$E$27,IF(A49-$A$45:A49=0,1,A49-$A$45:A49))),0) -> 0 | I49: =Parameters!$E$23*I48+B49*Parameters!$E$22 -> 0 | J49: =E49*Parameters!$E$14*(1-Parameters!$E$15) -> 0 | K49: =H49*Parameters!$E$29 -> 0 | L49: =I49*Parameters!$E$24 -> 0 | M49: =J49+K49+L49 -> 0 | N49: =C49*Parameters!$E$17+D49*Parameters!$E$18+E49*Parameters!$E$16+I49*Parameters!$E$25+G49*Parameters!$E$30 -> 0.012288 | O49: =0 -> 0 | P49: =M49-N49-O49 -> -0.012288 | Q49: =0 -> 0 | R49: =P49-Q49 -> -0.012288 | S49: =IF(A49<1+Parameters!$E$31,0,INDEX($M$45:$M$80,A49-Parameters!$E$31)) -> 0 | T49: =T48+M49-S49 -> 0 | U49: =S49-N49-O49-Q49 -> -0.012288 | V49: =V48+U49 -> 1.529152 | W49: =(1-Parameters!$E$7)*(C49-E49)+(1-Parameters!$E$8)*(D49+E49) -> 0.008192 | X49: =Parameters!$E$7*(C49-E49)+Parameters!$E$8*Parameters!$E$9*(D49+E49) -> 0 | Y49: =Parameters!$E$8*(1-Parameters!$E$9)*(D49+E49) -> 0.032768 | Z49: =POWER(1/(1+Parameters!$E$32),A49-1)*(M49-N49) -> -0.011808526
A50: 6 | B50: =0 -> 0 | C50: =X49+B50 -> 0 | D50: =Y49 -> 0.032768 | E50: =Parameters!$E$6*C50 -> 0 | F50: =IF(Parameters!$E$5=1,E50,0) -> 0 | G50: =Parameters!$E$27*G49+F50 -> 0 | H50: =IF(AND(Parameters!$E$5=1,Parameters!$E$26=1),SUMPRODUCT(--($A$45:A50<A50),--(MOD(A50-$A$45:A50,Parameters!$E$28)=0),$F$45:F50,POWER(Parameters!$E$27,IF(A50-$A$45:A50=0,1,A50-$A$45:A50))),0) -> 0 | I50: =Parameters!$E$23*I49+B50*Parameters!$E$22 -> 0 | J50: =E50*Parameters!$E$14*(1-Parameters!$E$15) -> 0 | K50: =H50*Parameters!$E$29 -> 0 | L50: =I50*Parameters!$E$24 -> 0 | M50: =J50+K50+L50 -> 0 | N50: =C50*Parameters!$E$17+D50*Parameters!$E$18+E50*Parameters!$E$16+I50*Parameters!$E$25+G50*Parameters!$E$30 -> 0.0098304 | O50: =0 -> 0 | P50: =M50-N50-O50 -> -0.0098304 | Q50: =0 -> 0 | R50: =P50-Q50 -> -0.0098304 | S50: =IF(A50<1+Parameters!$E$31,0,INDEX($M$45:$M$80,A50-Parameters!$E$31)) -> 0 | T50: =T49+M50-S50 -> 0 | U50: =S50-N50-O50-Q50 -> -0.0098304 | V50: =V49+U50 -> 1.5193216 | W50: =(1-Parameters!$E$7)*(C50-E50)+(1-Parameters!$E$8)*(D50+E50) -> 0.0065536 | X50: =Parameters!$E$7*(C50-E50)+Parameters!$E$8*Parameters!$E$9*(D50+E50) -> 0 | Y50: =Parameters!$E$8*(1-Parameters!$E$9)*(D50+E50) -> 0.0262144 | Z50: =POWER(1/(1+Parameters!$E$32),A50-1)*(M50-N50) -> -0.0093532883
A51: 7 | B51: =0 -> 0 | C51: =X50+B51 -> 0 | D51: =Y50 -> 0.0262144 | E51: =Parameters!$E$6*C51 -> 0 | F51: =IF(Parameters!$E$5=1,E51,0) -> 0 | G51: =Parameters!$E$27*G50+F51 -> 0 | H51: =IF(AND(Parameters!$E$5=1,Parameters!$E$26=1),SUMPRODUCT(--($A$45:A51<A51),--(MOD(A51-$A$45:A51,Parameters!$E$28)=0),$F$45:F51,POWER(Parameters!$E$27,IF(A51-$A$45:A51=0,1,A51-$A$45:A51))),0) -> 0 | I51: =Parameters!$E$23*I50+B51*Parameters!$E$22 -> 0 | J51: =E51*Parameters!$E$14*(1-Parameters!$E$15) -> 0 | K51: =H51*Parameters!$E$29 -> 0 | L51: =I51*Parameters!$E$24 -> 0 | M51: =J51+K51+L51 -> 0 | N51: =C51*Parameters!$E$17+D51*Parameters!$E$18+E51*Parameters!$E$16+I51*Parameters!$E$25+G51*Parameters!$E$30 -> 0.00786432 | O51: =0 -> 0 | P51: =M51-N51-O51 -> -0.00786432 | Q51: =0 -> 0 | R51: =P51-Q51 -> -0.00786432 | S51: =IF(A51<1+Parameters!$E$31,0,INDEX($M$45:$M$80,A51-Parameters!$E$31)) -> 0 | T51: =T50+M51-S51 -> 0 | U51: =S51-N51-O51-Q51 -> -0.00786432 | V51: =V50+U51 -> 1.5114573 | W51: =(1-Parameters!$E$7)*(C51-E51)+(1-Parameters!$E$8)*(D51+E51) -> 0.00524288 | X51: =Parameters!$E$7*(C51-E51)+Parameters!$E$8*Parameters!$E$9*(D51+E51) -> 0 | Y51: =Parameters!$E$8*(1-Parameters!$E$9)*(D51+E51) -> 0.02097152 | Z51: =POWER(1/(1+Parameters!$E$32),A51-1)*(M51-N51) -> -0.0074085452
A52: 8 | B52: =0 -> 0 | C52: =X51+B52 -> 0 | D52: =Y51 -> 0.02097152 | E52: =Parameters!$E$6*C52 -> 0 | F52: =IF(Parameters!$E$5=1,E52,0) -> 0 | G52: =Parameters!$E$27*G51+F52 -> 0 | H52: =IF(AND(Parameters!$E$5=1,Parameters!$E$26=1),SUMPRODUCT(--($A$45:A52<A52),--(MOD(A52-$A$45:A52,Parameters!$E$28)=0),$F$45:F52,POWER(Parameters!$E$27,IF(A52-$A$45:A52=0,1,A52-$A$45:A52))),0) -> 0 | I52: =Parameters!$E$23*I51+B52*Parameters!$E$22 -> 0 | J52: =E52*Parameters!$E$14*(1-Parameters!$E$15) -> 0 | K52: =H52*Parameters!$E$29 -> 0 | L52: =I52*Parameters!$E$24 -> 0 | M52: =J52+K52+L52 -> 0 | N52: =C52*Parameters!$E$17+D52*Parameters!$E$18+E52*Parameters!$E$16+I52*Parameters!$E$25+G52*Parameters!$E$30 -> 0.006291456 | O52: =0 -> 0 | P52: =M52-N52-O52 -> -0.006291456 | Q52: =0 -> 0 | R52: =P52-Q52 -> -0.006291456 | S52: =IF(A52<1+Parameters!$E$31,0,INDEX($M$45:$M$80,A52-Parameters!$E$31)) -> 0 | T52: =T51+M52-S52 -> 0 | U52: =S52-N52-O52-Q52 -> -0.006291456 | V52: =V51+U52 -> 1.5051658 | W52: =(1-Parameters!$E$7)*(C52-E52)+(1-Parameters!$E$8)*(D52+E52) -> 0.004194304 | X52: =Parameters!$E$7*(C52-E52)+Parameters!$E$8*Parameters!$E$9*(D52+E52) -> 0 | Y52: =Parameters!$E$8*(1-Parameters!$E$9)*(D52+E52) -> 0.016777216 | Z52: =POWER(1/(1+Parameters!$E$32),A52-1)*(M52-N52) -> -0.0058681546
A53: 9 | B53: =0 -> 0 | C53: =X52+B53 -> 0 | D53: =Y52 -> 0.016777216 | E53: =Parameters!$E$6*C53 -> 0 | F53: =IF(Parameters!$E$5=1,E53,0) -> 0 | G53: =Parameters!$E$27*G52+F53 -> 0 | H53: =IF(AND(Parameters!$E$5=1,Parameters!$E$26=1),SUMPRODUCT(--($A$45:A53<A53),--(MOD(A53-$A$45:A53,Parameters!$E$28)=0),$F$45:F53,POWER(Parameters!$E$27,IF(A53-$A$45:A53=0,1,A53-$A$45:A53))),0) -> 0 | I53: =Parameters!$E$23*I52+B53*Parameters!$E$22 -> 0 | J53: =E53*Parameters!$E$14*(1-Parameters!$E$15) -> 0 | K53: =H53*Parameters!$E$29 -> 0 | L53: =I53*Parameters!$E$24 -> 0 | M53: =J53+K53+L53 -> 0 | N53: =C53*Parameters!$E$17+D53*Parameters!$E$18+E53*Parameters!$E$16+I53*Parameters!$E$25+G53*Parameters!$E$30 -> 0.0050331648 | O53: =0 -> 0 | P53: =M53-N53-O53 -> -0.0050331648 | Q53: =0 -> 0 | R53: =P53-Q53 -> -0.0050331648 | S53: =IF(A53<1+Parameters!$E$31,0,INDEX($M$45:$M$80,A53-Parameters!$E$31)) -> 0 | T53: =T52+M53-S53 -> 0 | U53: =S53-N53-O53-Q53 -> -0.0050331648 | V53: =V52+U53 -> 1.5001327 | W53: =(1-Parameters!$E$7)*(C53-E53)+(1-Parameters!$E$8)*(D53+E53) -> 0.0033554432 | X53: =Parameters!$E$7*(C53-E53)+Parameters!$E$8*Parameters!$E$9*(D53+E53) -> 0 | Y53: =Parameters!$E$8*(1-Parameters!$E$9)*(D53+E53) -> 0.013421773 | Z53: =POWER(1/(1+Parameters!$E$32),A53-1)*(M53-N53) -> -0.0046480432
A54: 10 | B54: =0 -> 0 | C54: =X53+B54 -> 0 | D54: =Y53 -> 0.013421773 | E54: =Parameters!$E$6*C54 -> 0 | F54: =IF(Parameters!$E$5=1,E54,0) -> 0 | G54: =Parameters!$E$27*G53+F54 -> 0 | H54: =IF(AND(Parameters!$E$5=1,Parameters!$E$26=1),SUMPRODUCT(--($A$45:A54<A54),--(MOD(A54-$A$45:A54,Parameters!$E$28)=0),$F$45:F54,POWER(Parameters!$E$27,IF(A54-$A$45:A54=0,1,A54-$A$45:A54))),0) -> 0 | I54: =Parameters!$E$23*I53+B54*Parameters!$E$22 -> 0 | J54: =E54*Parameters!$E$14*(1-Parameters!$E$15) -> 0 | K54: =H54*Parameters!$E$29 -> 0 | L54: =I54*Parameters!$E$24 -> 0 | M54: =J54+K54+L54 -> 0 | N54: =C54*Parameters!$E$17+D54*Parameters!$E$18+E54*Parameters!$E$16+I54*Parameters!$E$25+G54*Parameters!$E$30 -> 0.0040265318 | O54: =0 -> 0 | P54: =M54-N54-O54 -> -0.0040265318 | Q54: =0 -> 0 | R54: =P54-Q54 -> -0.0040265318 | S54: =IF(A54<1+Parameters!$E$31,0,INDEX($M$45:$M$80,A54-Parameters!$E$31)) -> 0 | T54: =T53+M54-S54 -> 0 | U54: =S54-N54-O54-Q54 -> -0.0040265318 | V54: =V53+U54 -> 1.4961061 | W54: =(1-Parameters!$E$7)*(C54-E54)+(1-Parameters!$E$8)*(D54+E54) -> 0.0026843546 | X54: =Parameters!$E$7*(C54-E54)+Parameters!$E$8*Parameters!$E$9*(D54+E54) -> 0 | Y54: =Parameters!$E$8*(1-Parameters!$E$9)*(D54+E54) -> 0.010737418 | Z54: =POWER(1/(1+Parameters!$E$32),A54-1)*(M54-N54) -> -0.0036816184
A55: 11 | B55: =0 -> 0 | C55: =X54+B55 -> 0 | D55: =Y54 -> 0.010737418 | E55: =Parameters!$E$6*C55 -> 0 | F55: =IF(Parameters!$E$5=1,E55,0) -> 0 | G55: =Parameters!$E$27*G54+F55 -> 0 | H55: =IF(AND(Parameters!$E$5=1,Parameters!$E$26=1),SUMPRODUCT(--($A$45:A55<A55),--(MOD(A55-$A$45:A55,Parameters!$E$28)=0),$F$45:F55,POWER(Parameters!$E$27,IF(A55-$A$45:A55=0,1,A55-$A$45:A55))),0) -> 0 | I55: =Parameters!$E$23*I54+B55*Parameters!$E$22 -> 0 | J55: =E55*Parameters!$E$14*(1-Parameters!$E$15) -> 0 | K55: =H55*Parameters!$E$29 -> 0 | L55: =I55*Parameters!$E$24 -> 0 | M55: =J55+K55+L55 -> 0 | N55: =C55*Parameters!$E$17+D55*Parameters!$E$18+E55*Parameters!$E$16+I55*Parameters!$E$25+G55*Parameters!$E$30 -> 0.0032212255 | O55: =0 -> 0 | P55: =M55-N55-O55 -> -0.0032212255 | Q55: =0 -> 0 | R55: =P55-Q55 -> -0.0032212255 | S55: =IF(A55<1+Parameters!$E$31,0,INDEX($M$45:$M$80,A55-Parameters!$E$31)) -> 0 | T55: =T54+M55-S55 -> 0 | U55: =S55-N55-O55-Q55 -> -0.0032212255 | V55: =V54+U55 -> 1.4928849 | W55: =(1-Parameters!$E$7)*(C55-E55)+(1-Parameters!$E$8)*(D55+E55) -> 0.0021474836 | X55: =Parameters!$E$7*(C55-E55)+Parameters!$E$8*Parameters!$E$9*(D55+E55) -> 0 | Y55: =Parameters!$E$8*(1-Parameters!$E$9)*(D55+E55) -> 0.0085899346 | Z55: =POWER(1/(1+Parameters!$E$32),A55-1)*(M55-N55) -> -0.0029161334
A56: 12 | B56: =0 -> 0 | C56: =X55+B56 -> 0 | D56: =Y55 -> 0.0085899346 | E56: =Parameters!$E$6*C56 -> 0 | F56: =IF(Parameters!$E$5=1,E56,0) -> 0 | G56: =Parameters!$E$27*G55+F56 -> 0 | H56: =IF(AND(Parameters!$E$5=1,Parameters!$E$26=1),SUMPRODUCT(--($A$45:A56<A56),--(MOD(A56-$A$45:A56,Parameters!$E$28)=0),$F$45:F56,POWER(Parameters!$E$27,IF(A56-$A$45:A56=0,1,A56-$A$45:A56))),0) -> 0 | I56: =Parameters!$E$23*I55+B56*Parameters!$E$22 -> 0 | J56: =E56*Parameters!$E$14*(1-Parameters!$E$15) -> 0 | K56: =H56*Parameters!$E$29 -> 0 | L56: =I56*Parameters!$E$24 -> 0 | M56: =J56+K56+L56 -> 0 | N56: =C56*Parameters!$E$17+D56*Parameters!$E$18+E56*Parameters!$E$16+I56*Parameters!$E$25+G56*Parameters!$E$30 -> 0.0025769804 | O56: =0 -> 0 | P56: =M56-N56-O56 -> -0.0025769804 | Q56: =0 -> 0 | R56: =P56-Q56 -> -0.0025769804 | S56: =IF(A56<1+Parameters!$E$31,0,INDEX($M$45:$M$80,A56-Parameters!$E$31)) -> 0 | T56: =T55+M56-S56 -> 0 | U56: =S56-N56-O56-Q56 -> -0.0025769804 | V56: =V55+U56 -> 1.4903079 | W56: =(1-Parameters!$E$7)*(C56-E56)+(1-Parameters!$E$8)*(D56+E56) -> 0.0017179869 | X56: =Parameters!$E$7*(C56-E56)+Parameters!$E$8*Parameters!$E$9*(D56+E56) -> 0 | Y56: =Parameters!$E$8*(1-Parameters!$E$9)*(D56+E56) -> 0.0068719477 | Z56: =POWER(1/(1+Parameters!$E$32),A56-1)*(M56-N56) -> -0.0023098086
A57: 13 | B57: =0 -> 0 | C57: =X56+B57 -> 0 | D57: =Y56 -> 0.0068719477 | E57: =Parameters!$E$6*C57 -> 0 | F57: =IF(Parameters!$E$5=1,E57,0) -> 0 | G57: =Parameters!$E$27*G56+F57 -> 0 | H57: =IF(AND(Parameters!$E$5=1,Parameters!$E$26=1),SUMPRODUCT(--($A$45:A57<A57),--(MOD(A57-$A$45:A57,Parameters!$E$28)=0),$F$45:F57,POWER(Parameters!$E$27,IF(A57-$A$45:A57=0,1,A57-$A$45:A57))),0) -> 0 | I57: =Parameters!$E$23*I56+B57*Parameters!$E$22 -> 0 | J57: =E57*Parameters!$E$14*(1-Parameters!$E$15) -> 0 | K57: =H57*Parameters!$E$29 -> 0 | L57: =I57*Parameters!$E$24 -> 0 | M57: =J57+K57+L57 -> 0 | N57: =C57*Parameters!$E$17+D57*Parameters!$E$18+E57*Parameters!$E$16+I57*Parameters!$E$25+G57*Parameters!$E$30 -> 0.0020615843 | O57: =0 -> 0 | P57: =M57-N57-O57 -> -0.0020615843 | Q57: =0 -> 0 | R57: =P57-Q57 -> -0.0020615843 | S57: =IF(A57<1+Parameters!$E$31,0,INDEX($M$45:$M$80,A57-Parameters!$E$31)) -> 0 | T57: =T56+M57-S57 -> 0 | U57: =S57-N57-O57-Q57 -> -0.0020615843 | V57: =V56+U57 -> 1.4882463 | W57: =(1-Parameters!$E$7)*(C57-E57)+(1-Parameters!$E$8)*(D57+E57) -> 0.0013743895 | X57: =Parameters!$E$7*(C57-E57)+Parameters!$E$8*Parameters!$E$9*(D57+E57) -> 0 | Y57: =Parameters!$E$8*(1-Parameters!$E$9)*(D57+E57) -> 0.0054975581 | Z57: =POWER(1/(1+Parameters!$E$32),A57-1)*(M57-N57) -> -0.0018295514
... A80: 36 | B80: =0 -> 0 | C80: =X79+B80 -> 0 | D80: =Y79 -> 4.0564819e-05 | E80: =Parameters!$E$6*C80 -> 0 | F80: =IF(Parameters!$E$5=1,E80,0) -> 0 | G80: =Parameters!$E$27*G79+F80 -> 0 | H80: =IF(AND(Parameters!$E$5=1,Parameters!$E$26=1),SUMPRODUCT(--($A$45:A80<A80),--(MOD(A80-$A$45:A80,Parameters!$E$28)=0),$F$45:F80,POWER(Parameters!$E$27,IF(A80-$A$45:A80=0,1,A80-$A$45:A80))),0) -> 0 | I80: =Parameters!$E$23*I79+B80*Parameters!$E$22 -> 0 | J80: =E80*Parameters!$E$14*(1-Parameters!$E$15) -> 0 | K80: =H80*Parameters!$E$29 -> 0 | L80: =I80*Parameters!$E$24 -> 0 | M80: =J80+K80+L80 -> 0 | N80: =C80*Parameters!$E$17+D80*Parameters!$E$18+E80*Parameters!$E$16+I80*Parameters!$E$25+G80*Parameters!$E$30 -> 1.2169446e-05 | O80: =0 -> 0 | P80: =M80-N80-O80 -> -1.2169446e-05 | Q80: =0 -> 0 | R80: =P80-Q80 -> -1.2169446e-05 | S80: =IF(A80<1+Parameters!$E$31,0,INDEX($M$45:$M$80,A80-Parameters!$E$31)) -> 0 | T80: =T79+M80-S80 -> 0 | U80: =S80-N80-O80-Q80 -> -1.2169446e-05 | V80: =V79+U80 -> 1.4800487 | W80: =(1-Parameters!$E$7)*(C80-E80)+(1-Parameters!$E$8)*(D80+E80) -> 8.1129638e-06 | X80: =Parameters!$E$7*(C80-E80)+Parameters!$E$8*Parameters!$E$9*(D80+E80) -> 0 | Y80: =Parameters!$E$8*(1-Parameters!$E$9)*(D80+E80) -> 3.2451855e-05 | Z80: =POWER(1/(1+Parameters!$E$32),A80-1)*(M80-N80) -> -8.5905846e-06

Sheet S3
A1: S3 — Retain before and after first lead
A2: All parameters are illustrative. Top block: calendar cohorts. Lower block: one acquired owner, no CAC/fixed cost, for customer-value calculation.
A4: Month | B4: Acquired | C4: E eligible | D4: M completed active | E4: Payable events | F4: New policies | G4: Active policies | H4: Renewed policies | I4: Billed subscribers | J4: Initial revenue | K4: Renewal revenue | L4: Software revenue | M4: Total revenue | N4: Variable cost | O4: Acquisition cost | P4: Contribution | Q4: Fixed cost | R4: Operating result | S4: Cash receipts | T4: Receivables | U4: Cash surplus | V4: Cumulative cash | W4: Churned opportunity owners | X4: Next E | Y4: Next M | Z4: Discounted contribution before CAC
A5: 1 | B5: =Parameters!$F$20 -> 1000 | C5: =B5 -> 1000 | D5: =0 -> 0 | E5: =Parameters!$F$6*C5 -> 100 | F5: =IF(Parameters!$F$5=1,E5,0) -> 0 | G5: =F5 -> 0 | H5: =IF(AND(Parameters!$F$5=1,Parameters!$F$26=1),SUMPRODUCT(--($A$5:A5<A5),--(MOD(A5-$A$5:A5,Parameters!$F$28)=0),$F$5:F5,POWER(Parameters!$F$27,IF(A5-$A$5:A5=0,1,A5-$A$5:A5))),0) -> 0 | I5: =B5*Parameters!$F$22 -> 0 | J5: =E5*Parameters!$F$14*(1-Parameters!$F$15) -> 1900 | K5: =H5*Parameters!$F$29 -> 0 | L5: =I5*Parameters!$F$24 -> 0 | M5: =J5+K5+L5 -> 1900 | N5: =C5*Parameters!$F$17+D5*Parameters!$F$18+E5*Parameters!$F$16+I5*Parameters!$F$25+G5*Parameters!$F$30 -> 300 | O5: =B5*Parameters!$F$19 -> 4000 | P5: =M5-N5-O5 -> -2400 | Q5: =Parameters!$F$21 -> 1000 | R5: =P5-Q5 -> -3400 | S5: =IF(A5<1+Parameters!$F$31,0,INDEX($M$5:$M$40,A5-Parameters!$F$31)) -> 0 | T5: =M5-S5 -> 1900 | U5: =S5-N5-O5-Q5 -> -5300 | V5: =U5 -> -5300 | W5: =(1-Parameters!$F$7)*(C5-E5)+(1-Parameters!$F$8)*(D5+E5) -> 200 | X5: =Parameters!$F$7*(C5-E5)+Parameters!$F$8*Parameters!$F$9*(D5+E5) -> 720 | Y5: =Parameters!$F$8*(1-Parameters!$F$9)*(D5+E5) -> 80 | Z5: =POWER(1/(1+Parameters!$F$32),A5-1)*(M5-N5) -> 1600
A6: 2 | B6: =Parameters!$F$20 -> 1000 | C6: =X5+B6 -> 1720 | D6: =Y5 -> 80 | E6: =Parameters!$F$6*C6 -> 172 | F6: =IF(Parameters!$F$5=1,E6,0) -> 0 | G6: =Parameters!$F$27*G5+F6 -> 0 | H6: =IF(AND(Parameters!$F$5=1,Parameters!$F$26=1),SUMPRODUCT(--($A$5:A6<A6),--(MOD(A6-$A$5:A6,Parameters!$F$28)=0),$F$5:F6,POWER(Parameters!$F$27,IF(A6-$A$5:A6=0,1,A6-$A$5:A6))),0) -> 0 | I6: =Parameters!$F$23*I5+B6*Parameters!$F$22 -> 0 | J6: =E6*Parameters!$F$14*(1-Parameters!$F$15) -> 3268 | K6: =H6*Parameters!$F$29 -> 0 | L6: =I6*Parameters!$F$24 -> 0 | M6: =J6+K6+L6 -> 3268 | N6: =C6*Parameters!$F$17+D6*Parameters!$F$18+E6*Parameters!$F$16+I6*Parameters!$F$25+G6*Parameters!$F$30 -> 540 | O6: =B6*Parameters!$F$19 -> 4000 | P6: =M6-N6-O6 -> -1272 | Q6: =Parameters!$F$21 -> 1000 | R6: =P6-Q6 -> -2272 | S6: =IF(A6<1+Parameters!$F$31,0,INDEX($M$5:$M$40,A6-Parameters!$F$31)) -> 1900 | T6: =T5+M6-S6 -> 3268 | U6: =S6-N6-O6-Q6 -> -3640 | V6: =V5+U6 -> -8940 | W6: =(1-Parameters!$F$7)*(C6-E6)+(1-Parameters!$F$8)*(D6+E6) -> 360 | X6: =Parameters!$F$7*(C6-E6)+Parameters!$F$8*Parameters!$F$9*(D6+E6) -> 1238.4 | Y6: =Parameters!$F$8*(1-Parameters!$F$9)*(D6+E6) -> 201.6 | Z6: =POWER(1/(1+Parameters!$F$32),A6-1)*(M6-N6) -> 2700.9901
A7: 3 | B7: =Parameters!$F$20 -> 1000 | C7: =X6+B7 -> 2238.4 | D7: =Y6 -> 201.6 | E7: =Parameters!$F$6*C7 -> 223.84 | F7: =IF(Parameters!$F$5=1,E7,0) -> 0 | G7: =Parameters!$F$27*G6+F7 -> 0 | H7: =IF(AND(Parameters!$F$5=1,Parameters!$F$26=1),SUMPRODUCT(--($A$5:A7<A7),--(MOD(A7-$A$5:A7,Parameters!$F$28)=0),$F$5:F7,POWER(Parameters!$F$27,IF(A7-$A$5:A7=0,1,A7-$A$5:A7))),0) -> 0 | I7: =Parameters!$F$23*I6+B7*Parameters!$F$22 -> 0 | J7: =E7*Parameters!$F$14*(1-Parameters!$F$15) -> 4252.96 | K7: =H7*Parameters!$F$29 -> 0 | L7: =I7*Parameters!$F$24 -> 0 | M7: =J7+K7+L7 -> 4252.96 | N7: =C7*Parameters!$F$17+D7*Parameters!$F$18+E7*Parameters!$F$16+I7*Parameters!$F$25+G7*Parameters!$F$30 -> 732 | O7: =B7*Parameters!$F$19 -> 4000 | P7: =M7-N7-O7 -> -479.04 | Q7: =Parameters!$F$21 -> 1000 | R7: =P7-Q7 -> -1479.04 | S7: =IF(A7<1+Parameters!$F$31,0,INDEX($M$5:$M$40,A7-Parameters!$F$31)) -> 3268 | T7: =T6+M7-S7 -> 4252.96 | U7: =S7-N7-O7-Q7 -> -2464 | V7: =V6+U7 -> -11404 | W7: =(1-Parameters!$F$7)*(C7-E7)+(1-Parameters!$F$8)*(D7+E7) -> 488 | X7: =Parameters!$F$7*(C7-E7)+Parameters!$F$8*Parameters!$F$9*(D7+E7) -> 1611.648 | Y7: =Parameters!$F$8*(1-Parameters!$F$9)*(D7+E7) -> 340.352 | Z7: =POWER(1/(1+Parameters!$F$32),A7-1)*(M7-N7) -> 3451.5832
A8: 4 | B8: =Parameters!$F$20 -> 1000 | C8: =X7+B8 -> 2611.648 | D8: =Y7 -> 340.352 | E8: =Parameters!$F$6*C8 -> 261.1648 | F8: =IF(Parameters!$F$5=1,E8,0) -> 0 | G8: =Parameters!$F$27*G7+F8 -> 0 | H8: =IF(AND(Parameters!$F$5=1,Parameters!$F$26=1),SUMPRODUCT(--($A$5:A8<A8),--(MOD(A8-$A$5:A8,Parameters!$F$28)=0),$F$5:F8,POWER(Parameters!$F$27,IF(A8-$A$5:A8=0,1,A8-$A$5:A8))),0) -> 0 | I8: =Parameters!$F$23*I7+B8*Parameters!$F$22 -> 0 | J8: =E8*Parameters!$F$14*(1-Parameters!$F$15) -> 4962.1312 | K8: =H8*Parameters!$F$29 -> 0 | L8: =I8*Parameters!$F$24 -> 0 | M8: =J8+K8+L8 -> 4962.1312 | N8: =C8*Parameters!$F$17+D8*Parameters!$F$18+E8*Parameters!$F$16+I8*Parameters!$F$25+G8*Parameters!$F$30 -> 885.6 | O8: =B8*Parameters!$F$19 -> 4000 | P8: =M8-N8-O8 -> 76.5312 | Q8: =Parameters!$F$21 -> 1000 | R8: =P8-Q8 -> -923.4688 | S8: =IF(A8<1+Parameters!$F$31,0,INDEX($M$5:$M$40,A8-Parameters!$F$31)) -> 4252.96 | T8: =T7+M8-S8 -> 4962.1312 | U8: =S8-N8-O8-Q8 -> -1632.64 | V8: =V7+U8 -> -13036.64 | W8: =(1-Parameters!$F$7)*(C8-E8)+(1-Parameters!$F$8)*(D8+E8) -> 590.4 | X8: =Parameters!$F$7*(C8-E8)+Parameters!$F$8*Parameters!$F$9*(D8+E8) -> 1880.3866 | Y8: =Parameters!$F$8*(1-Parameters!$F$9)*(D8+E8) -> 481.21344 | Z8: =POWER(1/(1+Parameters!$F$32),A8-1)*(M8-N8) -> 3956.641
A9: 5 | B9: =Parameters!$F$20 -> 1000 | C9: =X8+B9 -> 2880.3866 | D9: =Y8 -> 481.21344 | E9: =Parameters!$F$6*C9 -> 288.03866 | F9: =IF(Parameters!$F$5=1,E9,0) -> 0 | G9: =Parameters!$F$27*G8+F9 -> 0 | H9: =IF(AND(Parameters!$F$5=1,Parameters!$F$26=1),SUMPRODUCT(--($A$5:A9<A9),--(MOD(A9-$A$5:A9,Parameters!$F$28)=0),$F$5:F9,POWER(Parameters!$F$27,IF(A9-$A$5:A9=0,1,A9-$A$5:A9))),0) -> 0 | I9: =Parameters!$F$23*I8+B9*Parameters!$F$22 -> 0 | J9: =E9*Parameters!$F$14*(1-Parameters!$F$15) -> 5472.7345 | K9: =H9*Parameters!$F$29 -> 0 | L9: =I9*Parameters!$F$24 -> 0 | M9: =J9+K9+L9 -> 5472.7345 | N9: =C9*Parameters!$F$17+D9*Parameters!$F$18+E9*Parameters!$F$16+I9*Parameters!$F$25+G9*Parameters!$F$30 -> 1008.48 | O9: =B9*Parameters!$F$19 -> 4000 | P9: =M9-N9-O9 -> 464.25446 | Q9: =Parameters!$F$21 -> 1000 | R9: =P9-Q9 -> -535.74554 | S9: =IF(A9<1+Parameters!$F$31,0,INDEX($M$5:$M$40,A9-Parameters!$F$31)) -> 4962.1312 | T9: =T8+M9-S9 -> 5472.7345 | U9: =S9-N9-O9-Q9 -> -1046.3488 | V9: =V8+U9 -> -14082.989 | W9: =(1-Parameters!$F$7)*(C9-E9)+(1-Parameters!$F$8)*(D9+E9) -> 672.32 | X9: =Parameters!$F$7*(C9-E9)+Parameters!$F$8*Parameters!$F$9*(D9+E9) -> 2073.8783 | Y9: =Parameters!$F$8*(1-Parameters!$F$9)*(D9+E9) -> 615.40168 | Z9: =POWER(1/(1+Parameters!$F$32),A9-1)*(M9-N9) -> 4290.0608
A10: 6 | B10: =Parameters!$F$20 -> 1000 | C10: =X9+B10 -> 3073.8783 | D10: =Y9 -> 615.40168 | E10: =Parameters!$F$6*C10 -> 307.38783 | F10: =IF(Parameters!$F$5=1,E10,0) -> 0 | G10: =Parameters!$F$27*G9+F10 -> 0 | H10: =IF(AND(Parameters!$F$5=1,Parameters!$F$26=1),SUMPRODUCT(--($A$5:A10<A10),--(MOD(A10-$A$5:A10,Parameters!$F$28)=0),$F$5:F10,POWER(Parameters!$F$27,IF(A10-$A$5:A10=0,1,A10-$A$5:A10))),0) -> 0 | I10: =Parameters!$F$23*I9+B10*Parameters!$F$22 -> 0 | J10: =E10*Parameters!$F$14*(1-Parameters!$F$15) -> 5840.3688 | K10: =H10*Parameters!$F$29 -> 0 | L10: =I10*Parameters!$F$24 -> 0 | M10: =J10+K10+L10 -> 5840.3688 | N10: =C10*Parameters!$F$17+D10*Parameters!$F$18+E10*Parameters!$F$16+I10*Parameters!$F$25+G10*Parameters!$F$30 -> 1106.784 | O10: =B10*Parameters!$F$19 -> 4000 | P10: =M10-N10-O10 -> 733.58481 | Q10: =Parameters!$F$21 -> 1000 | R10: =P10-Q10 -> -266.41519 | S10: =IF(A10<1+Parameters!$F$31,0,INDEX($M$5:$M$40,A10-Parameters!$F$31)) -> 5472.7345 | T10: =T9+M10-S10 -> 5840.3688 | U10: =S10-N10-O10-Q10 -> -634.04954 | V10: =V9+U10 -> -14717.038 | W10: =(1-Parameters!$F$7)*(C10-E10)+(1-Parameters!$F$8)*(D10+E10) -> 737.856 | X10: =Parameters!$F$7*(C10-E10)+Parameters!$F$8*Parameters!$F$9*(D10+E10) -> 2213.1924 | Y10: =Parameters!$F$8*(1-Parameters!$F$9)*(D10+E10) -> 738.23161 | Z10: =POWER(1/(1+Parameters!$F$32),A10-1)*(M10-N10) -> 4503.8435
A11: 7 | B11: =Parameters!$F$20 -> 1000 | C11: =X10+B11 -> 3213.1924 | D11: =Y10 -> 738.23161 | E11: =Parameters!$F$6*C11 -> 321.31924 | F11: =IF(Parameters!$F$5=1,E11,0) -> 0 | G11: =Parameters!$F$27*G10+F11 -> 0 | H11: =IF(AND(Parameters!$F$5=1,Parameters!$F$26=1),SUMPRODUCT(--($A$5:A11<A11),--(MOD(A11-$A$5:A11,Parameters!$F$28)=0),$F$5:F11,POWER(Parameters!$F$27,IF(A11-$A$5:A11=0,1,A11-$A$5:A11))),0) -> 0 | I11: =Parameters!$F$23*I10+B11*Parameters!$F$22 -> 0 | J11: =E11*Parameters!$F$14*(1-Parameters!$F$15) -> 6105.0655 | K11: =H11*Parameters!$F$29 -> 0 | L11: =I11*Parameters!$F$24 -> 0 | M11: =J11+K11+L11 -> 6105.0655 | N11: =C11*Parameters!$F$17+D11*Parameters!$F$18+E11*Parameters!$F$16+I11*Parameters!$F$25+G11*Parameters!$F$30 -> 1185.4272 | O11: =B11*Parameters!$F$19 -> 4000 | P11: =M11-N11-O11 -> 919.63835 | Q11: =Parameters!$F$21 -> 1000 | R11: =P11-Q11 -> -80.361654 | S11: =IF(A11<1+Parameters!$F$31,0,INDEX($M$5:$M$40,A11-Parameters!$F$31)) -> 5840.3688 | T11: =T10+M11-S11 -> 6105.0655 | U11: =S11-N11-O11-Q11 -> -345.05839 | V11: =V10+U11 -> -15062.097 | W11: =(1-Parameters!$F$7)*(C11-E11)+(1-Parameters!$F$8)*(D11+E11) -> 790.2848 | X11: =Parameters!$F$7*(C11-E11)+Parameters!$F$8*Parameters!$F$9*(D11+E11) -> 2313.4985 | Y11: =Parameters!$F$8*(1-Parameters!$F$9)*(D11+E11) -> 847.64068 | Z11: =POWER(1/(1+Parameters!$F$32),A11-1)*(M11-N11) -> 4634.5219
A12: 8 | B12: =Parameters!$F$20 -> 1000 | C12: =X11+B12 -> 3313.4985 | D12: =Y11 -> 847.64068 | E12: =Parameters!$F$6*C12 -> 331.34985 | F12: =IF(Parameters!$F$5=1,E12,0) -> 0 | G12: =Parameters!$F$27*G11+F12 -> 0 | H12: =IF(AND(Parameters!$F$5=1,Parameters!$F$26=1),SUMPRODUCT(--($A$5:A12<A12),--(MOD(A12-$A$5:A12,Parameters!$F$28)=0),$F$5:F12,POWER(Parameters!$F$27,IF(A12-$A$5:A12=0,1,A12-$A$5:A12))),0) -> 0 | I12: =Parameters!$F$23*I11+B12*Parameters!$F$22 -> 0 | J12: =E12*Parameters!$F$14*(1-Parameters!$F$15) -> 6295.6472 | K12: =H12*Parameters!$F$29 -> 0 | L12: =I12*Parameters!$F$24 -> 0 | M12: =J12+K12+L12 -> 6295.6472 | N12: =C12*Parameters!$F$17+D12*Parameters!$F$18+E12*Parameters!$F$16+I12*Parameters!$F$25+G12*Parameters!$F$30 -> 1248.3418 | O12: =B12*Parameters!$F$19 -> 4000 | P12: =M12-N12-O12 -> 1047.3054 | Q12: =Parameters!$F$21 -> 1000 | R12: =P12-Q12 -> 47.305433 | S12: =IF(A12<1+Parameters!$F$31,0,INDEX($M$5:$M$40,A12-Parameters!$F$31)) -> 6105.0655 | T12: =T11+M12-S12 -> 6295.6472 | U12: =S12-N12-O12-Q12 -> -143.27621 | V12: =V11+U12 -> -15205.373 | W12: =(1-Parameters!$F$7)*(C12-E12)+(1-Parameters!$F$8)*(D12+E12) -> 832.22784 | X12: =Parameters!$F$7*(C12-E12)+Parameters!$F$8*Parameters!$F$9*(D12+E12) -> 2385.7189 | Y12: =Parameters!$F$8*(1-Parameters!$F$9)*(D12+E12) -> 943.19242 | Z12: =POWER(1/(1+Parameters!$F$32),A12-1)*(M12-N12) -> 4707.7129
A13: 9 | B13: =Parameters!$F$20 -> 1000 | C13: =X12+B13 -> 3385.7189 | D13: =Y12 -> 943.19242 | E13: =Parameters!$F$6*C13 -> 338.57189 | F13: =IF(Parameters!$F$5=1,E13,0) -> 0 | G13: =Parameters!$F$27*G12+F13 -> 0 | H13: =IF(AND(Parameters!$F$5=1,Parameters!$F$26=1),SUMPRODUCT(--($A$5:A13<A13),--(MOD(A13-$A$5:A13,Parameters!$F$28)=0),$F$5:F13,POWER(Parameters!$F$27,IF(A13-$A$5:A13=0,1,A13-$A$5:A13))),0) -> 0 | I13: =Parameters!$F$23*I12+B13*Parameters!$F$22 -> 0 | J13: =E13*Parameters!$F$14*(1-Parameters!$F$15) -> 6432.866 | K13: =H13*Parameters!$F$29 -> 0 | L13: =I13*Parameters!$F$24 -> 0 | M13: =J13+K13+L13 -> 6432.866 | N13: =C13*Parameters!$F$17+D13*Parameters!$F$18+E13*Parameters!$F$16+I13*Parameters!$F$25+G13*Parameters!$F$30 -> 1298.6734 | O13: =B13*Parameters!$F$19 -> 4000 | P13: =M13-N13-O13 -> 1134.1926 | Q13: =Parameters!$F$21 -> 1000 | R13: =P13-Q13 -> 134.19257 | S13: =IF(A13<1+Parameters!$F$31,0,INDEX($M$5:$M$40,A13-Parameters!$F$31)) -> 6295.6472 | T13: =T12+M13-S13 -> 6432.866 | U13: =S13-N13-O13-Q13 -> -3.0262148 | V13: =V12+U13 -> -15208.399 | W13: =(1-Parameters!$F$7)*(C13-E13)+(1-Parameters!$F$8)*(D13+E13) -> 865.78227 | X13: =Parameters!$F$7*(C13-E13)+Parameters!$F$8*Parameters!$F$9*(D13+E13) -> 2437.7176 | Y13: =Parameters!$F$8*(1-Parameters!$F$9)*(D13+E13) -> 1025.4115 | Z13: =POWER(1/(1+Parameters!$F$32),A13-1)*(M13-N13) -> 4741.3407
A14: 10 | B14: =Parameters!$F$20 -> 1000 | C14: =X13+B14 -> 3437.7176 | D14: =Y13 -> 1025.4115 | E14: =Parameters!$F$6*C14 -> 343.77176 | F14: =IF(Parameters!$F$5=1,E14,0) -> 0 | G14: =Parameters!$F$27*G13+F14 -> 0 | H14: =IF(AND(Parameters!$F$5=1,Parameters!$F$26=1),SUMPRODUCT(--($A$5:A14<A14),--(MOD(A14-$A$5:A14,Parameters!$F$28)=0),$F$5:F14,POWER(Parameters!$F$27,IF(A14-$A$5:A14=0,1,A14-$A$5:A14))),0) -> 0 | I14: =Parameters!$F$23*I13+B14*Parameters!$F$22 -> 0 | J14: =E14*Parameters!$F$14*(1-Parameters!$F$15) -> 6531.6635 | K14: =H14*Parameters!$F$29 -> 0 | L14: =I14*Parameters!$F$24 -> 0 | M14: =J14+K14+L14 -> 6531.6635 | N14: =C14*Parameters!$F$17+D14*Parameters!$F$18+E14*Parameters!$F$16+I14*Parameters!$F$25+G14*Parameters!$F$30 -> 1338.9387 | O14: =B14*Parameters!$F$19 -> 4000 | P14: =M14-N14-O14 -> 1192.7248 | Q14: =Parameters!$F$21 -> 1000 | R14: =P14-Q14 -> 192.72478 | S14: =IF(A14<1+Parameters!$F$31,0,INDEX($M$5:$M$40,A14-Parameters!$F$31)) -> 6432.866 | T14: =T13+M14-S14 -> 6531.6635 | U14: =S14-N14-O14-Q14 -> 93.927253 | V14: =V13+U14 -> -15114.472 | W14: =(1-Parameters!$F$7)*(C14-E14)+(1-Parameters!$F$8)*(D14+E14) -> 892.62582 | X14: =Parameters!$F$7*(C14-E14)+Parameters!$F$8*Parameters!$F$9*(D14+E14) -> 2475.1567 | Y14: =Parameters!$F$8*(1-Parameters!$F$9)*(D14+E14) -> 1095.3466 | Z14: =POWER(1/(1+Parameters!$F$32),A14-1)*(M14-N14) -> 4747.9151
A15: 11 | B15: =Parameters!$F$20 -> 1000 | C15: =X14+B15 -> 3475.1567 | D15: =Y14 -> 1095.3466 | E15: =Parameters!$F$6*C15 -> 347.51567 | F15: =IF(Parameters!$F$5=1,E15,0) -> 0 | G15: =Parameters!$F$27*G14+F15 -> 0 | H15: =IF(AND(Parameters!$F$5=1,Parameters!$F$26=1),SUMPRODUCT(--($A$5:A15<A15),--(MOD(A15-$A$5:A15,Parameters!$F$28)=0),$F$5:F15,POWER(Parameters!$F$27,IF(A15-$A$5:A15=0,1,A15-$A$5:A15))),0) -> 0 | I15: =Parameters!$F$23*I14+B15*Parameters!$F$22 -> 0 | J15: =E15*Parameters!$F$14*(1-Parameters!$F$15) -> 6602.7977 | K15: =H15*Parameters!$F$29 -> 0 | L15: =I15*Parameters!$F$24 -> 0 | M15: =J15+K15+L15 -> 6602.7977 | N15: =C15*Parameters!$F$17+D15*Parameters!$F$18+E15*Parameters!$F$16+I15*Parameters!$F$25+G15*Parameters!$F$30 -> 1371.151 | O15: =B15*Parameters!$F$19 -> 4000 | P15: =M15-N15-O15 -> 1231.6467 | Q15: =Parameters!$F$21 -> 1000 | R15: =P15-Q15 -> 231.64674 | S15: =IF(A15<1+Parameters!$F$31,0,INDEX($M$5:$M$40,A15-Parameters!$F$31)) -> 6531.6635 | T15: =T14+M15-S15 -> 6602.7977 | U15: =S15-N15-O15-Q15 -> 160.51252 | V15: =V14+U15 -> -14953.959 | W15: =(1-Parameters!$F$7)*(C15-E15)+(1-Parameters!$F$8)*(D15+E15) -> 914.10065 | X15: =Parameters!$F$7*(C15-E15)+Parameters!$F$8*Parameters!$F$9*(D15+E15) -> 2502.1128 | Y15: =Parameters!$F$8*(1-Parameters!$F$9)*(D15+E15) -> 1154.2898 | Z15: =POWER(1/(1+Parameters!$F$32),A15-1)*(M15-N15) -> 4736.1415
A16: 12 | B16: =Parameters!$F$20 -> 1000 | C16: =X15+B16 -> 3502.1128 | D16: =Y15 -> 1154.2898 | E16: =Parameters!$F$6*C16 -> 350.21128 | F16: =IF(Parameters!$F$5=1,E16,0) -> 0 | G16: =Parameters!$F$27*G15+F16 -> 0 | H16: =IF(AND(Parameters!$F$5=1,Parameters!$F$26=1),SUMPRODUCT(--($A$5:A16<A16),--(MOD(A16-$A$5:A16,Parameters!$F$28)=0),$F$5:F16,POWER(Parameters!$F$27,IF(A16-$A$5:A16=0,1,A16-$A$5:A16))),0) -> 0 | I16: =Parameters!$F$23*I15+B16*Parameters!$F$22 -> 0 | J16: =E16*Parameters!$F$14*(1-Parameters!$F$15) -> 6654.0144 | K16: =H16*Parameters!$F$29 -> 0 | L16: =I16*Parameters!$F$24 -> 0 | M16: =J16+K16+L16 -> 6654.0144 | N16: =C16*Parameters!$F$17+D16*Parameters!$F$18+E16*Parameters!$F$16+I16*Parameters!$F$25+G16*Parameters!$F$30 -> 1396.9208 | O16: =B16*Parameters!$F$19 -> 4000 | P16: =M16-N16-O16 -> 1257.0936 | Q16: =Parameters!$F$21 -> 1000 | R16: =P16-Q16 -> 257.09358 | S16: =IF(A16<1+Parameters!$F$31,0,INDEX($M$5:$M$40,A16-Parameters!$F$31)) -> 6602.7977 | T16: =T15+M16-S16 -> 6654.0144 | U16: =S16-N16-O16-Q16 -> 205.87694 | V16: =V15+U16 -> -14748.082 | W16: =(1-Parameters!$F$7)*(C16-E16)+(1-Parameters!$F$8)*(D16+E16) -> 931.28052 | X16: =Parameters!$F$7*(C16-E16)+Parameters!$F$8*Parameters!$F$9*(D16+E16) -> 2521.5212 | Y16: =Parameters!$F$8*(1-Parameters!$F$9)*(D16+E16) -> 1203.6009 | Z16: =POWER(1/(1+Parameters!$F$32),A16-1)*(M16-N16) -> 4712.0577
A17: 13 | B17: =Parameters!$F$20 -> 1000 | C17: =X16+B17 -> 3521.5212 | D17: =Y16 -> 1203.6009 | E17: =Parameters!$F$6*C17 -> 352.15212 | F17: =IF(Parameters!$F$5=1,E17,0) -> 0 | G17: =Parameters!$F$27*G16+F17 -> 0 | H17: =IF(AND(Parameters!$F$5=1,Parameters!$F$26=1),SUMPRODUCT(--($A$5:A17<A17),--(MOD(A17-$A$5:A17,Parameters!$F$28)=0),$F$5:F17,POWER(Parameters!$F$27,IF(A17-$A$5:A17=0,1,A17-$A$5:A17))),0) -> 0 | I17: =Parameters!$F$23*I16+B17*Parameters!$F$22 -> 0 | J17: =E17*Parameters!$F$14*(1-Parameters!$F$15) -> 6690.8903 | K17: =H17*Parameters!$F$29 -> 0 | L17: =I17*Parameters!$F$24 -> 0 | M17: =J17+K17+L17 -> 6690.8903 | N17: =C17*Parameters!$F$17+D17*Parameters!$F$18+E17*Parameters!$F$16+I17*Parameters!$F$25+G17*Parameters!$F$30 -> 1417.5366 | O17: =B17*Parameters!$F$19 -> 4000 | P17: =M17-N17-O17 -> 1273.3537 | Q17: =Parameters!$F$21 -> 1000 | R17: =P17-Q17 -> 273.35371 | S17: =IF(A17<1+Parameters!$F$31,0,INDEX($M$5:$M$40,A17-Parameters!$F$31)) -> 6654.0144 | T17: =T16+M17-S17 -> 6690.8903 | U17: =S17-N17-O17-Q17 -> 236.47773 | V17: =V16+U17 -> -14511.605 | W17: =(1-Parameters!$F$7)*(C17-E17)+(1-Parameters!$F$8)*(D17+E17) -> 945.02442 | X17: =Parameters!$F$7*(C17-E17)+Parameters!$F$8*Parameters!$F$9*(D17+E17) -> 2535.4953 | Y17: =Parameters!$F$8*(1-Parameters!$F$9)*(D17+E17) -> 1244.6024 | Z17: =POWER(1/(1+Parameters!$F$32),A17-1)*(M17-N17) -> 4679.8337
... A40: 36 | B40: =Parameters!$F$20 -> 1000 | C40: =X39+B40 -> 3571.4025 | D40: =Y39 -> 1426.9749 | E40: =Parameters!$F$6*C40 -> 357.14025 | F40: =IF(Parameters!$F$5=1,E40,0) -> 0 | G40: =Parameters!$F$27*G39+F40 -> 0 | H40: =IF(AND(Parameters!$F$5=1,Parameters!$F$26=1),SUMPRODUCT(--($A$5:A40<A40),--(MOD(A40-$A$5:A40,Parameters!$F$28)=0),$F$5:F40,POWER(Parameters!$F$27,IF(A40-$A$5:A40=0,1,A40-$A$5:A40))),0) -> 0 | I40: =Parameters!$F$23*I39+B40*Parameters!$F$22 -> 0 | J40: =E40*Parameters!$F$14*(1-Parameters!$F$15) -> 6785.6647 | K40: =H40*Parameters!$F$29 -> 0 | L40: =I40*Parameters!$F$24 -> 0 | M40: =J40+K40+L40 -> 6785.6647 | N40: =C40*Parameters!$F$17+D40*Parameters!$F$18+E40*Parameters!$F$16+I40*Parameters!$F$25+G40*Parameters!$F$30 -> 1499.5132 | O40: =B40*Parameters!$F$19 -> 4000 | P40: =M40-N40-O40 -> 1286.1515 | Q40: =Parameters!$F$21 -> 1000 | R40: =P40-Q40 -> 286.15145 | S40: =IF(A40<1+Parameters!$F$31,0,INDEX($M$5:$M$40,A40-Parameters!$F$31)) -> 6785.6454 | T40: =T39+M40-S40 -> 6785.6647 | U40: =S40-N40-O40-Q40 -> 286.13216 | V40: =V39+U40 -> -7950.7495 | W40: =(1-Parameters!$F$7)*(C40-E40)+(1-Parameters!$F$8)*(D40+E40) -> 999.67548 | X40: =Parameters!$F$7*(C40-E40)+Parameters!$F$8*Parameters!$F$9*(D40+E40) -> 2571.4098 | Y40: =Parameters!$F$8*(1-Parameters!$F$9)*(D40+E40) -> 1427.2922 | Z40: =POWER(1/(1+Parameters!$F$32),A40-1)*(M40-N40) -> 3731.5694
A43: One acquired-owner cohort: V36 before acquisition/fixed costs. This isolates the mathematical unit value.
A44: Month | B44: Acquired | C44: E eligible | D44: M completed active | E44: Payable events | F44: New policies | G44: Active policies | H44: Renewed policies | I44: Billed subscribers | J44: Initial revenue | K44: Renewal revenue | L44: Software revenue | M44: Total revenue | N44: Variable cost | O44: Acquisition cost | P44: Contribution | Q44: Fixed cost | R44: Operating result | S44: Cash receipts | T44: Receivables | U44: Cash surplus | V44: Cumulative cash | W44: Churned opportunity owners | X44: Next E | Y44: Next M | Z44: Discounted contribution before CAC
A45: 1 | B45: =1 -> 1 | C45: =B45 -> 1 | D45: =0 -> 0 | E45: =Parameters!$F$6*C45 -> 0.1 | F45: =IF(Parameters!$F$5=1,E45,0) -> 0 | G45: =F45 -> 0 | H45: =IF(AND(Parameters!$F$5=1,Parameters!$F$26=1),SUMPRODUCT(--($A$45:A45<A45),--(MOD(A45-$A$45:A45,Parameters!$F$28)=0),$F$45:F45,POWER(Parameters!$F$27,IF(A45-$A$45:A45=0,1,A45-$A$45:A45))),0) -> 0 | I45: =B45*Parameters!$F$22 -> 0 | J45: =E45*Parameters!$F$14*(1-Parameters!$F$15) -> 1.9 | K45: =H45*Parameters!$F$29 -> 0 | L45: =I45*Parameters!$F$24 -> 0 | M45: =J45+K45+L45 -> 1.9 | N45: =C45*Parameters!$F$17+D45*Parameters!$F$18+E45*Parameters!$F$16+I45*Parameters!$F$25+G45*Parameters!$F$30 -> 0.3 | O45: =0 -> 0 | P45: =M45-N45-O45 -> 1.6 | Q45: =0 -> 0 | R45: =P45-Q45 -> 1.6 | S45: =IF(A45<1+Parameters!$F$31,0,INDEX($M$45:$M$80,A45-Parameters!$F$31)) -> 0 | T45: =M45-S45 -> 1.9 | U45: =S45-N45-O45-Q45 -> -0.3 | V45: =U45 -> -0.3 | W45: =(1-Parameters!$F$7)*(C45-E45)+(1-Parameters!$F$8)*(D45+E45) -> 0.2 | X45: =Parameters!$F$7*(C45-E45)+Parameters!$F$8*Parameters!$F$9*(D45+E45) -> 0.72 | Y45: =Parameters!$F$8*(1-Parameters!$F$9)*(D45+E45) -> 0.08 | Z45: =POWER(1/(1+Parameters!$F$32),A45-1)*(M45-N45) -> 1.6
A46: 2 | B46: =0 -> 0 | C46: =X45+B46 -> 0.72 | D46: =Y45 -> 0.08 | E46: =Parameters!$F$6*C46 -> 0.072 | F46: =IF(Parameters!$F$5=1,E46,0) -> 0 | G46: =Parameters!$F$27*G45+F46 -> 0 | H46: =IF(AND(Parameters!$F$5=1,Parameters!$F$26=1),SUMPRODUCT(--($A$45:A46<A46),--(MOD(A46-$A$45:A46,Parameters!$F$28)=0),$F$45:F46,POWER(Parameters!$F$27,IF(A46-$A$45:A46=0,1,A46-$A$45:A46))),0) -> 0 | I46: =Parameters!$F$23*I45+B46*Parameters!$F$22 -> 0 | J46: =E46*Parameters!$F$14*(1-Parameters!$F$15) -> 1.368 | K46: =H46*Parameters!$F$29 -> 0 | L46: =I46*Parameters!$F$24 -> 0 | M46: =J46+K46+L46 -> 1.368 | N46: =C46*Parameters!$F$17+D46*Parameters!$F$18+E46*Parameters!$F$16+I46*Parameters!$F$25+G46*Parameters!$F$30 -> 0.24 | O46: =0 -> 0 | P46: =M46-N46-O46 -> 1.128 | Q46: =0 -> 0 | R46: =P46-Q46 -> 1.128 | S46: =IF(A46<1+Parameters!$F$31,0,INDEX($M$45:$M$80,A46-Parameters!$F$31)) -> 1.9 | T46: =T45+M46-S46 -> 1.368 | U46: =S46-N46-O46-Q46 -> 1.66 | V46: =V45+U46 -> 1.36 | W46: =(1-Parameters!$F$7)*(C46-E46)+(1-Parameters!$F$8)*(D46+E46) -> 0.16 | X46: =Parameters!$F$7*(C46-E46)+Parameters!$F$8*Parameters!$F$9*(D46+E46) -> 0.5184 | Y46: =Parameters!$F$8*(1-Parameters!$F$9)*(D46+E46) -> 0.1216 | Z46: =POWER(1/(1+Parameters!$F$32),A46-1)*(M46-N46) -> 1.1168317
A47: 3 | B47: =0 -> 0 | C47: =X46+B47 -> 0.5184 | D47: =Y46 -> 0.1216 | E47: =Parameters!$F$6*C47 -> 0.05184 | F47: =IF(Parameters!$F$5=1,E47,0) -> 0 | G47: =Parameters!$F$27*G46+F47 -> 0 | H47: =IF(AND(Parameters!$F$5=1,Parameters!$F$26=1),SUMPRODUCT(--($A$45:A47<A47),--(MOD(A47-$A$45:A47,Parameters!$F$28)=0),$F$45:F47,POWER(Parameters!$F$27,IF(A47-$A$45:A47=0,1,A47-$A$45:A47))),0) -> 0 | I47: =Parameters!$F$23*I46+B47*Parameters!$F$22 -> 0 | J47: =E47*Parameters!$F$14*(1-Parameters!$F$15) -> 0.98496 | K47: =H47*Parameters!$F$29 -> 0 | L47: =I47*Parameters!$F$24 -> 0 | M47: =J47+K47+L47 -> 0.98496 | N47: =C47*Parameters!$F$17+D47*Parameters!$F$18+E47*Parameters!$F$16+I47*Parameters!$F$25+G47*Parameters!$F$30 -> 0.192 | O47: =0 -> 0 | P47: =M47-N47-O47 -> 0.79296 | Q47: =0 -> 0 | R47: =P47-Q47 -> 0.79296 | S47: =IF(A47<1+Parameters!$F$31,0,INDEX($M$45:$M$80,A47-Parameters!$F$31)) -> 1.368 | T47: =T46+M47-S47 -> 0.98496 | U47: =S47-N47-O47-Q47 -> 1.176 | V47: =V46+U47 -> 2.536 | W47: =(1-Parameters!$F$7)*(C47-E47)+(1-Parameters!$F$8)*(D47+E47) -> 0.128 | X47: =Parameters!$F$7*(C47-E47)+Parameters!$F$8*Parameters!$F$9*(D47+E47) -> 0.373248 | Y47: =Parameters!$F$8*(1-Parameters!$F$9)*(D47+E47) -> 0.138752 | Z47: =POWER(1/(1+Parameters!$F$32),A47-1)*(M47-N47) -> 0.77733556
A48: 4 | B48: =0 -> 0 | C48: =X47+B48 -> 0.373248 | D48: =Y47 -> 0.138752 | E48: =Parameters!$F$6*C48 -> 0.0373248 | F48: =IF(Parameters!$F$5=1,E48,0) -> 0 | G48: =Parameters!$F$27*G47+F48 -> 0 | H48: =IF(AND(Parameters!$F$5=1,Parameters!$F$26=1),SUMPRODUCT(--($A$45:A48<A48),--(MOD(A48-$A$45:A48,Parameters!$F$28)=0),$F$45:F48,POWER(Parameters!$F$27,IF(A48-$A$45:A48=0,1,A48-$A$45:A48))),0) -> 0 | I48: =Parameters!$F$23*I47+B48*Parameters!$F$22 -> 0 | J48: =E48*Parameters!$F$14*(1-Parameters!$F$15) -> 0.7091712 | K48: =H48*Parameters!$F$29 -> 0 | L48: =I48*Parameters!$F$24 -> 0 | M48: =J48+K48+L48 -> 0.7091712 | N48: =C48*Parameters!$F$17+D48*Parameters!$F$18+E48*Parameters!$F$16+I48*Parameters!$F$25+G48*Parameters!$F$30 -> 0.1536 | O48: =0 -> 0 | P48: =M48-N48-O48 -> 0.5555712 | Q48: =0 -> 0 | R48: =P48-Q48 -> 0.5555712 | S48: =IF(A48<1+Parameters!$F$31,0,INDEX($M$45:$M$80,A48-Parameters!$F$31)) -> 0.98496 | T48: =T47+M48-S48 -> 0.7091712 | U48: =S48-N48-O48-Q48 -> 0.83136 | V48: =V47+U48 -> 3.36736 | W48: =(1-Parameters!$F$7)*(C48-E48)+(1-Parameters!$F$8)*(D48+E48) -> 0.1024 | X48: =Parameters!$F$7*(C48-E48)+Parameters!$F$8*Parameters!$F$9*(D48+E48) -> 0.26873856 | Y48: =Parameters!$F$8*(1-Parameters!$F$9)*(D48+E48) -> 0.14086144 | Z48: =POWER(1/(1+Parameters!$F$32),A48-1)*(M48-N48) -> 0.53923193
A49: 5 | B49: =0 -> 0 | C49: =X48+B49 -> 0.26873856 | D49: =Y48 -> 0.14086144 | E49: =Parameters!$F$6*C49 -> 0.026873856 | F49: =IF(Parameters!$F$5=1,E49,0) -> 0 | G49: =Parameters!$F$27*G48+F49 -> 0 | H49: =IF(AND(Parameters!$F$5=1,Parameters!$F$26=1),SUMPRODUCT(--($A$45:A49<A49),--(MOD(A49-$A$45:A49,Parameters!$F$28)=0),$F$45:F49,POWER(Parameters!$F$27,IF(A49-$A$45:A49=0,1,A49-$A$45:A49))),0) -> 0 | I49: =Parameters!$F$23*I48+B49*Parameters!$F$22 -> 0 | J49: =E49*Parameters!$F$14*(1-Parameters!$F$15) -> 0.51060326 | K49: =H49*Parameters!$F$29 -> 0 | L49: =I49*Parameters!$F$24 -> 0 | M49: =J49+K49+L49 -> 0.51060326 | N49: =C49*Parameters!$F$17+D49*Parameters!$F$18+E49*Parameters!$F$16+I49*Parameters!$F$25+G49*Parameters!$F$30 -> 0.12288 | O49: =0 -> 0 | P49: =M49-N49-O49 -> 0.38772326 | Q49: =0 -> 0 | R49: =P49-Q49 -> 0.38772326 | S49: =IF(A49<1+Parameters!$F$31,0,INDEX($M$45:$M$80,A49-Parameters!$F$31)) -> 0.7091712 | T49: =T48+M49-S49 -> 0.51060326 | U49: =S49-N49-O49-Q49 -> 0.5862912 | V49: =V48+U49 -> 3.9536512 | W49: =(1-Parameters!$F$7)*(C49-E49)+(1-Parameters!$F$8)*(D49+E49) -> 0.08192 | X49: =Parameters!$F$7*(C49-E49)+Parameters!$F$8*Parameters!$F$9*(D49+E49) -> 0.19349176 | Y49: =Parameters!$F$8*(1-Parameters!$F$9)*(D49+E49) -> 0.13418824 | Z49: =POWER(1/(1+Parameters!$F$32),A49-1)*(M49-N49) -> 0.37259444
A50: 6 | B50: =0 -> 0 | C50: =X49+B50 -> 0.19349176 | D50: =Y49 -> 0.13418824 | E50: =Parameters!$F$6*C50 -> 0.019349176 | F50: =IF(Parameters!$F$5=1,E50,0) -> 0 | G50: =Parameters!$F$27*G49+F50 -> 0 | H50: =IF(AND(Parameters!$F$5=1,Parameters!$F$26=1),SUMPRODUCT(--($A$45:A50<A50),--(MOD(A50-$A$45:A50,Parameters!$F$28)=0),$F$45:F50,POWER(Parameters!$F$27,IF(A50-$A$45:A50=0,1,A50-$A$45:A50))),0) -> 0 | I50: =Parameters!$F$23*I49+B50*Parameters!$F$22 -> 0 | J50: =E50*Parameters!$F$14*(1-Parameters!$F$15) -> 0.36763435 | K50: =H50*Parameters!$F$29 -> 0 | L50: =I50*Parameters!$F$24 -> 0 | M50: =J50+K50+L50 -> 0.36763435 | N50: =C50*Parameters!$F$17+D50*Parameters!$F$18+E50*Parameters!$F$16+I50*Parameters!$F$25+G50*Parameters!$F$30 -> 0.098304 | O50: =0 -> 0 | P50: =M50-N50-O50 -> 0.26933035 | Q50: =0 -> 0 | R50: =P50-Q50 -> 0.26933035 | S50: =IF(A50<1+Parameters!$F$31,0,INDEX($M$45:$M$80,A50-Parameters!$F$31)) -> 0.51060326 | T50: =T49+M50-S50 -> 0.36763435 | U50: =S50-N50-O50-Q50 -> 0.41229926 | V50: =V49+U50 -> 4.3659505 | W50: =(1-Parameters!$F$7)*(C50-E50)+(1-Parameters!$F$8)*(D50+E50) -> 0.065536 | X50: =Parameters!$F$7*(C50-E50)+Parameters!$F$8*Parameters!$F$9*(D50+E50) -> 0.13931407 | Y50: =Parameters!$F$8*(1-Parameters!$F$9)*(D50+E50) -> 0.12282993 | Z50: =POWER(1/(1+Parameters!$F$32),A50-1)*(M50-N50) -> 0.25625859
A51: 7 | B51: =0 -> 0 | C51: =X50+B51 -> 0.13931407 | D51: =Y50 -> 0.12282993 | E51: =Parameters!$F$6*C51 -> 0.013931407 | F51: =IF(Parameters!$F$5=1,E51,0) -> 0 | G51: =Parameters!$F$27*G50+F51 -> 0 | H51: =IF(AND(Parameters!$F$5=1,Parameters!$F$26=1),SUMPRODUCT(--($A$45:A51<A51),--(MOD(A51-$A$45:A51,Parameters!$F$28)=0),$F$45:F51,POWER(Parameters!$F$27,IF(A51-$A$45:A51=0,1,A51-$A$45:A51))),0) -> 0 | I51: =Parameters!$F$23*I50+B51*Parameters!$F$22 -> 0 | J51: =E51*Parameters!$F$14*(1-Parameters!$F$15) -> 0.26469673 | K51: =H51*Parameters!$F$29 -> 0 | L51: =I51*Parameters!$F$24 -> 0 | M51: =J51+K51+L51 -> 0.26469673 | N51: =C51*Parameters!$F$17+D51*Parameters!$F$18+E51*Parameters!$F$16+I51*Parameters!$F$25+G51*Parameters!$F$30 -> 0.0786432 | O51: =0 -> 0 | P51: =M51-N51-O51 -> 0.18605353 | Q51: =0 -> 0 | R51: =P51-Q51 -> 0.18605353 | S51: =IF(A51<1+Parameters!$F$31,0,INDEX($M$45:$M$80,A51-Parameters!$F$31)) -> 0.36763435 | T51: =T50+M51-S51 -> 0.26469673 | U51: =S51-N51-O51-Q51 -> 0.28899115 | V51: =V50+U51 -> 4.6549416 | W51: =(1-Parameters!$F$7)*(C51-E51)+(1-Parameters!$F$8)*(D51+E51) -> 0.0524288 | X51: =Parameters!$F$7*(C51-E51)+Parameters!$F$8*Parameters!$F$9*(D51+E51) -> 0.10030613 | Y51: =Parameters!$F$8*(1-Parameters!$F$9)*(D51+E51) -> 0.10940907 | Z51: =POWER(1/(1+Parameters!$F$32),A51-1)*(M51-N51) -> 0.17527084
A52: 8 | B52: =0 -> 0 | C52: =X51+B52 -> 0.10030613 | D52: =Y51 -> 0.10940907 | E52: =Parameters!$F$6*C52 -> 0.010030613 | F52: =IF(Parameters!$F$5=1,E52,0) -> 0 | G52: =Parameters!$F$27*G51+F52 -> 0 | H52: =IF(AND(Parameters!$F$5=1,Parameters!$F$26=1),SUMPRODUCT(--($A$45:A52<A52),--(MOD(A52-$A$45:A52,Parameters!$F$28)=0),$F$45:F52,POWER(Parameters!$F$27,IF(A52-$A$45:A52=0,1,A52-$A$45:A52))),0) -> 0 | I52: =Parameters!$F$23*I51+B52*Parameters!$F$22 -> 0 | J52: =E52*Parameters!$F$14*(1-Parameters!$F$15) -> 0.19058165 | K52: =H52*Parameters!$F$29 -> 0 | L52: =I52*Parameters!$F$24 -> 0 | M52: =J52+K52+L52 -> 0.19058165 | N52: =C52*Parameters!$F$17+D52*Parameters!$F$18+E52*Parameters!$F$16+I52*Parameters!$F$25+G52*Parameters!$F$30 -> 0.06291456 | O52: =0 -> 0 | P52: =M52-N52-O52 -> 0.12766709 | Q52: =0 -> 0 | R52: =P52-Q52 -> 0.12766709 | S52: =IF(A52<1+Parameters!$F$31,0,INDEX($M$45:$M$80,A52-Parameters!$F$31)) -> 0.26469673 | T52: =T51+M52-S52 -> 0.19058165 | U52: =S52-N52-O52-Q52 -> 0.20178217 | V52: =V51+U52 -> 4.8567238 | W52: =(1-Parameters!$F$7)*(C52-E52)+(1-Parameters!$F$8)*(D52+E52) -> 0.04194304 | X52: =Parameters!$F$7*(C52-E52)+Parameters!$F$8*Parameters!$F$9*(D52+E52) -> 0.072220414 | Y52: =Parameters!$F$8*(1-Parameters!$F$9)*(D52+E52) -> 0.095551746 | Z52: =POWER(1/(1+Parameters!$F$32),A52-1)*(M52-N52) -> 0.1190774
A53: 9 | B53: =0 -> 0 | C53: =X52+B53 -> 0.072220414 | D53: =Y52 -> 0.095551746 | E53: =Parameters!$F$6*C53 -> 0.0072220414 | F53: =IF(Parameters!$F$5=1,E53,0) -> 0 | G53: =Parameters!$F$27*G52+F53 -> 0 | H53: =IF(AND(Parameters!$F$5=1,Parameters!$F$26=1),SUMPRODUCT(--($A$45:A53<A53),--(MOD(A53-$A$45:A53,Parameters!$F$28)=0),$F$45:F53,POWER(Parameters!$F$27,IF(A53-$A$45:A53=0,1,A53-$A$45:A53))),0) -> 0 | I53: =Parameters!$F$23*I52+B53*Parameters!$F$22 -> 0 | J53: =E53*Parameters!$F$14*(1-Parameters!$F$15) -> 0.13721879 | K53: =H53*Parameters!$F$29 -> 0 | L53: =I53*Parameters!$F$24 -> 0 | M53: =J53+K53+L53 -> 0.13721879 | N53: =C53*Parameters!$F$17+D53*Parameters!$F$18+E53*Parameters!$F$16+I53*Parameters!$F$25+G53*Parameters!$F$30 -> 0.050331648 | O53: =0 -> 0 | P53: =M53-N53-O53 -> 0.086887138 | Q53: =0 -> 0 | R53: =P53-Q53 -> 0.086887138 | S53: =IF(A53<1+Parameters!$F$31,0,INDEX($M$45:$M$80,A53-Parameters!$F$31)) -> 0.19058165 | T53: =T52+M53-S53 -> 0.13721879 | U53: =S53-N53-O53-Q53 -> 0.14025 | V53: =V52+U53 -> 4.9969738 | W53: =(1-Parameters!$F$7)*(C53-E53)+(1-Parameters!$F$8)*(D53+E53) -> 0.033554432 | X53: =Parameters!$F$7*(C53-E53)+Parameters!$F$8*Parameters!$F$9*(D53+E53) -> 0.051998698 | Y53: =Parameters!$F$8*(1-Parameters!$F$9)*(D53+E53) -> 0.08221903 | Z53: =POWER(1/(1+Parameters!$F$32),A53-1)*(M53-N53) -> 0.080238814
A54: 10 | B54: =0 -> 0 | C54: =X53+B54 -> 0.051998698 | D54: =Y53 -> 0.08221903 | E54: =Parameters!$F$6*C54 -> 0.0051998698 | F54: =IF(Parameters!$F$5=1,E54,0) -> 0 | G54: =Parameters!$F$27*G53+F54 -> 0 | H54: =IF(AND(Parameters!$F$5=1,Parameters!$F$26=1),SUMPRODUCT(--($A$45:A54<A54),--(MOD(A54-$A$45:A54,Parameters!$F$28)=0),$F$45:F54,POWER(Parameters!$F$27,IF(A54-$A$45:A54=0,1,A54-$A$45:A54))),0) -> 0 | I54: =Parameters!$F$23*I53+B54*Parameters!$F$22 -> 0 | J54: =E54*Parameters!$F$14*(1-Parameters!$F$15) -> 0.098797526 | K54: =H54*Parameters!$F$29 -> 0 | L54: =I54*Parameters!$F$24 -> 0 | M54: =J54+K54+L54 -> 0.098797526 | N54: =C54*Parameters!$F$17+D54*Parameters!$F$18+E54*Parameters!$F$16+I54*Parameters!$F$25+G54*Parameters!$F$30 -> 0.040265318 | O54: =0 -> 0 | P54: =M54-N54-O54 -> 0.058532207 | Q54: =0 -> 0 | R54: =P54-Q54 -> 0.058532207 | S54: =IF(A54<1+Parameters!$F$31,0,INDEX($M$45:$M$80,A54-Parameters!$F$31)) -> 0.13721879 | T54: =T53+M54-S54 -> 0.098797526 | U54: =S54-N54-O54-Q54 -> 0.096953467 | V54: =V53+U54 -> 5.0939273 | W54: =(1-Parameters!$F$7)*(C54-E54)+(1-Parameters!$F$8)*(D54+E54) -> 0.026843546 | X54: =Parameters!$F$7*(C54-E54)+Parameters!$F$8*Parameters!$F$9*(D54+E54) -> 0.037439062 | Y54: =Parameters!$F$8*(1-Parameters!$F$9)*(D54+E54) -> 0.06993512 | Z54: =POWER(1/(1+Parameters!$F$32),A54-1)*(M54-N54) -> 0.053518328
A55: 11 | B55: =0 -> 0 | C55: =X54+B55 -> 0.037439062 | D55: =Y54 -> 0.06993512 | E55: =Parameters!$F$6*C55 -> 0.0037439062 | F55: =IF(Parameters!$F$5=1,E55,0) -> 0 | G55: =Parameters!$F$27*G54+F55 -> 0 | H55: =IF(AND(Parameters!$F$5=1,Parameters!$F$26=1),SUMPRODUCT(--($A$45:A55<A55),--(MOD(A55-$A$45:A55,Parameters!$F$28)=0),$F$45:F55,POWER(Parameters!$F$27,IF(A55-$A$45:A55=0,1,A55-$A$45:A55))),0) -> 0 | I55: =Parameters!$F$23*I54+B55*Parameters!$F$22 -> 0 | J55: =E55*Parameters!$F$14*(1-Parameters!$F$15) -> 0.071134219 | K55: =H55*Parameters!$F$29 -> 0 | L55: =I55*Parameters!$F$24 -> 0 | M55: =J55+K55+L55 -> 0.071134219 | N55: =C55*Parameters!$F$17+D55*Parameters!$F$18+E55*Parameters!$F$16+I55*Parameters!$F$25+G55*Parameters!$F$30 -> 0.032212255 | O55: =0 -> 0 | P55: =M55-N55-O55 -> 0.038921964 | Q55: =0 -> 0 | R55: =P55-Q55 -> 0.038921964 | S55: =IF(A55<1+Parameters!$F$31,0,INDEX($M$45:$M$80,A55-Parameters!$F$31)) -> 0.098797526 | T55: =T54+M55-S55 -> 0.071134219 | U55: =S55-N55-O55-Q55 -> 0.066585271 | V55: =V54+U55 -> 5.1605125 | W55: =(1-Parameters!$F$7)*(C55-E55)+(1-Parameters!$F$8)*(D55+E55) -> 0.021474836 | X55: =Parameters!$F$7*(C55-E55)+Parameters!$F$8*Parameters!$F$9*(D55+E55) -> 0.026956125 | Y55: =Parameters!$F$8*(1-Parameters!$F$9)*(D55+E55) -> 0.058943221 | Z55: =POWER(1/(1+Parameters!$F$32),A55-1)*(M55-N55) -> 0.035235546
A56: 12 | B56: =0 -> 0 | C56: =X55+B56 -> 0.026956125 | D56: =Y55 -> 0.058943221 | E56: =Parameters!$F$6*C56 -> 0.0026956125 | F56: =IF(Parameters!$F$5=1,E56,0) -> 0 | G56: =Parameters!$F$27*G55+F56 -> 0 | H56: =IF(AND(Parameters!$F$5=1,Parameters!$F$26=1),SUMPRODUCT(--($A$45:A56<A56),--(MOD(A56-$A$45:A56,Parameters!$F$28)=0),$F$45:F56,POWER(Parameters!$F$27,IF(A56-$A$45:A56=0,1,A56-$A$45:A56))),0) -> 0 | I56: =Parameters!$F$23*I55+B56*Parameters!$F$22 -> 0 | J56: =E56*Parameters!$F$14*(1-Parameters!$F$15) -> 0.051216637 | K56: =H56*Parameters!$F$29 -> 0 | L56: =I56*Parameters!$F$24 -> 0 | M56: =J56+K56+L56 -> 0.051216637 | N56: =C56*Parameters!$F$17+D56*Parameters!$F$18+E56*Parameters!$F$16+I56*Parameters!$F$25+G56*Parameters!$F$30 -> 0.025769804 | O56: =0 -> 0 | P56: =M56-N56-O56 -> 0.025446834 | Q56: =0 -> 0 | R56: =P56-Q56 -> 0.025446834 | S56: =IF(A56<1+Parameters!$F$31,0,INDEX($M$45:$M$80,A56-Parameters!$F$31)) -> 0.071134219 | T56: =T55+M56-S56 -> 0.051216637 | U56: =S56-N56-O56-Q56 -> 0.045364415 | V56: =V55+U56 -> 5.2058769 | W56: =(1-Parameters!$F$7)*(C56-E56)+(1-Parameters!$F$8)*(D56+E56) -> 0.017179869 | X56: =Parameters!$F$7*(C56-E56)+Parameters!$F$8*Parameters!$F$9*(D56+E56) -> 0.01940841 | Y56: =Parameters!$F$8*(1-Parameters!$F$9)*(D56+E56) -> 0.049311067 | Z56: =POWER(1/(1+Parameters!$F$32),A56-1)*(M56-N56) -> 0.022808601
A57: 13 | B57: =0 -> 0 | C57: =X56+B57 -> 0.01940841 | D57: =Y56 -> 0.049311067 | E57: =Parameters!$F$6*C57 -> 0.001940841 | F57: =IF(Parameters!$F$5=1,E57,0) -> 0 | G57: =Parameters!$F$27*G56+F57 -> 0 | H57: =IF(AND(Parameters!$F$5=1,Parameters!$F$26=1),SUMPRODUCT(--($A$45:A57<A57),--(MOD(A57-$A$45:A57,Parameters!$F$28)=0),$F$45:F57,POWER(Parameters!$F$27,IF(A57-$A$45:A57=0,1,A57-$A$45:A57))),0) -> 0 | I57: =Parameters!$F$23*I56+B57*Parameters!$F$22 -> 0 | J57: =E57*Parameters!$F$14*(1-Parameters!$F$15) -> 0.036875979 | K57: =H57*Parameters!$F$29 -> 0 | L57: =I57*Parameters!$F$24 -> 0 | M57: =J57+K57+L57 -> 0.036875979 | N57: =C57*Parameters!$F$17+D57*Parameters!$F$18+E57*Parameters!$F$16+I57*Parameters!$F$25+G57*Parameters!$F$30 -> 0.020615843 | O57: =0 -> 0 | P57: =M57-N57-O57 -> 0.016260136 | Q57: =0 -> 0 | R57: =P57-Q57 -> 0.016260136 | S57: =IF(A57<1+Parameters!$F$31,0,INDEX($M$45:$M$80,A57-Parameters!$F$31)) -> 0.051216637 | T57: =T56+M57-S57 -> 0.036875979 | U57: =S57-N57-O57-Q57 -> 0.030600794 | V57: =V56+U57 -> 5.2364777 | W57: =(1-Parameters!$F$7)*(C57-E57)+(1-Parameters!$F$8)*(D57+E57) -> 0.013743895 | X57: =Parameters!$F$7*(C57-E57)+Parameters!$F$8*Parameters!$F$9*(D57+E57) -> 0.013974055 | Y57: =Parameters!$F$8*(1-Parameters!$F$9)*(D57+E57) -> 0.041001526 | Z57: =POWER(1/(1+Parameters!$F$32),A57-1)*(M57-N57) -> 0.014430045
... A80: 36 | B80: =0 -> 0 | C80: =X79+B80 -> 1.0154005e-05 | D80: =Y79 -> 0.00039549419 | E80: =Parameters!$F$6*C80 -> 1.0154005e-06 | F80: =IF(Parameters!$F$5=1,E80,0) -> 0 | G80: =Parameters!$F$27*G79+F80 -> 0 | H80: =IF(AND(Parameters!$F$5=1,Parameters!$F$26=1),SUMPRODUCT(--($A$45:A80<A80),--(MOD(A80-$A$45:A80,Parameters!$F$28)=0),$F$45:F80,POWER(Parameters!$F$27,IF(A80-$A$45:A80=0,1,A80-$A$45:A80))),0) -> 0 | I80: =Parameters!$F$23*I79+B80*Parameters!$F$22 -> 0 | J80: =E80*Parameters!$F$14*(1-Parameters!$F$15) -> 1.929261e-05 | K80: =H80*Parameters!$F$29 -> 0 | L80: =I80*Parameters!$F$24 -> 0 | M80: =J80+K80+L80 -> 1.929261e-05 | N80: =C80*Parameters!$F$17+D80*Parameters!$F$18+E80*Parameters!$F$16+I80*Parameters!$F$25+G80*Parameters!$F$30 -> 0.00012169446 | O80: =0 -> 0 | P80: =M80-N80-O80 -> -0.00010240185 | Q80: =0 -> 0 | R80: =P80-Q80 -> -0.00010240185 | S80: =IF(A80<1+Parameters!$F$31,0,INDEX($M$45:$M$80,A80-Parameters!$F$31)) -> 2.6795291e-05 | T80: =T79+M80-S80 -> 1.929261e-05 | U80: =S80-N80-O80-Q80 -> -9.4899167e-05 | V80: =V79+U80 -> 5.2861322 | W80: =(1-Parameters!$F$7)*(C80-E80)+(1-Parameters!$F$8)*(D80+E80) -> 8.1129638e-05 | X80: =Parameters!$F$7*(C80-E80)+Parameters!$F$8*Parameters!$F$9*(D80+E80) -> 7.3108836e-06 | Y80: =Parameters!$F$8*(1-Parameters!$F$9)*(D80+E80) -> 0.00031720767 | Z80: =POWER(1/(1+Parameters!$F$32),A80-1)*(M80-N80) -> -7.2286919e-05

Sheet S4
A1: S4 — New eligible opportunities
A2: All parameters are illustrative. Top block: calendar cohorts. Lower block: one acquired owner, no CAC/fixed cost, for customer-value calculation.
A4: Month | B4: Acquired | C4: E eligible | D4: M completed active | E4: Payable events | F4: New policies | G4: Active policies | H4: Renewed policies | I4: Billed subscribers | J4: Initial revenue | K4: Renewal revenue | L4: Software revenue | M4: Total revenue | N4: Variable cost | O4: Acquisition cost | P4: Contribution | Q4: Fixed cost | R4: Operating result | S4: Cash receipts | T4: Receivables | U4: Cash surplus | V4: Cumulative cash | W4: Churned opportunity owners | X4: Next E | Y4: Next M | Z4: Discounted contribution before CAC
A5: 1 | B5: =Parameters!$G$20 -> 1000 | C5: =B5 -> 1000 | D5: =0 -> 0 | E5: =Parameters!$G$6*C5 -> 100 | F5: =IF(Parameters!$G$5=1,E5,0) -> 0 | G5: =F5 -> 0 | H5: =IF(AND(Parameters!$G$5=1,Parameters!$G$26=1),SUMPRODUCT(--($A$5:A5<A5),--(MOD(A5-$A$5:A5,Parameters!$G$28)=0),$F$5:F5,POWER(Parameters!$G$27,IF(A5-$A$5:A5=0,1,A5-$A$5:A5))),0) -> 0 | I5: =B5*Parameters!$G$22 -> 0 | J5: =E5*Parameters!$G$14*(1-Parameters!$G$15) -> 1900 | K5: =H5*Parameters!$G$29 -> 0 | L5: =I5*Parameters!$G$24 -> 0 | M5: =J5+K5+L5 -> 1900 | N5: =C5*Parameters!$G$17+D5*Parameters!$G$18+E5*Parameters!$G$16+I5*Parameters!$G$25+G5*Parameters!$G$30 -> 300 | O5: =B5*Parameters!$G$19 -> 4000 | P5: =M5-N5-O5 -> -2400 | Q5: =Parameters!$G$21 -> 1000 | R5: =P5-Q5 -> -3400 | S5: =IF(A5<1+Parameters!$G$31,0,INDEX($M$5:$M$40,A5-Parameters!$G$31)) -> 0 | T5: =M5-S5 -> 1900 | U5: =S5-N5-O5-Q5 -> -5300 | V5: =U5 -> -5300 | W5: =(1-Parameters!$G$7)*(C5-E5)+(1-Parameters!$G$8)*(D5+E5) -> 200 | X5: =Parameters!$G$7*(C5-E5)+Parameters!$G$8*Parameters!$G$9*(D5+E5) -> 728 | Y5: =Parameters!$G$8*(1-Parameters!$G$9)*(D5+E5) -> 72 | Z5: =POWER(1/(1+Parameters!$G$32),A5-1)*(M5-N5) -> 1600
A6: 2 | B6: =Parameters!$G$20 -> 1000 | C6: =X5+B6 -> 1728 | D6: =Y5 -> 72 | E6: =Parameters!$G$6*C6 -> 172.8 | F6: =IF(Parameters!$G$5=1,E6,0) -> 0 | G6: =Parameters!$G$27*G5+F6 -> 0 | H6: =IF(AND(Parameters!$G$5=1,Parameters!$G$26=1),SUMPRODUCT(--($A$5:A6<A6),--(MOD(A6-$A$5:A6,Parameters!$G$28)=0),$F$5:F6,POWER(Parameters!$G$27,IF(A6-$A$5:A6=0,1,A6-$A$5:A6))),0) -> 0 | I6: =Parameters!$G$23*I5+B6*Parameters!$G$22 -> 0 | J6: =E6*Parameters!$G$14*(1-Parameters!$G$15) -> 3283.2 | K6: =H6*Parameters!$G$29 -> 0 | L6: =I6*Parameters!$G$24 -> 0 | M6: =J6+K6+L6 -> 3283.2 | N6: =C6*Parameters!$G$17+D6*Parameters!$G$18+E6*Parameters!$G$16+I6*Parameters!$G$25+G6*Parameters!$G$30 -> 540 | O6: =B6*Parameters!$G$19 -> 4000 | P6: =M6-N6-O6 -> -1256.8 | Q6: =Parameters!$G$21 -> 1000 | R6: =P6-Q6 -> -2256.8 | S6: =IF(A6<1+Parameters!$G$31,0,INDEX($M$5:$M$40,A6-Parameters!$G$31)) -> 1900 | T6: =T5+M6-S6 -> 3283.2 | U6: =S6-N6-O6-Q6 -> -3640 | V6: =V5+U6 -> -8940 | W6: =(1-Parameters!$G$7)*(C6-E6)+(1-Parameters!$G$8)*(D6+E6) -> 360 | X6: =Parameters!$G$7*(C6-E6)+Parameters!$G$8*Parameters!$G$9*(D6+E6) -> 1263.744 | Y6: =Parameters!$G$8*(1-Parameters!$G$9)*(D6+E6) -> 176.256 | Z6: =POWER(1/(1+Parameters!$G$32),A6-1)*(M6-N6) -> 2716.0396
A7: 3 | B7: =Parameters!$G$20 -> 1000 | C7: =X6+B7 -> 2263.744 | D7: =Y6 -> 176.256 | E7: =Parameters!$G$6*C7 -> 226.3744 | F7: =IF(Parameters!$G$5=1,E7,0) -> 0 | G7: =Parameters!$G$27*G6+F7 -> 0 | H7: =IF(AND(Parameters!$G$5=1,Parameters!$G$26=1),SUMPRODUCT(--($A$5:A7<A7),--(MOD(A7-$A$5:A7,Parameters!$G$28)=0),$F$5:F7,POWER(Parameters!$G$27,IF(A7-$A$5:A7=0,1,A7-$A$5:A7))),0) -> 0 | I7: =Parameters!$G$23*I6+B7*Parameters!$G$22 -> 0 | J7: =E7*Parameters!$G$14*(1-Parameters!$G$15) -> 4301.1136 | K7: =H7*Parameters!$G$29 -> 0 | L7: =I7*Parameters!$G$24 -> 0 | M7: =J7+K7+L7 -> 4301.1136 | N7: =C7*Parameters!$G$17+D7*Parameters!$G$18+E7*Parameters!$G$16+I7*Parameters!$G$25+G7*Parameters!$G$30 -> 732 | O7: =B7*Parameters!$G$19 -> 4000 | P7: =M7-N7-O7 -> -430.8864 | Q7: =Parameters!$G$21 -> 1000 | R7: =P7-Q7 -> -1430.8864 | S7: =IF(A7<1+Parameters!$G$31,0,INDEX($M$5:$M$40,A7-Parameters!$G$31)) -> 3283.2 | T7: =T6+M7-S7 -> 4301.1136 | U7: =S7-N7-O7-Q7 -> -2448.8 | V7: =V6+U7 -> -11388.8 | W7: =(1-Parameters!$G$7)*(C7-E7)+(1-Parameters!$G$8)*(D7+E7) -> 488 | X7: =Parameters!$G$7*(C7-E7)+Parameters!$G$8*Parameters!$G$9*(D7+E7) -> 1662.1061 | Y7: =Parameters!$G$8*(1-Parameters!$G$9)*(D7+E7) -> 289.89389 | Z7: =POWER(1/(1+Parameters!$G$32),A7-1)*(M7-N7) -> 3498.788
A8: 4 | B8: =Parameters!$G$20 -> 1000 | C8: =X7+B8 -> 2662.1061 | D8: =Y7 -> 289.89389 | E8: =Parameters!$G$6*C8 -> 266.21061 | F8: =IF(Parameters!$G$5=1,E8,0) -> 0 | G8: =Parameters!$G$27*G7+F8 -> 0 | H8: =IF(AND(Parameters!$G$5=1,Parameters!$G$26=1),SUMPRODUCT(--($A$5:A8<A8),--(MOD(A8-$A$5:A8,Parameters!$G$28)=0),$F$5:F8,POWER(Parameters!$G$27,IF(A8-$A$5:A8=0,1,A8-$A$5:A8))),0) -> 0 | I8: =Parameters!$G$23*I7+B8*Parameters!$G$22 -> 0 | J8: =E8*Parameters!$G$14*(1-Parameters!$G$15) -> 5058.0016 | K8: =H8*Parameters!$G$29 -> 0 | L8: =I8*Parameters!$G$24 -> 0 | M8: =J8+K8+L8 -> 5058.0016 | N8: =C8*Parameters!$G$17+D8*Parameters!$G$18+E8*Parameters!$G$16+I8*Parameters!$G$25+G8*Parameters!$G$30 -> 885.6 | O8: =B8*Parameters!$G$19 -> 4000 | P8: =M8-N8-O8 -> 172.40161 | Q8: =Parameters!$G$21 -> 1000 | R8: =P8-Q8 -> -827.59839 | S8: =IF(A8<1+Parameters!$G$31,0,INDEX($M$5:$M$40,A8-Parameters!$G$31)) -> 4301.1136 | T8: =T7+M8-S8 -> 5058.0016 | U8: =S8-N8-O8-Q8 -> -1584.4864 | V8: =V7+U8 -> -12973.286 | W8: =(1-Parameters!$G$7)*(C8-E8)+(1-Parameters!$G$8)*(D8+E8) -> 590.4 | X8: =Parameters!$G$7*(C8-E8)+Parameters!$G$8*Parameters!$G$9*(D8+E8) -> 1961.2048 | Y8: =Parameters!$G$8*(1-Parameters!$G$9)*(D8+E8) -> 400.39524 | Z8: =POWER(1/(1+Parameters!$G$32),A8-1)*(M8-N8) -> 4049.6919
A9: 5 | B9: =Parameters!$G$20 -> 1000 | C9: =X8+B9 -> 2961.2048 | D9: =Y8 -> 400.39524 | E9: =Parameters!$G$6*C9 -> 296.12048 | F9: =IF(Parameters!$G$5=1,E9,0) -> 0 | G9: =Parameters!$G$27*G8+F9 -> 0 | H9: =IF(AND(Parameters!$G$5=1,Parameters!$G$26=1),SUMPRODUCT(--($A$5:A9<A9),--(MOD(A9-$A$5:A9,Parameters!$G$28)=0),$F$5:F9,POWER(Parameters!$G$27,IF(A9-$A$5:A9=0,1,A9-$A$5:A9))),0) -> 0 | I9: =Parameters!$G$23*I8+B9*Parameters!$G$22 -> 0 | J9: =E9*Parameters!$G$14*(1-Parameters!$G$15) -> 5626.289 | K9: =H9*Parameters!$G$29 -> 0 | L9: =I9*Parameters!$G$24 -> 0 | M9: =J9+K9+L9 -> 5626.289 | N9: =C9*Parameters!$G$17+D9*Parameters!$G$18+E9*Parameters!$G$16+I9*Parameters!$G$25+G9*Parameters!$G$30 -> 1008.48 | O9: =B9*Parameters!$G$19 -> 4000 | P9: =M9-N9-O9 -> 617.80905 | Q9: =Parameters!$G$21 -> 1000 | R9: =P9-Q9 -> -382.19095 | S9: =IF(A9<1+Parameters!$G$31,0,INDEX($M$5:$M$40,A9-Parameters!$G$31)) -> 5058.0016 | T9: =T8+M9-S9 -> 5626.289 | U9: =S9-N9-O9-Q9 -> -950.47839 | V9: =V8+U9 -> -13923.765 | W9: =(1-Parameters!$G$7)*(C9-E9)+(1-Parameters!$G$8)*(D9+E9) -> 672.32 | X9: =Parameters!$G$7*(C9-E9)+Parameters!$G$8*Parameters!$G$9*(D9+E9) -> 2187.7887 | Y9: =Parameters!$G$8*(1-Parameters!$G$9)*(D9+E9) -> 501.49132 | Z9: =POWER(1/(1+Parameters!$G$32),A9-1)*(M9-N9) -> 4437.6237
A10: 6 | B10: =Parameters!$G$20 -> 1000 | C10: =X9+B10 -> 3187.7887 | D10: =Y9 -> 501.49132 | E10: =Parameters!$G$6*C10 -> 318.77887 | F10: =IF(Parameters!$G$5=1,E10,0) -> 0 | G10: =Parameters!$G$27*G9+F10 -> 0 | H10: =IF(AND(Parameters!$G$5=1,Parameters!$G$26=1),SUMPRODUCT(--($A$5:A10<A10),--(MOD(A10-$A$5:A10,Parameters!$G$28)=0),$F$5:F10,POWER(Parameters!$G$27,IF(A10-$A$5:A10=0,1,A10-$A$5:A10))),0) -> 0 | I10: =Parameters!$G$23*I9+B10*Parameters!$G$22 -> 0 | J10: =E10*Parameters!$G$14*(1-Parameters!$G$15) -> 6056.7985 | K10: =H10*Parameters!$G$29 -> 0 | L10: =I10*Parameters!$G$24 -> 0 | M10: =J10+K10+L10 -> 6056.7985 | N10: =C10*Parameters!$G$17+D10*Parameters!$G$18+E10*Parameters!$G$16+I10*Parameters!$G$25+G10*Parameters!$G$30 -> 1106.784 | O10: =B10*Parameters!$G$19 -> 4000 | P10: =M10-N10-O10 -> 950.0145 | Q10: =Parameters!$G$21 -> 1000 | R10: =P10-Q10 -> -49.985499 | S10: =IF(A10<1+Parameters!$G$31,0,INDEX($M$5:$M$40,A10-Parameters!$G$31)) -> 5626.289 | T10: =T9+M10-S10 -> 6056.7985 | U10: =S10-N10-O10-Q10 -> -480.49495 | V10: =V9+U10 -> -14404.26 | W10: =(1-Parameters!$G$7)*(C10-E10)+(1-Parameters!$G$8)*(D10+E10) -> 737.856 | X10: =Parameters!$G$7*(C10-E10)+Parameters!$G$8*Parameters!$G$9*(D10+E10) -> 2360.8295 | Y10: =Parameters!$G$8*(1-Parameters!$G$9)*(D10+E10) -> 590.59453 | Z10: =POWER(1/(1+Parameters!$G$32),A10-1)*(M10-N10) -> 4709.769
A11: 7 | B11: =Parameters!$G$20 -> 1000 | C11: =X10+B11 -> 3360.8295 | D11: =Y10 -> 590.59453 | E11: =Parameters!$G$6*C11 -> 336.08295 | F11: =IF(Parameters!$G$5=1,E11,0) -> 0 | G11: =Parameters!$G$27*G10+F11 -> 0 | H11: =IF(AND(Parameters!$G$5=1,Parameters!$G$26=1),SUMPRODUCT(--($A$5:A11<A11),--(MOD(A11-$A$5:A11,Parameters!$G$28)=0),$F$5:F11,POWER(Parameters!$G$27,IF(A11-$A$5:A11=0,1,A11-$A$5:A11))),0) -> 0 | I11: =Parameters!$G$23*I10+B11*Parameters!$G$22 -> 0 | J11: =E11*Parameters!$G$14*(1-Parameters!$G$15) -> 6385.576 | K11: =H11*Parameters!$G$29 -> 0 | L11: =I11*Parameters!$G$24 -> 0 | M11: =J11+K11+L11 -> 6385.576 | N11: =C11*Parameters!$G$17+D11*Parameters!$G$18+E11*Parameters!$G$16+I11*Parameters!$G$25+G11*Parameters!$G$30 -> 1185.4272 | O11: =B11*Parameters!$G$19 -> 4000 | P11: =M11-N11-O11 -> 1200.1488 | Q11: =Parameters!$G$21 -> 1000 | R11: =P11-Q11 -> 200.14879 | S11: =IF(A11<1+Parameters!$G$31,0,INDEX($M$5:$M$40,A11-Parameters!$G$31)) -> 6056.7985 | T11: =T10+M11-S11 -> 6385.576 | U11: =S11-N11-O11-Q11 -> -128.6287 | V11: =V10+U11 -> -14532.888 | W11: =(1-Parameters!$G$7)*(C11-E11)+(1-Parameters!$G$8)*(D11+E11) -> 790.2848 | X11: =Parameters!$G$7*(C11-E11)+Parameters!$G$8*Parameters!$G$9*(D11+E11) -> 2493.9314 | Y11: =Parameters!$G$8*(1-Parameters!$G$9)*(D11+E11) -> 667.20778 | Z11: =POWER(1/(1+Parameters!$G$32),A11-1)*(M11-N11) -> 4898.7754
A12: 8 | B12: =Parameters!$G$20 -> 1000 | C12: =X11+B12 -> 3493.9314 | D12: =Y11 -> 667.20778 | E12: =Parameters!$G$6*C12 -> 349.39314 | F12: =IF(Parameters!$G$5=1,E12,0) -> 0 | G12: =Parameters!$G$27*G11+F12 -> 0 | H12: =IF(AND(Parameters!$G$5=1,Parameters!$G$26=1),SUMPRODUCT(--($A$5:A12<A12),--(MOD(A12-$A$5:A12,Parameters!$G$28)=0),$F$5:F12,POWER(Parameters!$G$27,IF(A12-$A$5:A12=0,1,A12-$A$5:A12))),0) -> 0 | I12: =Parameters!$G$23*I11+B12*Parameters!$G$22 -> 0 | J12: =E12*Parameters!$G$14*(1-Parameters!$G$15) -> 6638.4697 | K12: =H12*Parameters!$G$29 -> 0 | L12: =I12*Parameters!$G$24 -> 0 | M12: =J12+K12+L12 -> 6638.4697 | N12: =C12*Parameters!$G$17+D12*Parameters!$G$18+E12*Parameters!$G$16+I12*Parameters!$G$25+G12*Parameters!$G$30 -> 1248.3418 | O12: =B12*Parameters!$G$19 -> 4000 | P12: =M12-N12-O12 -> 1390.1279 | Q12: =Parameters!$G$21 -> 1000 | R12: =P12-Q12 -> 390.12793 | S12: =IF(A12<1+Parameters!$G$31,0,INDEX($M$5:$M$40,A12-Parameters!$G$31)) -> 6385.576 | T12: =T11+M12-S12 -> 6638.4697 | U12: =S12-N12-O12-Q12 -> 137.23423 | V12: =V11+U12 -> -14395.654 | W12: =(1-Parameters!$G$7)*(C12-E12)+(1-Parameters!$G$8)*(D12+E12) -> 832.22784 | X12: =Parameters!$G$7*(C12-E12)+Parameters!$G$8*Parameters!$G$9*(D12+E12) -> 2596.9587 | Y12: =Parameters!$G$8*(1-Parameters!$G$9)*(D12+E12) -> 731.95267 | Z12: =POWER(1/(1+Parameters!$G$32),A12-1)*(M12-N12) -> 5027.4696
A13: 9 | B13: =Parameters!$G$20 -> 1000 | C13: =X12+B13 -> 3596.9587 | D13: =Y12 -> 731.95267 | E13: =Parameters!$G$6*C13 -> 359.69587 | F13: =IF(Parameters!$G$5=1,E13,0) -> 0 | G13: =Parameters!$G$27*G12+F13 -> 0 | H13: =IF(AND(Parameters!$G$5=1,Parameters!$G$26=1),SUMPRODUCT(--($A$5:A13<A13),--(MOD(A13-$A$5:A13,Parameters!$G$28)=0),$F$5:F13,POWER(Parameters!$G$27,IF(A13-$A$5:A13=0,1,A13-$A$5:A13))),0) -> 0 | I13: =Parameters!$G$23*I12+B13*Parameters!$G$22 -> 0 | J13: =E13*Parameters!$G$14*(1-Parameters!$G$15) -> 6834.2215 | K13: =H13*Parameters!$G$29 -> 0 | L13: =I13*Parameters!$G$24 -> 0 | M13: =J13+K13+L13 -> 6834.2215 | N13: =C13*Parameters!$G$17+D13*Parameters!$G$18+E13*Parameters!$G$16+I13*Parameters!$G$25+G13*Parameters!$G$30 -> 1298.6734 | O13: =B13*Parameters!$G$19 -> 4000 | P13: =M13-N13-O13 -> 1535.5481 | Q13: =Parameters!$G$21 -> 1000 | R13: =P13-Q13 -> 535.54811 | S13: =IF(A13<1+Parameters!$G$31,0,INDEX($M$5:$M$40,A13-Parameters!$G$31)) -> 6638.4697 | T13: =T12+M13-S13 -> 6834.2215 | U13: =S13-N13-O13-Q13 -> 339.79628 | V13: =V12+U13 -> -14055.858 | W13: =(1-Parameters!$G$7)*(C13-E13)+(1-Parameters!$G$8)*(D13+E13) -> 865.78227 | X13: =Parameters!$G$7*(C13-E13)+Parameters!$G$8*Parameters!$G$9*(D13+E13) -> 2677.1421 | Y13: =Parameters!$G$8*(1-Parameters!$G$9)*(D13+E13) -> 785.98695 | Z13: =POWER(1/(1+Parameters!$G$32),A13-1)*(M13-N13) -> 5111.9858
A14: 10 | B14: =Parameters!$G$20 -> 1000 | C14: =X13+B14 -> 3677.1421 | D14: =Y13 -> 785.98695 | E14: =Parameters!$G$6*C14 -> 367.71421 | F14: =IF(Parameters!$G$5=1,E14,0) -> 0 | G14: =Parameters!$G$27*G13+F14 -> 0 | H14: =IF(AND(Parameters!$G$5=1,Parameters!$G$26=1),SUMPRODUCT(--($A$5:A14<A14),--(MOD(A14-$A$5:A14,Parameters!$G$28)=0),$F$5:F14,POWER(Parameters!$G$27,IF(A14-$A$5:A14=0,1,A14-$A$5:A14))),0) -> 0 | I14: =Parameters!$G$23*I13+B14*Parameters!$G$22 -> 0 | J14: =E14*Parameters!$G$14*(1-Parameters!$G$15) -> 6986.5701 | K14: =H14*Parameters!$G$29 -> 0 | L14: =I14*Parameters!$G$24 -> 0 | M14: =J14+K14+L14 -> 6986.5701 | N14: =C14*Parameters!$G$17+D14*Parameters!$G$18+E14*Parameters!$G$16+I14*Parameters!$G$25+G14*Parameters!$G$30 -> 1338.9387 | O14: =B14*Parameters!$G$19 -> 4000 | P14: =M14-N14-O14 -> 1647.6313 | Q14: =Parameters!$G$21 -> 1000 | R14: =P14-Q14 -> 647.63134 | S14: =IF(A14<1+Parameters!$G$31,0,INDEX($M$5:$M$40,A14-Parameters!$G$31)) -> 6834.2215 | T14: =T13+M14-S14 -> 6986.5701 | U14: =S14-N14-O14-Q14 -> 495.28279 | V14: =V13+U14 -> -13560.575 | W14: =(1-Parameters!$G$7)*(C14-E14)+(1-Parameters!$G$8)*(D14+E14) -> 892.62582 | X14: =Parameters!$G$7*(C14-E14)+Parameters!$G$8*Parameters!$G$9*(D14+E14) -> 2739.8384 | Y14: =Parameters!$G$8*(1-Parameters!$G$9)*(D14+E14) -> 830.66484 | Z14: =POWER(1/(1+Parameters!$G$32),A14-1)*(M14-N14) -> 5163.8542
A15: 11 | B15: =Parameters!$G$20 -> 1000 | C15: =X14+B15 -> 3739.8384 | D15: =Y14 -> 830.66484 | E15: =Parameters!$G$6*C15 -> 373.98384 | F15: =IF(Parameters!$G$5=1,E15,0) -> 0 | G15: =Parameters!$G$27*G14+F15 -> 0 | H15: =IF(AND(Parameters!$G$5=1,Parameters!$G$26=1),SUMPRODUCT(--($A$5:A15<A15),--(MOD(A15-$A$5:A15,Parameters!$G$28)=0),$F$5:F15,POWER(Parameters!$G$27,IF(A15-$A$5:A15=0,1,A15-$A$5:A15))),0) -> 0 | I15: =Parameters!$G$23*I14+B15*Parameters!$G$22 -> 0 | J15: =E15*Parameters!$G$14*(1-Parameters!$G$15) -> 7105.693 | K15: =H15*Parameters!$G$29 -> 0 | L15: =I15*Parameters!$G$24 -> 0 | M15: =J15+K15+L15 -> 7105.693 | N15: =C15*Parameters!$G$17+D15*Parameters!$G$18+E15*Parameters!$G$16+I15*Parameters!$G$25+G15*Parameters!$G$30 -> 1371.151 | O15: =B15*Parameters!$G$19 -> 4000 | P15: =M15-N15-O15 -> 1734.542 | Q15: =Parameters!$G$21 -> 1000 | R15: =P15-Q15 -> 734.54205 | S15: =IF(A15<1+Parameters!$G$31,0,INDEX($M$5:$M$40,A15-Parameters!$G$31)) -> 6986.5701 | T15: =T14+M15-S15 -> 7105.693 | U15: =S15-N15-O15-Q15 -> 615.41909 | V15: =V14+U15 -> -12945.156 | W15: =(1-Parameters!$G$7)*(C15-E15)+(1-Parameters!$G$8)*(D15+E15) -> 914.10065 | X15: =Parameters!$G$7*(C15-E15)+Parameters!$G$8*Parameters!$G$9*(D15+E15) -> 2789.0556 | Y15: =Parameters!$G$8*(1-Parameters!$G$9)*(D15+E15) -> 867.34705 | Z15: =POWER(1/(1+Parameters!$G$32),A15-1)*(M15-N15) -> 5191.4061
A16: 12 | B16: =Parameters!$G$20 -> 1000 | C16: =X15+B16 -> 3789.0556 | D16: =Y15 -> 867.34705 | E16: =Parameters!$G$6*C16 -> 378.90556 | F16: =IF(Parameters!$G$5=1,E16,0) -> 0 | G16: =Parameters!$G$27*G15+F16 -> 0 | H16: =IF(AND(Parameters!$G$5=1,Parameters!$G$26=1),SUMPRODUCT(--($A$5:A16<A16),--(MOD(A16-$A$5:A16,Parameters!$G$28)=0),$F$5:F16,POWER(Parameters!$G$27,IF(A16-$A$5:A16=0,1,A16-$A$5:A16))),0) -> 0 | I16: =Parameters!$G$23*I15+B16*Parameters!$G$22 -> 0 | J16: =E16*Parameters!$G$14*(1-Parameters!$G$15) -> 7199.2056 | K16: =H16*Parameters!$G$29 -> 0 | L16: =I16*Parameters!$G$24 -> 0 | M16: =J16+K16+L16 -> 7199.2056 | N16: =C16*Parameters!$G$17+D16*Parameters!$G$18+E16*Parameters!$G$16+I16*Parameters!$G$25+G16*Parameters!$G$30 -> 1396.9208 | O16: =B16*Parameters!$G$19 -> 4000 | P16: =M16-N16-O16 -> 1802.2848 | Q16: =Parameters!$G$21 -> 1000 | R16: =P16-Q16 -> 802.28479 | S16: =IF(A16<1+Parameters!$G$31,0,INDEX($M$5:$M$40,A16-Parameters!$G$31)) -> 7105.693 | T16: =T15+M16-S16 -> 7199.2056 | U16: =S16-N16-O16-Q16 -> 708.77224 | V16: =V15+U16 -> -12236.384 | W16: =(1-Parameters!$G$7)*(C16-E16)+(1-Parameters!$G$8)*(D16+E16) -> 931.28052 | X16: =Parameters!$G$7*(C16-E16)+Parameters!$G$8*Parameters!$G$9*(D16+E16) -> 2827.8202 | Y16: =Parameters!$G$8*(1-Parameters!$G$9)*(D16+E16) -> 897.30188 | Z16: =POWER(1/(1+Parameters!$G$32),A16-1)*(M16-N16) -> 5200.7255
A17: 13 | B17: =Parameters!$G$20 -> 1000 | C17: =X16+B17 -> 3827.8202 | D17: =Y16 -> 897.30188 | E17: =Parameters!$G$6*C17 -> 382.78202 | F17: =IF(Parameters!$G$5=1,E17,0) -> 0 | G17: =Parameters!$G$27*G16+F17 -> 0 | H17: =IF(AND(Parameters!$G$5=1,Parameters!$G$26=1),SUMPRODUCT(--($A$5:A17<A17),--(MOD(A17-$A$5:A17,Parameters!$G$28)=0),$F$5:F17,POWER(Parameters!$G$27,IF(A17-$A$5:A17=0,1,A17-$A$5:A17))),0) -> 0 | I17: =Parameters!$G$23*I16+B17*Parameters!$G$22 -> 0 | J17: =E17*Parameters!$G$14*(1-Parameters!$G$15) -> 7272.8584 | K17: =H17*Parameters!$G$29 -> 0 | L17: =I17*Parameters!$G$24 -> 0 | M17: =J17+K17+L17 -> 7272.8584 | N17: =C17*Parameters!$G$17+D17*Parameters!$G$18+E17*Parameters!$G$16+I17*Parameters!$G$25+G17*Parameters!$G$30 -> 1417.5366 | O17: =B17*Parameters!$G$19 -> 4000 | P17: =M17-N17-O17 -> 1855.3218 | Q17: =Parameters!$G$21 -> 1000 | R17: =P17-Q17 -> 855.32178 | S17: =IF(A17<1+Parameters!$G$31,0,INDEX($M$5:$M$40,A17-Parameters!$G$31)) -> 7199.2056 | T17: =T16+M17-S17 -> 7272.8584 | U17: =S17-N17-O17-Q17 -> 781.66895 | V17: =V16+U17 -> -11454.715 | W17: =(1-Parameters!$G$7)*(C17-E17)+(1-Parameters!$G$8)*(D17+E17) -> 945.02442 | X17: =Parameters!$G$7*(C17-E17)+Parameters!$G$8*Parameters!$G$9*(D17+E17) -> 2858.4373 | Y17: =Parameters!$G$8*(1-Parameters!$G$9)*(D17+E17) -> 921.66041 | Z17: =POWER(1/(1+Parameters!$G$32),A17-1)*(M17-N17) -> 5196.3008
... A40: 36 | B40: =Parameters!$G$20 -> 1000 | C40: =X39+B40 -> 3976.4185 | D40: =Y39 -> 1021.9589 | E40: =Parameters!$G$6*C40 -> 397.64185 | F40: =IF(Parameters!$G$5=1,E40,0) -> 0 | G40: =Parameters!$G$27*G39+F40 -> 0 | H40: =IF(AND(Parameters!$G$5=1,Parameters!$G$26=1),SUMPRODUCT(--($A$5:A40<A40),--(MOD(A40-$A$5:A40,Parameters!$G$28)=0),$F$5:F40,POWER(Parameters!$G$27,IF(A40-$A$5:A40=0,1,A40-$A$5:A40))),0) -> 0 | I40: =Parameters!$G$23*I39+B40*Parameters!$G$22 -> 0 | J40: =E40*Parameters!$G$14*(1-Parameters!$G$15) -> 7555.1952 | K40: =H40*Parameters!$G$29 -> 0 | L40: =I40*Parameters!$G$24 -> 0 | M40: =J40+K40+L40 -> 7555.1952 | N40: =C40*Parameters!$G$17+D40*Parameters!$G$18+E40*Parameters!$G$16+I40*Parameters!$G$25+G40*Parameters!$G$30 -> 1499.5132 | O40: =B40*Parameters!$G$19 -> 4000 | P40: =M40-N40-O40 -> 2055.6819 | Q40: =Parameters!$G$21 -> 1000 | R40: =P40-Q40 -> 1055.6819 | S40: =IF(A40<1+Parameters!$G$31,0,INDEX($M$5:$M$40,A40-Parameters!$G$31)) -> 7554.7893 | T40: =T39+M40-S40 -> 7555.1952 | U40: =S40-N40-O40-Q40 -> 1055.2761 | V40: =V39+U40 -> 11787.934 | W40: =(1-Parameters!$G$7)*(C40-E40)+(1-Parameters!$G$8)*(D40+E40) -> 999.67548 | X40: =Parameters!$G$7*(C40-E40)+Parameters!$G$8*Parameters!$G$9*(D40+E40) -> 2976.5894 | Y40: =Parameters!$G$8*(1-Parameters!$G$9)*(D40+E40) -> 1022.1125 | Z40: =POWER(1/(1+Parameters!$G$32),A40-1)*(M40-N40) -> 4274.7919
A43: One acquired-owner cohort: V36 before acquisition/fixed costs. This isolates the mathematical unit value.
A44: Month | B44: Acquired | C44: E eligible | D44: M completed active | E44: Payable events | F44: New policies | G44: Active policies | H44: Renewed policies | I44: Billed subscribers | J44: Initial revenue | K44: Renewal revenue | L44: Software revenue | M44: Total revenue | N44: Variable cost | O44: Acquisition cost | P44: Contribution | Q44: Fixed cost | R44: Operating result | S44: Cash receipts | T44: Receivables | U44: Cash surplus | V44: Cumulative cash | W44: Churned opportunity owners | X44: Next E | Y44: Next M | Z44: Discounted contribution before CAC
A45: 1 | B45: =1 -> 1 | C45: =B45 -> 1 | D45: =0 -> 0 | E45: =Parameters!$G$6*C45 -> 0.1 | F45: =IF(Parameters!$G$5=1,E45,0) -> 0 | G45: =F45 -> 0 | H45: =IF(AND(Parameters!$G$5=1,Parameters!$G$26=1),SUMPRODUCT(--($A$45:A45<A45),--(MOD(A45-$A$45:A45,Parameters!$G$28)=0),$F$45:F45,POWER(Parameters!$G$27,IF(A45-$A$45:A45=0,1,A45-$A$45:A45))),0) -> 0 | I45: =B45*Parameters!$G$22 -> 0 | J45: =E45*Parameters!$G$14*(1-Parameters!$G$15) -> 1.9 | K45: =H45*Parameters!$G$29 -> 0 | L45: =I45*Parameters!$G$24 -> 0 | M45: =J45+K45+L45 -> 1.9 | N45: =C45*Parameters!$G$17+D45*Parameters!$G$18+E45*Parameters!$G$16+I45*Parameters!$G$25+G45*Parameters!$G$30 -> 0.3 | O45: =0 -> 0 | P45: =M45-N45-O45 -> 1.6 | Q45: =0 -> 0 | R45: =P45-Q45 -> 1.6 | S45: =IF(A45<1+Parameters!$G$31,0,INDEX($M$45:$M$80,A45-Parameters!$G$31)) -> 0 | T45: =M45-S45 -> 1.9 | U45: =S45-N45-O45-Q45 -> -0.3 | V45: =U45 -> -0.3 | W45: =(1-Parameters!$G$7)*(C45-E45)+(1-Parameters!$G$8)*(D45+E45) -> 0.2 | X45: =Parameters!$G$7*(C45-E45)+Parameters!$G$8*Parameters!$G$9*(D45+E45) -> 0.728 | Y45: =Parameters!$G$8*(1-Parameters!$G$9)*(D45+E45) -> 0.072 | Z45: =POWER(1/(1+Parameters!$G$32),A45-1)*(M45-N45) -> 1.6
A46: 2 | B46: =0 -> 0 | C46: =X45+B46 -> 0.728 | D46: =Y45 -> 0.072 | E46: =Parameters!$G$6*C46 -> 0.0728 | F46: =IF(Parameters!$G$5=1,E46,0) -> 0 | G46: =Parameters!$G$27*G45+F46 -> 0 | H46: =IF(AND(Parameters!$G$5=1,Parameters!$G$26=1),SUMPRODUCT(--($A$45:A46<A46),--(MOD(A46-$A$45:A46,Parameters!$G$28)=0),$F$45:F46,POWER(Parameters!$G$27,IF(A46-$A$45:A46=0,1,A46-$A$45:A46))),0) -> 0 | I46: =Parameters!$G$23*I45+B46*Parameters!$G$22 -> 0 | J46: =E46*Parameters!$G$14*(1-Parameters!$G$15) -> 1.3832 | K46: =H46*Parameters!$G$29 -> 0 | L46: =I46*Parameters!$G$24 -> 0 | M46: =J46+K46+L46 -> 1.3832 | N46: =C46*Parameters!$G$17+D46*Parameters!$G$18+E46*Parameters!$G$16+I46*Parameters!$G$25+G46*Parameters!$G$30 -> 0.24 | O46: =0 -> 0 | P46: =M46-N46-O46 -> 1.1432 | Q46: =0 -> 0 | R46: =P46-Q46 -> 1.1432 | S46: =IF(A46<1+Parameters!$G$31,0,INDEX($M$45:$M$80,A46-Parameters!$G$31)) -> 1.9 | T46: =T45+M46-S46 -> 1.3832 | U46: =S46-N46-O46-Q46 -> 1.66 | V46: =V45+U46 -> 1.36 | W46: =(1-Parameters!$G$7)*(C46-E46)+(1-Parameters!$G$8)*(D46+E46) -> 0.16 | X46: =Parameters!$G$7*(C46-E46)+Parameters!$G$8*Parameters!$G$9*(D46+E46) -> 0.535744 | Y46: =Parameters!$G$8*(1-Parameters!$G$9)*(D46+E46) -> 0.104256 | Z46: =POWER(1/(1+Parameters!$G$32),A46-1)*(M46-N46) -> 1.1318812
A47: 3 | B47: =0 -> 0 | C47: =X46+B47 -> 0.535744 | D47: =Y46 -> 0.104256 | E47: =Parameters!$G$6*C47 -> 0.0535744 | F47: =IF(Parameters!$G$5=1,E47,0) -> 0 | G47: =Parameters!$G$27*G46+F47 -> 0 | H47: =IF(AND(Parameters!$G$5=1,Parameters!$G$26=1),SUMPRODUCT(--($A$45:A47<A47),--(MOD(A47-$A$45:A47,Parameters!$G$28)=0),$F$45:F47,POWER(Parameters!$G$27,IF(A47-$A$45:A47=0,1,A47-$A$45:A47))),0) -> 0 | I47: =Parameters!$G$23*I46+B47*Parameters!$G$22 -> 0 | J47: =E47*Parameters!$G$14*(1-Parameters!$G$15) -> 1.0179136 | K47: =H47*Parameters!$G$29 -> 0 | L47: =I47*Parameters!$G$24 -> 0 | M47: =J47+K47+L47 -> 1.0179136 | N47: =C47*Parameters!$G$17+D47*Parameters!$G$18+E47*Parameters!$G$16+I47*Parameters!$G$25+G47*Parameters!$G$30 -> 0.192 | O47: =0 -> 0 | P47: =M47-N47-O47 -> 0.8259136 | Q47: =0 -> 0 | R47: =P47-Q47 -> 0.8259136 | S47: =IF(A47<1+Parameters!$G$31,0,INDEX($M$45:$M$80,A47-Parameters!$G$31)) -> 1.3832 | T47: =T46+M47-S47 -> 1.0179136 | U47: =S47-N47-O47-Q47 -> 1.1912 | V47: =V46+U47 -> 2.5512 | W47: =(1-Parameters!$G$7)*(C47-E47)+(1-Parameters!$G$8)*(D47+E47) -> 0.128 | X47: =Parameters!$G$7*(C47-E47)+Parameters!$G$8*Parameters!$G$9*(D47+E47) -> 0.39836211 | Y47: =Parameters!$G$8*(1-Parameters!$G$9)*(D47+E47) -> 0.11363789 | Z47: =POWER(1/(1+Parameters!$G$32),A47-1)*(M47-N47) -> 0.80963984
A48: 4 | B48: =0 -> 0 | C48: =X47+B48 -> 0.39836211 | D48: =Y47 -> 0.11363789 | E48: =Parameters!$G$6*C48 -> 0.039836211 | F48: =IF(Parameters!$G$5=1,E48,0) -> 0 | G48: =Parameters!$G$27*G47+F48 -> 0 | H48: =IF(AND(Parameters!$G$5=1,Parameters!$G$26=1),SUMPRODUCT(--($A$45:A48<A48),--(MOD(A48-$A$45:A48,Parameters!$G$28)=0),$F$45:F48,POWER(Parameters!$G$27,IF(A48-$A$45:A48=0,1,A48-$A$45:A48))),0) -> 0 | I48: =Parameters!$G$23*I47+B48*Parameters!$G$22 -> 0 | J48: =E48*Parameters!$G$14*(1-Parameters!$G$15) -> 0.75688801 | K48: =H48*Parameters!$G$29 -> 0 | L48: =I48*Parameters!$G$24 -> 0 | M48: =J48+K48+L48 -> 0.75688801 | N48: =C48*Parameters!$G$17+D48*Parameters!$G$18+E48*Parameters!$G$16+I48*Parameters!$G$25+G48*Parameters!$G$30 -> 0.1536 | O48: =0 -> 0 | P48: =M48-N48-O48 -> 0.60328801 | Q48: =0 -> 0 | R48: =P48-Q48 -> 0.60328801 | S48: =IF(A48<1+Parameters!$G$31,0,INDEX($M$45:$M$80,A48-Parameters!$G$31)) -> 1.0179136 | T48: =T47+M48-S48 -> 0.75688801 | U48: =S48-N48-O48-Q48 -> 0.8643136 | V48: =V47+U48 -> 3.4155136 | W48: =(1-Parameters!$G$7)*(C48-E48)+(1-Parameters!$G$8)*(D48+E48) -> 0.1024 | X48: =Parameters!$G$7*(C48-E48)+Parameters!$G$8*Parameters!$G$9*(D48+E48) -> 0.29909865 | Y48: =Parameters!$G$8*(1-Parameters!$G$9)*(D48+E48) -> 0.11050135 | Z48: =POWER(1/(1+Parameters!$G$32),A48-1)*(M48-N48) -> 0.5855454
A49: 5 | B49: =0 -> 0 | C49: =X48+B49 -> 0.29909865 | D49: =Y48 -> 0.11050135 | E49: =Parameters!$G$6*C49 -> 0.029909865 | F49: =IF(Parameters!$G$5=1,E49,0) -> 0 | G49: =Parameters!$G$27*G48+F49 -> 0 | H49: =IF(AND(Parameters!$G$5=1,Parameters!$G$26=1),SUMPRODUCT(--($A$45:A49<A49),--(MOD(A49-$A$45:A49,Parameters!$G$28)=0),$F$45:F49,POWER(Parameters!$G$27,IF(A49-$A$45:A49=0,1,A49-$A$45:A49))),0) -> 0 | I49: =Parameters!$G$23*I48+B49*Parameters!$G$22 -> 0 | J49: =E49*Parameters!$G$14*(1-Parameters!$G$15) -> 0.56828743 | K49: =H49*Parameters!$G$29 -> 0 | L49: =I49*Parameters!$G$24 -> 0 | M49: =J49+K49+L49 -> 0.56828743 | N49: =C49*Parameters!$G$17+D49*Parameters!$G$18+E49*Parameters!$G$16+I49*Parameters!$G$25+G49*Parameters!$G$30 -> 0.12288 | O49: =0 -> 0 | P49: =M49-N49-O49 -> 0.44540743 | Q49: =0 -> 0 | R49: =P49-Q49 -> 0.44540743 | S49: =IF(A49<1+Parameters!$G$31,0,INDEX($M$45:$M$80,A49-Parameters!$G$31)) -> 0.75688801 | T49: =T48+M49-S49 -> 0.56828743 | U49: =S49-N49-O49-Q49 -> 0.63400801 | V49: =V48+U49 -> 4.0495216 | W49: =(1-Parameters!$G$7)*(C49-E49)+(1-Parameters!$G$8)*(D49+E49) -> 0.08192 | X49: =Parameters!$G$7*(C49-E49)+Parameters!$G$8*Parameters!$G$9*(D49+E49) -> 0.22658392 | Y49: =Parameters!$G$8*(1-Parameters!$G$9)*(D49+E49) -> 0.10109608 | Z49: =POWER(1/(1+Parameters!$G$32),A49-1)*(M49-N49) -> 0.42802779
A50: 6 | B50: =0 -> 0 | C50: =X49+B50 -> 0.22658392 | D50: =Y49 -> 0.10109608 | E50: =Parameters!$G$6*C50 -> 0.022658392 | F50: =IF(Parameters!$G$5=1,E50,0) -> 0 | G50: =Parameters!$G$27*G49+F50 -> 0 | H50: =IF(AND(Parameters!$G$5=1,Parameters!$G$26=1),SUMPRODUCT(--($A$45:A50<A50),--(MOD(A50-$A$45:A50,Parameters!$G$28)=0),$F$45:F50,POWER(Parameters!$G$27,IF(A50-$A$45:A50=0,1,A50-$A$45:A50))),0) -> 0 | I50: =Parameters!$G$23*I49+B50*Parameters!$G$22 -> 0 | J50: =E50*Parameters!$G$14*(1-Parameters!$G$15) -> 0.43050946 | K50: =H50*Parameters!$G$29 -> 0 | L50: =I50*Parameters!$G$24 -> 0 | M50: =J50+K50+L50 -> 0.43050946 | N50: =C50*Parameters!$G$17+D50*Parameters!$G$18+E50*Parameters!$G$16+I50*Parameters!$G$25+G50*Parameters!$G$30 -> 0.098304 | O50: =0 -> 0 | P50: =M50-N50-O50 -> 0.33220546 | Q50: =0 -> 0 | R50: =P50-Q50 -> 0.33220546 | S50: =IF(A50<1+Parameters!$G$31,0,INDEX($M$45:$M$80,A50-Parameters!$G$31)) -> 0.56828743 | T50: =T49+M50-S50 -> 0.43050946 | U50: =S50-N50-O50-Q50 -> 0.46998343 | V50: =V49+U50 -> 4.519505 | W50: =(1-Parameters!$G$7)*(C50-E50)+(1-Parameters!$G$8)*(D50+E50) -> 0.065536 | X50: =Parameters!$G$7*(C50-E50)+Parameters!$G$8*Parameters!$G$9*(D50+E50) -> 0.17304078 | Y50: =Parameters!$G$8*(1-Parameters!$G$9)*(D50+E50) -> 0.089103217 | Z50: =POWER(1/(1+Parameters!$G$32),A50-1)*(M50-N50) -> 0.31608209
A51: 7 | B51: =0 -> 0 | C51: =X50+B51 -> 0.17304078 | D51: =Y50 -> 0.089103217 | E51: =Parameters!$G$6*C51 -> 0.017304078 | F51: =IF(Parameters!$G$5=1,E51,0) -> 0 | G51: =Parameters!$G$27*G50+F51 -> 0 | H51: =IF(AND(Parameters!$G$5=1,Parameters!$G$26=1),SUMPRODUCT(--($A$45:A51<A51),--(MOD(A51-$A$45:A51,Parameters!$G$28)=0),$F$45:F51,POWER(Parameters!$G$27,IF(A51-$A$45:A51=0,1,A51-$A$45:A51))),0) -> 0 | I51: =Parameters!$G$23*I50+B51*Parameters!$G$22 -> 0 | J51: =E51*Parameters!$G$14*(1-Parameters!$G$15) -> 0.32877749 | K51: =H51*Parameters!$G$29 -> 0 | L51: =I51*Parameters!$G$24 -> 0 | M51: =J51+K51+L51 -> 0.32877749 | N51: =C51*Parameters!$G$17+D51*Parameters!$G$18+E51*Parameters!$G$16+I51*Parameters!$G$25+G51*Parameters!$G$30 -> 0.0786432 | O51: =0 -> 0 | P51: =M51-N51-O51 -> 0.25013429 | Q51: =0 -> 0 | R51: =P51-Q51 -> 0.25013429 | S51: =IF(A51<1+Parameters!$G$31,0,INDEX($M$45:$M$80,A51-Parameters!$G$31)) -> 0.43050946 | T51: =T50+M51-S51 -> 0.32877749 | U51: =S51-N51-O51-Q51 -> 0.35186626 | V51: =V50+U51 -> 4.8713713 | W51: =(1-Parameters!$G$7)*(C51-E51)+(1-Parameters!$G$8)*(D51+E51) -> 0.0524288 | X51: =Parameters!$G$7*(C51-E51)+Parameters!$G$8*Parameters!$G$9*(D51+E51) -> 0.13310195 | Y51: =Parameters!$G$8*(1-Parameters!$G$9)*(D51+E51) -> 0.076613253 | Z51: =POWER(1/(1+Parameters!$G$32),A51-1)*(M51-N51) -> 0.23563781
A52: 8 | B52: =0 -> 0 | C52: =X51+B52 -> 0.13310195 | D52: =Y51 -> 0.076613253 | E52: =Parameters!$G$6*C52 -> 0.013310195 | F52: =IF(Parameters!$G$5=1,E52,0) -> 0 | G52: =Parameters!$G$27*G51+F52 -> 0 | H52: =IF(AND(Parameters!$G$5=1,Parameters!$G$26=1),SUMPRODUCT(--($A$45:A52<A52),--(MOD(A52-$A$45:A52,Parameters!$G$28)=0),$F$45:F52,POWER(Parameters!$G$27,IF(A52-$A$45:A52=0,1,A52-$A$45:A52))),0) -> 0 | I52: =Parameters!$G$23*I51+B52*Parameters!$G$22 -> 0 | J52: =E52*Parameters!$G$14*(1-Parameters!$G$15) -> 0.2528937 | K52: =H52*Parameters!$G$29 -> 0 | L52: =I52*Parameters!$G$24 -> 0 | M52: =J52+K52+L52 -> 0.2528937 | N52: =C52*Parameters!$G$17+D52*Parameters!$G$18+E52*Parameters!$G$16+I52*Parameters!$G$25+G52*Parameters!$G$30 -> 0.06291456 | O52: =0 -> 0 | P52: =M52-N52-O52 -> 0.18997914 | Q52: =0 -> 0 | R52: =P52-Q52 -> 0.18997914 | S52: =IF(A52<1+Parameters!$G$31,0,INDEX($M$45:$M$80,A52-Parameters!$G$31)) -> 0.32877749 | T52: =T51+M52-S52 -> 0.2528937 | U52: =S52-N52-O52-Q52 -> 0.26586293 | V52: =V51+U52 -> 5.1372342 | W52: =(1-Parameters!$G$7)*(C52-E52)+(1-Parameters!$G$8)*(D52+E52) -> 0.04194304 | X52: =Parameters!$G$7*(C52-E52)+Parameters!$G$8*Parameters!$G$9*(D52+E52) -> 0.10302728 | Y52: =Parameters!$G$8*(1-Parameters!$G$9)*(D52+E52) -> 0.064744882 | Z52: =POWER(1/(1+Parameters!$G$32),A52-1)*(M52-N52) -> 0.17719697
A53: 9 | B53: =0 -> 0 | C53: =X52+B53 -> 0.10302728 | D53: =Y52 -> 0.064744882 | E53: =Parameters!$G$6*C53 -> 0.010302728 | F53: =IF(Parameters!$G$5=1,E53,0) -> 0 | G53: =Parameters!$G$27*G52+F53 -> 0 | H53: =IF(AND(Parameters!$G$5=1,Parameters!$G$26=1),SUMPRODUCT(--($A$45:A53<A53),--(MOD(A53-$A$45:A53,Parameters!$G$28)=0),$F$45:F53,POWER(Parameters!$G$27,IF(A53-$A$45:A53=0,1,A53-$A$45:A53))),0) -> 0 | I53: =Parameters!$G$23*I52+B53*Parameters!$G$22 -> 0 | J53: =E53*Parameters!$G$14*(1-Parameters!$G$15) -> 0.19575183 | K53: =H53*Parameters!$G$29 -> 0 | L53: =I53*Parameters!$G$24 -> 0 | M53: =J53+K53+L53 -> 0.19575183 | N53: =C53*Parameters!$G$17+D53*Parameters!$G$18+E53*Parameters!$G$16+I53*Parameters!$G$25+G53*Parameters!$G$30 -> 0.050331648 | O53: =0 -> 0 | P53: =M53-N53-O53 -> 0.14542018 | Q53: =0 -> 0 | R53: =P53-Q53 -> 0.14542018 | S53: =IF(A53<1+Parameters!$G$31,0,INDEX($M$45:$M$80,A53-Parameters!$G$31)) -> 0.2528937 | T53: =T52+M53-S53 -> 0.19575183 | U53: =S53-N53-O53-Q53 -> 0.20256205 | V53: =V52+U53 -> 5.3397963 | W53: =(1-Parameters!$G$7)*(C53-E53)+(1-Parameters!$G$8)*(D53+E53) -> 0.033554432 | X53: =Parameters!$G$7*(C53-E53)+Parameters!$G$8*Parameters!$G$9*(D53+E53) -> 0.080183449 | Y53: =Parameters!$G$8*(1-Parameters!$G$9)*(D53+E53) -> 0.054034279 | Z53: =POWER(1/(1+Parameters!$G$32),A53-1)*(M53-N53) -> 0.1342931
A54: 10 | B54: =0 -> 0 | C54: =X53+B54 -> 0.080183449 | D54: =Y53 -> 0.054034279 | E54: =Parameters!$G$6*C54 -> 0.0080183449 | F54: =IF(Parameters!$G$5=1,E54,0) -> 0 | G54: =Parameters!$G$27*G53+F54 -> 0 | H54: =IF(AND(Parameters!$G$5=1,Parameters!$G$26=1),SUMPRODUCT(--($A$45:A54<A54),--(MOD(A54-$A$45:A54,Parameters!$G$28)=0),$F$45:F54,POWER(Parameters!$G$27,IF(A54-$A$45:A54=0,1,A54-$A$45:A54))),0) -> 0 | I54: =Parameters!$G$23*I53+B54*Parameters!$G$22 -> 0 | J54: =E54*Parameters!$G$14*(1-Parameters!$G$15) -> 0.15234855 | K54: =H54*Parameters!$G$29 -> 0 | L54: =I54*Parameters!$G$24 -> 0 | M54: =J54+K54+L54 -> 0.15234855 | N54: =C54*Parameters!$G$17+D54*Parameters!$G$18+E54*Parameters!$G$16+I54*Parameters!$G$25+G54*Parameters!$G$30 -> 0.040265318 | O54: =0 -> 0 | P54: =M54-N54-O54 -> 0.11208323 | Q54: =0 -> 0 | R54: =P54-Q54 -> 0.11208323 | S54: =IF(A54<1+Parameters!$G$31,0,INDEX($M$45:$M$80,A54-Parameters!$G$31)) -> 0.19575183 | T54: =T53+M54-S54 -> 0.15234855 | U54: =S54-N54-O54-Q54 -> 0.15548651 | V54: =V53+U54 -> 5.4952828 | W54: =(1-Parameters!$G$7)*(C54-E54)+(1-Parameters!$G$8)*(D54+E54) -> 0.026843546 | X54: =Parameters!$G$7*(C54-E54)+Parameters!$G$8*Parameters!$G$9*(D54+E54) -> 0.062696293 | Y54: =Parameters!$G$8*(1-Parameters!$G$9)*(D54+E54) -> 0.044677889 | Z54: =POWER(1/(1+Parameters!$G$32),A54-1)*(M54-N54) -> 0.10248216
A55: 11 | B55: =0 -> 0 | C55: =X54+B55 -> 0.062696293 | D55: =Y54 -> 0.044677889 | E55: =Parameters!$G$6*C55 -> 0.0062696293 | F55: =IF(Parameters!$G$5=1,E55,0) -> 0 | G55: =Parameters!$G$27*G54+F55 -> 0 | H55: =IF(AND(Parameters!$G$5=1,Parameters!$G$26=1),SUMPRODUCT(--($A$45:A55<A55),--(MOD(A55-$A$45:A55,Parameters!$G$28)=0),$F$45:F55,POWER(Parameters!$G$27,IF(A55-$A$45:A55=0,1,A55-$A$45:A55))),0) -> 0 | I55: =Parameters!$G$23*I54+B55*Parameters!$G$22 -> 0 | J55: =E55*Parameters!$G$14*(1-Parameters!$G$15) -> 0.11912296 | K55: =H55*Parameters!$G$29 -> 0 | L55: =I55*Parameters!$G$24 -> 0 | M55: =J55+K55+L55 -> 0.11912296 | N55: =C55*Parameters!$G$17+D55*Parameters!$G$18+E55*Parameters!$G$16+I55*Parameters!$G$25+G55*Parameters!$G$30 -> 0.032212255 | O55: =0 -> 0 | P55: =M55-N55-O55 -> 0.086910702 | Q55: =0 -> 0 | R55: =P55-Q55 -> 0.086910702 | S55: =IF(A55<1+Parameters!$G$31,0,INDEX($M$45:$M$80,A55-Parameters!$G$31)) -> 0.15234855 | T55: =T54+M55-S55 -> 0.11912296 | U55: =S55-N55-O55-Q55 -> 0.1201363 | V55: =V54+U55 -> 5.6154191 | W55: =(1-Parameters!$G$7)*(C55-E55)+(1-Parameters!$G$8)*(D55+E55) -> 0.021474836 | X55: =Parameters!$G$7*(C55-E55)+Parameters!$G$8*Parameters!$G$9*(D55+E55) -> 0.049217133 | Y55: =Parameters!$G$8*(1-Parameters!$G$9)*(D55+E55) -> 0.036682213 | Z55: =POWER(1/(1+Parameters!$G$32),A55-1)*(M55-N55) -> 0.078679125
A56: 12 | B56: =0 -> 0 | C56: =X55+B56 -> 0.049217133 | D56: =Y55 -> 0.036682213 | E56: =Parameters!$G$6*C56 -> 0.0049217133 | F56: =IF(Parameters!$G$5=1,E56,0) -> 0 | G56: =Parameters!$G$27*G55+F56 -> 0 | H56: =IF(AND(Parameters!$G$5=1,Parameters!$G$26=1),SUMPRODUCT(--($A$45:A56<A56),--(MOD(A56-$A$45:A56,Parameters!$G$28)=0),$F$45:F56,POWER(Parameters!$G$27,IF(A56-$A$45:A56=0,1,A56-$A$45:A56))),0) -> 0 | I56: =Parameters!$G$23*I55+B56*Parameters!$G$22 -> 0 | J56: =E56*Parameters!$G$14*(1-Parameters!$G$15) -> 0.093512552 | K56: =H56*Parameters!$G$29 -> 0 | L56: =I56*Parameters!$G$24 -> 0 | M56: =J56+K56+L56 -> 0.093512552 | N56: =C56*Parameters!$G$17+D56*Parameters!$G$18+E56*Parameters!$G$16+I56*Parameters!$G$25+G56*Parameters!$G$30 -> 0.025769804 | O56: =0 -> 0 | P56: =M56-N56-O56 -> 0.067742748 | Q56: =0 -> 0 | R56: =P56-Q56 -> 0.067742748 | S56: =IF(A56<1+Parameters!$G$31,0,INDEX($M$45:$M$80,A56-Parameters!$G$31)) -> 0.11912296 | T56: =T55+M56-S56 -> 0.093512552 | U56: =S56-N56-O56-Q56 -> 0.093353153 | V56: =V55+U56 -> 5.7087722 | W56: =(1-Parameters!$G$7)*(C56-E56)+(1-Parameters!$G$8)*(D56+E56) -> 0.017179869 | X56: =Parameters!$G$7*(C56-E56)+Parameters!$G$8*Parameters!$G$9*(D56+E56) -> 0.03876465 | Y56: =Parameters!$G$8*(1-Parameters!$G$9)*(D56+E56) -> 0.029954827 | Z56: =POWER(1/(1+Parameters!$G$32),A56-1)*(M56-N56) -> 0.060719432
A57: 13 | B57: =0 -> 0 | C57: =X56+B57 -> 0.03876465 | D57: =Y56 -> 0.029954827 | E57: =Parameters!$G$6*C57 -> 0.003876465 | F57: =IF(Parameters!$G$5=1,E57,0) -> 0 | G57: =Parameters!$G$27*G56+F57 -> 0 | H57: =IF(AND(Parameters!$G$5=1,Parameters!$G$26=1),SUMPRODUCT(--($A$45:A57<A57),--(MOD(A57-$A$45:A57,Parameters!$G$28)=0),$F$45:F57,POWER(Parameters!$G$27,IF(A57-$A$45:A57=0,1,A57-$A$45:A57))),0) -> 0 | I57: =Parameters!$G$23*I56+B57*Parameters!$G$22 -> 0 | J57: =E57*Parameters!$G$14*(1-Parameters!$G$15) -> 0.073652834 | K57: =H57*Parameters!$G$29 -> 0 | L57: =I57*Parameters!$G$24 -> 0 | M57: =J57+K57+L57 -> 0.073652834 | N57: =C57*Parameters!$G$17+D57*Parameters!$G$18+E57*Parameters!$G$16+I57*Parameters!$G$25+G57*Parameters!$G$30 -> 0.020615843 | O57: =0 -> 0 | P57: =M57-N57-O57 -> 0.053036991 | Q57: =0 -> 0 | R57: =P57-Q57 -> 0.053036991 | S57: =IF(A57<1+Parameters!$G$31,0,INDEX($M$45:$M$80,A57-Parameters!$G$31)) -> 0.093512552 | T57: =T56+M57-S57 -> 0.073652834 | U57: =S57-N57-O57-Q57 -> 0.072896709 | V57: =V56+U57 -> 5.781669 | W57: =(1-Parameters!$G$7)*(C57-E57)+(1-Parameters!$G$8)*(D57+E57) -> 0.013743895 | X57: =Parameters!$G$7*(C57-E57)+Parameters!$G$8*Parameters!$G$9*(D57+E57) -> 0.030617051 | Y57: =Parameters!$G$8*(1-Parameters!$G$9)*(D57+E57) -> 0.02435853 | Z57: =POWER(1/(1+Parameters!$G$32),A57-1)*(M57-N57) -> 0.047067637
... A80: 36 | B80: =0 -> 0 | C80: =X79+B80 -> 0.00021361945 | D80: =Y79 -> 0.00019202875 | E80: =Parameters!$G$6*C80 -> 2.1361945e-05 | F80: =IF(Parameters!$G$5=1,E80,0) -> 0 | G80: =Parameters!$G$27*G79+F80 -> 0 | H80: =IF(AND(Parameters!$G$5=1,Parameters!$G$26=1),SUMPRODUCT(--($A$45:A80<A80),--(MOD(A80-$A$45:A80,Parameters!$G$28)=0),$F$45:F80,POWER(Parameters!$G$27,IF(A80-$A$45:A80=0,1,A80-$A$45:A80))),0) -> 0 | I80: =Parameters!$G$23*I79+B80*Parameters!$G$22 -> 0 | J80: =E80*Parameters!$G$14*(1-Parameters!$G$15) -> 0.00040587695 | K80: =H80*Parameters!$G$29 -> 0 | L80: =I80*Parameters!$G$24 -> 0 | M80: =J80+K80+L80 -> 0.00040587695 | N80: =C80*Parameters!$G$17+D80*Parameters!$G$18+E80*Parameters!$G$16+I80*Parameters!$G$25+G80*Parameters!$G$30 -> 0.00012169446 | O80: =0 -> 0 | P80: =M80-N80-O80 -> 0.00028418249 | Q80: =0 -> 0 | R80: =P80-Q80 -> 0.00028418249 | S80: =IF(A80<1+Parameters!$G$31,0,INDEX($M$45:$M$80,A80-Parameters!$G$31)) -> 0.00050741325 | T80: =T79+M80-S80 -> 0.00040587695 | U80: =S80-N80-O80-Q80 -> 0.0003857188 | V80: =V79+U80 -> 6.0552761 | W80: =(1-Parameters!$G$7)*(C80-E80)+(1-Parameters!$G$8)*(D80+E80) -> 8.1129638e-05 | X80: =Parameters!$G$7*(C80-E80)+Parameters!$G$8*Parameters!$G$9*(D80+E80) -> 0.00017087726 | Y80: =Parameters!$G$8*(1-Parameters!$G$9)*(D80+E80) -> 0.0001536413 | Z80: =POWER(1/(1+Parameters!$G$32),A80-1)*(M80-N80) -> 0.00020060845

Sheet S5
A1: S5 — Paid tools with post-lead retention
A2: All parameters are illustrative. Top block: calendar cohorts. Lower block: one acquired owner, no CAC/fixed cost, for customer-value calculation.
A4: Month | B4: Acquired | C4: E eligible | D4: M completed active | E4: Payable events | F4: New policies | G4: Active policies | H4: Renewed policies | I4: Billed subscribers | J4: Initial revenue | K4: Renewal revenue | L4: Software revenue | M4: Total revenue | N4: Variable cost | O4: Acquisition cost | P4: Contribution | Q4: Fixed cost | R4: Operating result | S4: Cash receipts | T4: Receivables | U4: Cash surplus | V4: Cumulative cash | W4: Churned opportunity owners | X4: Next E | Y4: Next M | Z4: Discounted contribution before CAC
A5: 1 | B5: =Parameters!$H$20 -> 1000 | C5: =B5 -> 1000 | D5: =0 -> 0 | E5: =Parameters!$H$6*C5 -> 100 | F5: =IF(Parameters!$H$5=1,E5,0) -> 0 | G5: =F5 -> 0 | H5: =IF(AND(Parameters!$H$5=1,Parameters!$H$26=1),SUMPRODUCT(--($A$5:A5<A5),--(MOD(A5-$A$5:A5,Parameters!$H$28)=0),$F$5:F5,POWER(Parameters!$H$27,IF(A5-$A$5:A5=0,1,A5-$A$5:A5))),0) -> 0 | I5: =B5*Parameters!$H$22 -> 50 | J5: =E5*Parameters!$H$14*(1-Parameters!$H$15) -> 1900 | K5: =H5*Parameters!$H$29 -> 0 | L5: =I5*Parameters!$H$24 -> 150 | M5: =J5+K5+L5 -> 2050 | N5: =C5*Parameters!$H$17+D5*Parameters!$H$18+E5*Parameters!$H$16+I5*Parameters!$H$25+G5*Parameters!$H$30 -> 325 | O5: =B5*Parameters!$H$19 -> 4000 | P5: =M5-N5-O5 -> -2275 | Q5: =Parameters!$H$21 -> 1000 | R5: =P5-Q5 -> -3275 | S5: =IF(A5<1+Parameters!$H$31,0,INDEX($M$5:$M$40,A5-Parameters!$H$31)) -> 0 | T5: =M5-S5 -> 2050 | U5: =S5-N5-O5-Q5 -> -5325 | V5: =U5 -> -5325 | W5: =(1-Parameters!$H$7)*(C5-E5)+(1-Parameters!$H$8)*(D5+E5) -> 920 | X5: =Parameters!$H$7*(C5-E5)+Parameters!$H$8*Parameters!$H$9*(D5+E5) -> 0 | Y5: =Parameters!$H$8*(1-Parameters!$H$9)*(D5+E5) -> 80 | Z5: =POWER(1/(1+Parameters!$H$32),A5-1)*(M5-N5) -> 1725
A6: 2 | B6: =Parameters!$H$20 -> 1000 | C6: =X5+B6 -> 1000 | D6: =Y5 -> 80 | E6: =Parameters!$H$6*C6 -> 100 | F6: =IF(Parameters!$H$5=1,E6,0) -> 0 | G6: =Parameters!$H$27*G5+F6 -> 0 | H6: =IF(AND(Parameters!$H$5=1,Parameters!$H$26=1),SUMPRODUCT(--($A$5:A6<A6),--(MOD(A6-$A$5:A6,Parameters!$H$28)=0),$F$5:F6,POWER(Parameters!$H$27,IF(A6-$A$5:A6=0,1,A6-$A$5:A6))),0) -> 0 | I6: =Parameters!$H$23*I5+B6*Parameters!$H$22 -> 97.5 | J6: =E6*Parameters!$H$14*(1-Parameters!$H$15) -> 1900 | K6: =H6*Parameters!$H$29 -> 0 | L6: =I6*Parameters!$H$24 -> 292.5 | M6: =J6+K6+L6 -> 2192.5 | N6: =C6*Parameters!$H$17+D6*Parameters!$H$18+E6*Parameters!$H$16+I6*Parameters!$H$25+G6*Parameters!$H$30 -> 372.75 | O6: =B6*Parameters!$H$19 -> 4000 | P6: =M6-N6-O6 -> -2180.25 | Q6: =Parameters!$H$21 -> 1000 | R6: =P6-Q6 -> -3180.25 | S6: =IF(A6<1+Parameters!$H$31,0,INDEX($M$5:$M$40,A6-Parameters!$H$31)) -> 2050 | T6: =T5+M6-S6 -> 2192.5 | U6: =S6-N6-O6-Q6 -> -3322.75 | V6: =V5+U6 -> -8647.75 | W6: =(1-Parameters!$H$7)*(C6-E6)+(1-Parameters!$H$8)*(D6+E6) -> 936 | X6: =Parameters!$H$7*(C6-E6)+Parameters!$H$8*Parameters!$H$9*(D6+E6) -> 0 | Y6: =Parameters!$H$8*(1-Parameters!$H$9)*(D6+E6) -> 144 | Z6: =POWER(1/(1+Parameters!$H$32),A6-1)*(M6-N6) -> 1801.7327
A7: 3 | B7: =Parameters!$H$20 -> 1000 | C7: =X6+B7 -> 1000 | D7: =Y6 -> 144 | E7: =Parameters!$H$6*C7 -> 100 | F7: =IF(Parameters!$H$5=1,E7,0) -> 0 | G7: =Parameters!$H$27*G6+F7 -> 0 | H7: =IF(AND(Parameters!$H$5=1,Parameters!$H$26=1),SUMPRODUCT(--($A$5:A7<A7),--(MOD(A7-$A$5:A7,Parameters!$H$28)=0),$F$5:F7,POWER(Parameters!$H$27,IF(A7-$A$5:A7=0,1,A7-$A$5:A7))),0) -> 0 | I7: =Parameters!$H$23*I6+B7*Parameters!$H$22 -> 142.625 | J7: =E7*Parameters!$H$14*(1-Parameters!$H$15) -> 1900 | K7: =H7*Parameters!$H$29 -> 0 | L7: =I7*Parameters!$H$24 -> 427.875 | M7: =J7+K7+L7 -> 2327.875 | N7: =C7*Parameters!$H$17+D7*Parameters!$H$18+E7*Parameters!$H$16+I7*Parameters!$H$25+G7*Parameters!$H$30 -> 414.5125 | O7: =B7*Parameters!$H$19 -> 4000 | P7: =M7-N7-O7 -> -2086.6375 | Q7: =Parameters!$H$21 -> 1000 | R7: =P7-Q7 -> -3086.6375 | S7: =IF(A7<1+Parameters!$H$31,0,INDEX($M$5:$M$40,A7-Parameters!$H$31)) -> 2192.5 | T7: =T6+M7-S7 -> 2327.875 | U7: =S7-N7-O7-Q7 -> -3222.0125 | V7: =V6+U7 -> -11869.763 | W7: =(1-Parameters!$H$7)*(C7-E7)+(1-Parameters!$H$8)*(D7+E7) -> 948.8 | X7: =Parameters!$H$7*(C7-E7)+Parameters!$H$8*Parameters!$H$9*(D7+E7) -> 0 | Y7: =Parameters!$H$8*(1-Parameters!$H$9)*(D7+E7) -> 195.2 | Z7: =POWER(1/(1+Parameters!$H$32),A7-1)*(M7-N7) -> 1875.6617
A8: 4 | B8: =Parameters!$H$20 -> 1000 | C8: =X7+B8 -> 1000 | D8: =Y7 -> 195.2 | E8: =Parameters!$H$6*C8 -> 100 | F8: =IF(Parameters!$H$5=1,E8,0) -> 0 | G8: =Parameters!$H$27*G7+F8 -> 0 | H8: =IF(AND(Parameters!$H$5=1,Parameters!$H$26=1),SUMPRODUCT(--($A$5:A8<A8),--(MOD(A8-$A$5:A8,Parameters!$H$28)=0),$F$5:F8,POWER(Parameters!$H$27,IF(A8-$A$5:A8=0,1,A8-$A$5:A8))),0) -> 0 | I8: =Parameters!$H$23*I7+B8*Parameters!$H$22 -> 185.49375 | J8: =E8*Parameters!$H$14*(1-Parameters!$H$15) -> 1900 | K8: =H8*Parameters!$H$29 -> 0 | L8: =I8*Parameters!$H$24 -> 556.48125 | M8: =J8+K8+L8 -> 2456.4812 | N8: =C8*Parameters!$H$17+D8*Parameters!$H$18+E8*Parameters!$H$16+I8*Parameters!$H$25+G8*Parameters!$H$30 -> 451.30687 | O8: =B8*Parameters!$H$19 -> 4000 | P8: =M8-N8-O8 -> -1994.8256 | Q8: =Parameters!$H$21 -> 1000 | R8: =P8-Q8 -> -2994.8256 | S8: =IF(A8<1+Parameters!$H$31,0,INDEX($M$5:$M$40,A8-Parameters!$H$31)) -> 2327.875 | T8: =T7+M8-S8 -> 2456.4812 | U8: =S8-N8-O8-Q8 -> -3123.4319 | V8: =V7+U8 -> -14993.194 | W8: =(1-Parameters!$H$7)*(C8-E8)+(1-Parameters!$H$8)*(D8+E8) -> 959.04 | X8: =Parameters!$H$7*(C8-E8)+Parameters!$H$8*Parameters!$H$9*(D8+E8) -> 0 | Y8: =Parameters!$H$8*(1-Parameters!$H$9)*(D8+E8) -> 236.16 | Z8: =POWER(1/(1+Parameters!$H$32),A8-1)*(M8-N8) -> 1946.2025
A9: 5 | B9: =Parameters!$H$20 -> 1000 | C9: =X8+B9 -> 1000 | D9: =Y8 -> 236.16 | E9: =Parameters!$H$6*C9 -> 100 | F9: =IF(Parameters!$H$5=1,E9,0) -> 0 | G9: =Parameters!$H$27*G8+F9 -> 0 | H9: =IF(AND(Parameters!$H$5=1,Parameters!$H$26=1),SUMPRODUCT(--($A$5:A9<A9),--(MOD(A9-$A$5:A9,Parameters!$H$28)=0),$F$5:F9,POWER(Parameters!$H$27,IF(A9-$A$5:A9=0,1,A9-$A$5:A9))),0) -> 0 | I9: =Parameters!$H$23*I8+B9*Parameters!$H$22 -> 226.21906 | J9: =E9*Parameters!$H$14*(1-Parameters!$H$15) -> 1900 | K9: =H9*Parameters!$H$29 -> 0 | L9: =I9*Parameters!$H$24 -> 678.65719 | M9: =J9+K9+L9 -> 2578.6572 | N9: =C9*Parameters!$H$17+D9*Parameters!$H$18+E9*Parameters!$H$16+I9*Parameters!$H$25+G9*Parameters!$H$30 -> 483.95753 | O9: =B9*Parameters!$H$19 -> 4000 | P9: =M9-N9-O9 -> -1905.3003 | Q9: =Parameters!$H$21 -> 1000 | R9: =P9-Q9 -> -2905.3003 | S9: =IF(A9<1+Parameters!$H$31,0,INDEX($M$5:$M$40,A9-Parameters!$H$31)) -> 2456.4812 | T9: =T8+M9-S9 -> 2578.6572 | U9: =S9-N9-O9-Q9 -> -3027.4763 | V9: =V8+U9 -> -18020.671 | W9: =(1-Parameters!$H$7)*(C9-E9)+(1-Parameters!$H$8)*(D9+E9) -> 967.232 | X9: =Parameters!$H$7*(C9-E9)+Parameters!$H$8*Parameters!$H$9*(D9+E9) -> 0 | Y9: =Parameters!$H$8*(1-Parameters!$H$9)*(D9+E9) -> 268.928 | Z9: =POWER(1/(1+Parameters!$H$32),A9-1)*(M9-N9) -> 2012.9652
A10: 6 | B10: =Parameters!$H$20 -> 1000 | C10: =X9+B10 -> 1000 | D10: =Y9 -> 268.928 | E10: =Parameters!$H$6*C10 -> 100 | F10: =IF(Parameters!$H$5=1,E10,0) -> 0 | G10: =Parameters!$H$27*G9+F10 -> 0 | H10: =IF(AND(Parameters!$H$5=1,Parameters!$H$26=1),SUMPRODUCT(--($A$5:A10<A10),--(MOD(A10-$A$5:A10,Parameters!$H$28)=0),$F$5:F10,POWER(Parameters!$H$27,IF(A10-$A$5:A10=0,1,A10-$A$5:A10))),0) -> 0 | I10: =Parameters!$H$23*I9+B10*Parameters!$H$22 -> 264.90811 | J10: =E10*Parameters!$H$14*(1-Parameters!$H$15) -> 1900 | K10: =H10*Parameters!$H$29 -> 0 | L10: =I10*Parameters!$H$24 -> 794.72433 | M10: =J10+K10+L10 -> 2694.7243 | N10: =C10*Parameters!$H$17+D10*Parameters!$H$18+E10*Parameters!$H$16+I10*Parameters!$H$25+G10*Parameters!$H$30 -> 513.13245 | O10: =B10*Parameters!$H$19 -> 4000 | P10: =M10-N10-O10 -> -1818.4081 | Q10: =Parameters!$H$21 -> 1000 | R10: =P10-Q10 -> -2818.4081 | S10: =IF(A10<1+Parameters!$H$31,0,INDEX($M$5:$M$40,A10-Parameters!$H$31)) -> 2578.6572 | T10: =T9+M10-S10 -> 2694.7243 | U10: =S10-N10-O10-Q10 -> -2934.4753 | V10: =V9+U10 -> -20955.146 | W10: =(1-Parameters!$H$7)*(C10-E10)+(1-Parameters!$H$8)*(D10+E10) -> 973.7856 | X10: =Parameters!$H$7*(C10-E10)+Parameters!$H$8*Parameters!$H$9*(D10+E10) -> 0 | Y10: =Parameters!$H$8*(1-Parameters!$H$9)*(D10+E10) -> 295.1424 | Z10: =POWER(1/(1+Parameters!$H$32),A10-1)*(M10-N10) -> 2075.7098
A11: 7 | B11: =Parameters!$H$20 -> 1000 | C11: =X10+B11 -> 1000 | D11: =Y10 -> 295.1424 | E11: =Parameters!$H$6*C11 -> 100 | F11: =IF(Parameters!$H$5=1,E11,0) -> 0 | G11: =Parameters!$H$27*G10+F11 -> 0 | H11: =IF(AND(Parameters!$H$5=1,Parameters!$H$26=1),SUMPRODUCT(--($A$5:A11<A11),--(MOD(A11-$A$5:A11,Parameters!$H$28)=0),$F$5:F11,POWER(Parameters!$H$27,IF(A11-$A$5:A11=0,1,A11-$A$5:A11))),0) -> 0 | I11: =Parameters!$H$23*I10+B11*Parameters!$H$22 -> 301.6627 | J11: =E11*Parameters!$H$14*(1-Parameters!$H$15) -> 1900 | K11: =H11*Parameters!$H$29 -> 0 | L11: =I11*Parameters!$H$24 -> 904.98811 | M11: =J11+K11+L11 -> 2804.9881 | N11: =C11*Parameters!$H$17+D11*Parameters!$H$18+E11*Parameters!$H$16+I11*Parameters!$H$25+G11*Parameters!$H$30 -> 539.37407 | O11: =B11*Parameters!$H$19 -> 4000 | P11: =M11-N11-O11 -> -1734.386 | Q11: =Parameters!$H$21 -> 1000 | R11: =P11-Q11 -> -2734.386 | S11: =IF(A11<1+Parameters!$H$31,0,INDEX($M$5:$M$40,A11-Parameters!$H$31)) -> 2694.7243 | T11: =T10+M11-S11 -> 2804.9881 | U11: =S11-N11-O11-Q11 -> -2844.6497 | V11: =V10+U11 -> -23799.796 | W11: =(1-Parameters!$H$7)*(C11-E11)+(1-Parameters!$H$8)*(D11+E11) -> 979.02848 | X11: =Parameters!$H$7*(C11-E11)+Parameters!$H$8*Parameters!$H$9*(D11+E11) -> 0 | Y11: =Parameters!$H$8*(1-Parameters!$H$9)*(D11+E11) -> 316.11392 | Z11: =POWER(1/(1+Parameters!$H$32),A11-1)*(M11-N11) -> 2134.3109
A12: 8 | B12: =Parameters!$H$20 -> 1000 | C12: =X11+B12 -> 1000 | D12: =Y11 -> 316.11392 | E12: =Parameters!$H$6*C12 -> 100 | F12: =IF(Parameters!$H$5=1,E12,0) -> 0 | G12: =Parameters!$H$27*G11+F12 -> 0 | H12: =IF(AND(Parameters!$H$5=1,Parameters!$H$26=1),SUMPRODUCT(--($A$5:A12<A12),--(MOD(A12-$A$5:A12,Parameters!$H$28)=0),$F$5:F12,POWER(Parameters!$H$27,IF(A12-$A$5:A12=0,1,A12-$A$5:A12))),0) -> 0 | I12: =Parameters!$H$23*I11+B12*Parameters!$H$22 -> 336.57957 | J12: =E12*Parameters!$H$14*(1-Parameters!$H$15) -> 1900 | K12: =H12*Parameters!$H$29 -> 0 | L12: =I12*Parameters!$H$24 -> 1009.7387 | M12: =J12+K12+L12 -> 2909.7387 | N12: =C12*Parameters!$H$17+D12*Parameters!$H$18+E12*Parameters!$H$16+I12*Parameters!$H$25+G12*Parameters!$H$30 -> 563.12396 | O12: =B12*Parameters!$H$19 -> 4000 | P12: =M12-N12-O12 -> -1653.3853 | Q12: =Parameters!$H$21 -> 1000 | R12: =P12-Q12 -> -2653.3853 | S12: =IF(A12<1+Parameters!$H$31,0,INDEX($M$5:$M$40,A12-Parameters!$H$31)) -> 2804.9881 | T12: =T11+M12-S12 -> 2909.7387 | U12: =S12-N12-O12-Q12 -> -2758.1358 | V12: =V11+U12 -> -26557.932 | W12: =(1-Parameters!$H$7)*(C12-E12)+(1-Parameters!$H$8)*(D12+E12) -> 983.22278 | X12: =Parameters!$H$7*(C12-E12)+Parameters!$H$8*Parameters!$H$9*(D12+E12) -> 0 | Y12: =Parameters!$H$8*(1-Parameters!$H$9)*(D12+E12) -> 332.89114 | Z12: =POWER(1/(1+Parameters!$H$32),A12-1)*(M12-N12) -> 2188.7299
A13: 9 | B13: =Parameters!$H$20 -> 1000 | C13: =X12+B13 -> 1000 | D13: =Y12 -> 332.89114 | E13: =Parameters!$H$6*C13 -> 100 | F13: =IF(Parameters!$H$5=1,E13,0) -> 0 | G13: =Parameters!$H$27*G12+F13 -> 0 | H13: =IF(AND(Parameters!$H$5=1,Parameters!$H$26=1),SUMPRODUCT(--($A$5:A13<A13),--(MOD(A13-$A$5:A13,Parameters!$H$28)=0),$F$5:F13,POWER(Parameters!$H$27,IF(A13-$A$5:A13=0,1,A13-$A$5:A13))),0) -> 0 | I13: =Parameters!$H$23*I12+B13*Parameters!$H$22 -> 369.75059 | J13: =E13*Parameters!$H$14*(1-Parameters!$H$15) -> 1900 | K13: =H13*Parameters!$H$29 -> 0 | L13: =I13*Parameters!$H$24 -> 1109.2518 | M13: =J13+K13+L13 -> 3009.2518 | N13: =C13*Parameters!$H$17+D13*Parameters!$H$18+E13*Parameters!$H$16+I13*Parameters!$H$25+G13*Parameters!$H$30 -> 584.74264 | O13: =B13*Parameters!$H$19 -> 4000 | P13: =M13-N13-O13 -> -1575.4909 | Q13: =Parameters!$H$21 -> 1000 | R13: =P13-Q13 -> -2575.4909 | S13: =IF(A13<1+Parameters!$H$31,0,INDEX($M$5:$M$40,A13-Parameters!$H$31)) -> 2909.7387 | T13: =T12+M13-S13 -> 3009.2518 | U13: =S13-N13-O13-Q13 -> -2675.0039 | V13: =V12+U13 -> -29232.935 | W13: =(1-Parameters!$H$7)*(C13-E13)+(1-Parameters!$H$8)*(D13+E13) -> 986.57823 | X13: =Parameters!$H$7*(C13-E13)+Parameters!$H$8*Parameters!$H$9*(D13+E13) -> 0 | Y13: =Parameters!$H$8*(1-Parameters!$H$9)*(D13+E13) -> 346.31291 | Z13: =POWER(1/(1+Parameters!$H$32),A13-1)*(M13-N13) -> 2238.9935
A14: 10 | B14: =Parameters!$H$20 -> 1000 | C14: =X13+B14 -> 1000 | D14: =Y13 -> 346.31291 | E14: =Parameters!$H$6*C14 -> 100 | F14: =IF(Parameters!$H$5=1,E14,0) -> 0 | G14: =Parameters!$H$27*G13+F14 -> 0 | H14: =IF(AND(Parameters!$H$5=1,Parameters!$H$26=1),SUMPRODUCT(--($A$5:A14<A14),--(MOD(A14-$A$5:A14,Parameters!$H$28)=0),$F$5:F14,POWER(Parameters!$H$27,IF(A14-$A$5:A14=0,1,A14-$A$5:A14))),0) -> 0 | I14: =Parameters!$H$23*I13+B14*Parameters!$H$22 -> 401.26306 | J14: =E14*Parameters!$H$14*(1-Parameters!$H$15) -> 1900 | K14: =H14*Parameters!$H$29 -> 0 | L14: =I14*Parameters!$H$24 -> 1203.7892 | M14: =J14+K14+L14 -> 3103.7892 | N14: =C14*Parameters!$H$17+D14*Parameters!$H$18+E14*Parameters!$H$16+I14*Parameters!$H$25+G14*Parameters!$H$30 -> 604.5254 | O14: =B14*Parameters!$H$19 -> 4000 | P14: =M14-N14-O14 -> -1500.7362 | Q14: =Parameters!$H$21 -> 1000 | R14: =P14-Q14 -> -2500.7362 | S14: =IF(A14<1+Parameters!$H$31,0,INDEX($M$5:$M$40,A14-Parameters!$H$31)) -> 3009.2518 | T14: =T13+M14-S14 -> 3103.7892 | U14: =S14-N14-O14-Q14 -> -2595.2736 | V14: =V13+U14 -> -31828.209 | W14: =(1-Parameters!$H$7)*(C14-E14)+(1-Parameters!$H$8)*(D14+E14) -> 989.26258 | X14: =Parameters!$H$7*(C14-E14)+Parameters!$H$8*Parameters!$H$9*(D14+E14) -> 0 | Y14: =Parameters!$H$8*(1-Parameters!$H$9)*(D14+E14) -> 357.05033 | Z14: =POWER(1/(1+Parameters!$H$32),A14-1)*(M14-N14) -> 2285.1764
A15: 11 | B15: =Parameters!$H$20 -> 1000 | C15: =X14+B15 -> 1000 | D15: =Y14 -> 357.05033 | E15: =Parameters!$H$6*C15 -> 100 | F15: =IF(Parameters!$H$5=1,E15,0) -> 0 | G15: =Parameters!$H$27*G14+F15 -> 0 | H15: =IF(AND(Parameters!$H$5=1,Parameters!$H$26=1),SUMPRODUCT(--($A$5:A15<A15),--(MOD(A15-$A$5:A15,Parameters!$H$28)=0),$F$5:F15,POWER(Parameters!$H$27,IF(A15-$A$5:A15=0,1,A15-$A$5:A15))),0) -> 0 | I15: =Parameters!$H$23*I14+B15*Parameters!$H$22 -> 431.19991 | J15: =E15*Parameters!$H$14*(1-Parameters!$H$15) -> 1900 | K15: =H15*Parameters!$H$29 -> 0 | L15: =I15*Parameters!$H$24 -> 1293.5997 | M15: =J15+K15+L15 -> 3193.5997 | N15: =C15*Parameters!$H$17+D15*Parameters!$H$18+E15*Parameters!$H$16+I15*Parameters!$H$25+G15*Parameters!$H$30 -> 622.71505 | O15: =B15*Parameters!$H$19 -> 4000 | P15: =M15-N15-O15 -> -1429.1153 | Q15: =Parameters!$H$21 -> 1000 | R15: =P15-Q15 -> -2429.1153 | S15: =IF(A15<1+Parameters!$H$31,0,INDEX($M$5:$M$40,A15-Parameters!$H$31)) -> 3103.7892 | T15: =T14+M15-S15 -> 3193.5997 | U15: =S15-N15-O15-Q15 -> -2518.9259 | V15: =V14+U15 -> -34347.135 | W15: =(1-Parameters!$H$7)*(C15-E15)+(1-Parameters!$H$8)*(D15+E15) -> 991.41007 | X15: =Parameters!$H$7*(C15-E15)+Parameters!$H$8*Parameters!$H$9*(D15+E15) -> 0 | Y15: =Parameters!$H$8*(1-Parameters!$H$9)*(D15+E15) -> 365.64026 | Z15: =POWER(1/(1+Parameters!$H$32),A15-1)*(M15-N15) -> 2327.3884
A16: 12 | B16: =Parameters!$H$20 -> 1000 | C16: =X15+B16 -> 1000 | D16: =Y15 -> 365.64026 | E16: =Parameters!$H$6*C16 -> 100 | F16: =IF(Parameters!$H$5=1,E16,0) -> 0 | G16: =Parameters!$H$27*G15+F16 -> 0 | H16: =IF(AND(Parameters!$H$5=1,Parameters!$H$26=1),SUMPRODUCT(--($A$5:A16<A16),--(MOD(A16-$A$5:A16,Parameters!$H$28)=0),$F$5:F16,POWER(Parameters!$H$27,IF(A16-$A$5:A16=0,1,A16-$A$5:A16))),0) -> 0 | I16: =Parameters!$H$23*I15+B16*Parameters!$H$22 -> 459.63991 | J16: =E16*Parameters!$H$14*(1-Parameters!$H$15) -> 1900 | K16: =H16*Parameters!$H$29 -> 0 | L16: =I16*Parameters!$H$24 -> 1378.9197 | M16: =J16+K16+L16 -> 3278.9197 | N16: =C16*Parameters!$H$17+D16*Parameters!$H$18+E16*Parameters!$H$16+I16*Parameters!$H$25+G16*Parameters!$H$30 -> 639.51203 | O16: =B16*Parameters!$H$19 -> 4000 | P16: =M16-N16-O16 -> -1360.5923 | Q16: =Parameters!$H$21 -> 1000 | R16: =P16-Q16 -> -2360.5923 | S16: =IF(A16<1+Parameters!$H$31,0,INDEX($M$5:$M$40,A16-Parameters!$H$31)) -> 3193.5997 | T16: =T15+M16-S16 -> 3278.9197 | U16: =S16-N16-O16-Q16 -> -2445.9123 | V16: =V15+U16 -> -36793.047 | W16: =(1-Parameters!$H$7)*(C16-E16)+(1-Parameters!$H$8)*(D16+E16) -> 993.12805 | X16: =Parameters!$H$7*(C16-E16)+Parameters!$H$8*Parameters!$H$9*(D16+E16) -> 0 | Y16: =Parameters!$H$8*(1-Parameters!$H$9)*(D16+E16) -> 372.51221 | Z16: =POWER(1/(1+Parameters!$H$32),A16-1)*(M16-N16) -> 2365.7637
A17: 13 | B17: =Parameters!$H$20 -> 1000 | C17: =X16+B17 -> 1000 | D17: =Y16 -> 372.51221 | E17: =Parameters!$H$6*C17 -> 100 | F17: =IF(Parameters!$H$5=1,E17,0) -> 0 | G17: =Parameters!$H$27*G16+F17 -> 0 | H17: =IF(AND(Parameters!$H$5=1,Parameters!$H$26=1),SUMPRODUCT(--($A$5:A17<A17),--(MOD(A17-$A$5:A17,Parameters!$H$28)=0),$F$5:F17,POWER(Parameters!$H$27,IF(A17-$A$5:A17=0,1,A17-$A$5:A17))),0) -> 0 | I17: =Parameters!$H$23*I16+B17*Parameters!$H$22 -> 486.65792 | J17: =E17*Parameters!$H$14*(1-Parameters!$H$15) -> 1900 | K17: =H17*Parameters!$H$29 -> 0 | L17: =I17*Parameters!$H$24 -> 1459.9738 | M17: =J17+K17+L17 -> 3359.9738 | N17: =C17*Parameters!$H$17+D17*Parameters!$H$18+E17*Parameters!$H$16+I17*Parameters!$H$25+G17*Parameters!$H$30 -> 655.08262 | O17: =B17*Parameters!$H$19 -> 4000 | P17: =M17-N17-O17 -> -1295.1089 | Q17: =Parameters!$H$21 -> 1000 | R17: =P17-Q17 -> -2295.1089 | S17: =IF(A17<1+Parameters!$H$31,0,INDEX($M$5:$M$40,A17-Parameters!$H$31)) -> 3278.9197 | T17: =T16+M17-S17 -> 3359.9738 | U17: =S17-N17-O17-Q17 -> -2376.1629 | V17: =V16+U17 -> -39169.21 | W17: =(1-Parameters!$H$7)*(C17-E17)+(1-Parameters!$H$8)*(D17+E17) -> 994.50244 | X17: =Parameters!$H$7*(C17-E17)+Parameters!$H$8*Parameters!$H$9*(D17+E17) -> 0 | Y17: =Parameters!$H$8*(1-Parameters!$H$9)*(D17+E17) -> 378.00977 | Z17: =POWER(1/(1+Parameters!$H$32),A17-1)*(M17-N17) -> 2400.4535
... A40: 36 | B40: =Parameters!$H$20 -> 1000 | C40: =X39+B40 -> 1000 | D40: =Y39 -> 399.83774 | E40: =Parameters!$H$6*C40 -> 100 | F40: =IF(Parameters!$H$5=1,E40,0) -> 0 | G40: =Parameters!$H$27*G39+F40 -> 0 | H40: =IF(AND(Parameters!$H$5=1,Parameters!$H$26=1),SUMPRODUCT(--($A$5:A40<A40),--(MOD(A40-$A$5:A40,Parameters!$H$28)=0),$F$5:F40,POWER(Parameters!$H$27,IF(A40-$A$5:A40=0,1,A40-$A$5:A40))),0) -> 0 | I40: =Parameters!$H$23*I39+B40*Parameters!$H$22 -> 842.22079 | J40: =E40*Parameters!$H$14*(1-Parameters!$H$15) -> 1900 | K40: =H40*Parameters!$H$29 -> 0 | L40: =I40*Parameters!$H$24 -> 2526.6624 | M40: =J40+K40+L40 -> 4426.6624 | N40: =C40*Parameters!$H$17+D40*Parameters!$H$18+E40*Parameters!$H$16+I40*Parameters!$H$25+G40*Parameters!$H$30 -> 841.06171 | O40: =B40*Parameters!$H$19 -> 4000 | P40: =M40-N40-O40 -> -414.39936 | Q40: =Parameters!$H$21 -> 1000 | R40: =P40-Q40 -> -1414.3994 | S40: =IF(A40<1+Parameters!$H$31,0,INDEX($M$5:$M$40,A40-Parameters!$H$31)) -> 4401.7498 | T40: =T39+M40-S40 -> 4426.6624 | U40: =S40-N40-O40-Q40 -> -1439.3119 | V40: =V39+U40 -> -80552.344 | W40: =(1-Parameters!$H$7)*(C40-E40)+(1-Parameters!$H$8)*(D40+E40) -> 999.96755 | X40: =Parameters!$H$7*(C40-E40)+Parameters!$H$8*Parameters!$H$9*(D40+E40) -> 0 | Y40: =Parameters!$H$8*(1-Parameters!$H$9)*(D40+E40) -> 399.87019 | Z40: =POWER(1/(1+Parameters!$H$32),A40-1)*(M40-N40) -> 2531.1264
A43: One acquired-owner cohort: V36 before acquisition/fixed costs. This isolates the mathematical unit value.
A44: Month | B44: Acquired | C44: E eligible | D44: M completed active | E44: Payable events | F44: New policies | G44: Active policies | H44: Renewed policies | I44: Billed subscribers | J44: Initial revenue | K44: Renewal revenue | L44: Software revenue | M44: Total revenue | N44: Variable cost | O44: Acquisition cost | P44: Contribution | Q44: Fixed cost | R44: Operating result | S44: Cash receipts | T44: Receivables | U44: Cash surplus | V44: Cumulative cash | W44: Churned opportunity owners | X44: Next E | Y44: Next M | Z44: Discounted contribution before CAC
A45: 1 | B45: =1 -> 1 | C45: =B45 -> 1 | D45: =0 -> 0 | E45: =Parameters!$H$6*C45 -> 0.1 | F45: =IF(Parameters!$H$5=1,E45,0) -> 0 | G45: =F45 -> 0 | H45: =IF(AND(Parameters!$H$5=1,Parameters!$H$26=1),SUMPRODUCT(--($A$45:A45<A45),--(MOD(A45-$A$45:A45,Parameters!$H$28)=0),$F$45:F45,POWER(Parameters!$H$27,IF(A45-$A$45:A45=0,1,A45-$A$45:A45))),0) -> 0 | I45: =B45*Parameters!$H$22 -> 0.05 | J45: =E45*Parameters!$H$14*(1-Parameters!$H$15) -> 1.9 | K45: =H45*Parameters!$H$29 -> 0 | L45: =I45*Parameters!$H$24 -> 0.15 | M45: =J45+K45+L45 -> 2.05 | N45: =C45*Parameters!$H$17+D45*Parameters!$H$18+E45*Parameters!$H$16+I45*Parameters!$H$25+G45*Parameters!$H$30 -> 0.325 | O45: =0 -> 0 | P45: =M45-N45-O45 -> 1.725 | Q45: =0 -> 0 | R45: =P45-Q45 -> 1.725 | S45: =IF(A45<1+Parameters!$H$31,0,INDEX($M$45:$M$80,A45-Parameters!$H$31)) -> 0 | T45: =M45-S45 -> 2.05 | U45: =S45-N45-O45-Q45 -> -0.325 | V45: =U45 -> -0.325 | W45: =(1-Parameters!$H$7)*(C45-E45)+(1-Parameters!$H$8)*(D45+E45) -> 0.92 | X45: =Parameters!$H$7*(C45-E45)+Parameters!$H$8*Parameters!$H$9*(D45+E45) -> 0 | Y45: =Parameters!$H$8*(1-Parameters!$H$9)*(D45+E45) -> 0.08 | Z45: =POWER(1/(1+Parameters!$H$32),A45-1)*(M45-N45) -> 1.725
A46: 2 | B46: =0 -> 0 | C46: =X45+B46 -> 0 | D46: =Y45 -> 0.08 | E46: =Parameters!$H$6*C46 -> 0 | F46: =IF(Parameters!$H$5=1,E46,0) -> 0 | G46: =Parameters!$H$27*G45+F46 -> 0 | H46: =IF(AND(Parameters!$H$5=1,Parameters!$H$26=1),SUMPRODUCT(--($A$45:A46<A46),--(MOD(A46-$A$45:A46,Parameters!$H$28)=0),$F$45:F46,POWER(Parameters!$H$27,IF(A46-$A$45:A46=0,1,A46-$A$45:A46))),0) -> 0 | I46: =Parameters!$H$23*I45+B46*Parameters!$H$22 -> 0.0475 | J46: =E46*Parameters!$H$14*(1-Parameters!$H$15) -> 0 | K46: =H46*Parameters!$H$29 -> 0 | L46: =I46*Parameters!$H$24 -> 0.1425 | M46: =J46+K46+L46 -> 0.1425 | N46: =C46*Parameters!$H$17+D46*Parameters!$H$18+E46*Parameters!$H$16+I46*Parameters!$H$25+G46*Parameters!$H$30 -> 0.04775 | O46: =0 -> 0 | P46: =M46-N46-O46 -> 0.09475 | Q46: =0 -> 0 | R46: =P46-Q46 -> 0.09475 | S46: =IF(A46<1+Parameters!$H$31,0,INDEX($M$45:$M$80,A46-Parameters!$H$31)) -> 2.05 | T46: =T45+M46-S46 -> 0.1425 | U46: =S46-N46-O46-Q46 -> 2.00225 | V46: =V45+U46 -> 1.67725 | W46: =(1-Parameters!$H$7)*(C46-E46)+(1-Parameters!$H$8)*(D46+E46) -> 0.016 | X46: =Parameters!$H$7*(C46-E46)+Parameters!$H$8*Parameters!$H$9*(D46+E46) -> 0 | Y46: =Parameters!$H$8*(1-Parameters!$H$9)*(D46+E46) -> 0.064 | Z46: =POWER(1/(1+Parameters!$H$32),A46-1)*(M46-N46) -> 0.093811881
A47: 3 | B47: =0 -> 0 | C47: =X46+B47 -> 0 | D47: =Y46 -> 0.064 | E47: =Parameters!$H$6*C47 -> 0 | F47: =IF(Parameters!$H$5=1,E47,0) -> 0 | G47: =Parameters!$H$27*G46+F47 -> 0 | H47: =IF(AND(Parameters!$H$5=1,Parameters!$H$26=1),SUMPRODUCT(--($A$45:A47<A47),--(MOD(A47-$A$45:A47,Parameters!$H$28)=0),$F$45:F47,POWER(Parameters!$H$27,IF(A47-$A$45:A47=0,1,A47-$A$45:A47))),0) -> 0 | I47: =Parameters!$H$23*I46+B47*Parameters!$H$22 -> 0.045125 | J47: =E47*Parameters!$H$14*(1-Parameters!$H$15) -> 0 | K47: =H47*Parameters!$H$29 -> 0 | L47: =I47*Parameters!$H$24 -> 0.135375 | M47: =J47+K47+L47 -> 0.135375 | N47: =C47*Parameters!$H$17+D47*Parameters!$H$18+E47*Parameters!$H$16+I47*Parameters!$H$25+G47*Parameters!$H$30 -> 0.0417625 | O47: =0 -> 0 | P47: =M47-N47-O47 -> 0.0936125 | Q47: =0 -> 0 | R47: =P47-Q47 -> 0.0936125 | S47: =IF(A47<1+Parameters!$H$31,0,INDEX($M$45:$M$80,A47-Parameters!$H$31)) -> 0.1425 | T47: =T46+M47-S47 -> 0.135375 | U47: =S47-N47-O47-Q47 -> 0.1007375 | V47: =V46+U47 -> 1.7779875 | W47: =(1-Parameters!$H$7)*(C47-E47)+(1-Parameters!$H$8)*(D47+E47) -> 0.0128 | X47: =Parameters!$H$7*(C47-E47)+Parameters!$H$8*Parameters!$H$9*(D47+E47) -> 0 | Y47: =Parameters!$H$8*(1-Parameters!$H$9)*(D47+E47) -> 0.0512 | Z47: =POWER(1/(1+Parameters!$H$32),A47-1)*(M47-N47) -> 0.091767964
A48: 4 | B48: =0 -> 0 | C48: =X47+B48 -> 0 | D48: =Y47 -> 0.0512 | E48: =Parameters!$H$6*C48 -> 0 | F48: =IF(Parameters!$H$5=1,E48,0) -> 0 | G48: =Parameters!$H$27*G47+F48 -> 0 | H48: =IF(AND(Parameters!$H$5=1,Parameters!$H$26=1),SUMPRODUCT(--($A$45:A48<A48),--(MOD(A48-$A$45:A48,Parameters!$H$28)=0),$F$45:F48,POWER(Parameters!$H$27,IF(A48-$A$45:A48=0,1,A48-$A$45:A48))),0) -> 0 | I48: =Parameters!$H$23*I47+B48*Parameters!$H$22 -> 0.04286875 | J48: =E48*Parameters!$H$14*(1-Parameters!$H$15) -> 0 | K48: =H48*Parameters!$H$29 -> 0 | L48: =I48*Parameters!$H$24 -> 0.12860625 | M48: =J48+K48+L48 -> 0.12860625 | N48: =C48*Parameters!$H$17+D48*Parameters!$H$18+E48*Parameters!$H$16+I48*Parameters!$H$25+G48*Parameters!$H$30 -> 0.036794375 | O48: =0 -> 0 | P48: =M48-N48-O48 -> 0.091811875 | Q48: =0 -> 0 | R48: =P48-Q48 -> 0.091811875 | S48: =IF(A48<1+Parameters!$H$31,0,INDEX($M$45:$M$80,A48-Parameters!$H$31)) -> 0.135375 | T48: =T47+M48-S48 -> 0.12860625 | U48: =S48-N48-O48-Q48 -> 0.098580625 | V48: =V47+U48 -> 1.8765681 | W48: =(1-Parameters!$H$7)*(C48-E48)+(1-Parameters!$H$8)*(D48+E48) -> 0.01024 | X48: =Parameters!$H$7*(C48-E48)+Parameters!$H$8*Parameters!$H$9*(D48+E48) -> 0 | Y48: =Parameters!$H$8*(1-Parameters!$H$9)*(D48+E48) -> 0.04096 | Z48: =POWER(1/(1+Parameters!$H$32),A48-1)*(M48-N48) -> 0.089111701
A49: 5 | B49: =0 -> 0 | C49: =X48+B49 -> 0 | D49: =Y48 -> 0.04096 | E49: =Parameters!$H$6*C49 -> 0 | F49: =IF(Parameters!$H$5=1,E49,0) -> 0 | G49: =Parameters!$H$27*G48+F49 -> 0 | H49: =IF(AND(Parameters!$H$5=1,Parameters!$H$26=1),SUMPRODUCT(--($A$45:A49<A49),--(MOD(A49-$A$45:A49,Parameters!$H$28)=0),$F$45:F49,POWER(Parameters!$H$27,IF(A49-$A$45:A49=0,1,A49-$A$45:A49))),0) -> 0 | I49: =Parameters!$H$23*I48+B49*Parameters!$H$22 -> 0.040725312 | J49: =E49*Parameters!$H$14*(1-Parameters!$H$15) -> 0 | K49: =H49*Parameters!$H$29 -> 0 | L49: =I49*Parameters!$H$24 -> 0.12217594 | M49: =J49+K49+L49 -> 0.12217594 | N49: =C49*Parameters!$H$17+D49*Parameters!$H$18+E49*Parameters!$H$16+I49*Parameters!$H$25+G49*Parameters!$H$30 -> 0.032650656 | O49: =0 -> 0 | P49: =M49-N49-O49 -> 0.089525281 | Q49: =0 -> 0 | R49: =P49-Q49 -> 0.089525281 | S49: =IF(A49<1+Parameters!$H$31,0,INDEX($M$45:$M$80,A49-Parameters!$H$31)) -> 0.12860625 | T49: =T48+M49-S49 -> 0.12217594 | U49: =S49-N49-O49-Q49 -> 0.095955594 | V49: =V48+U49 -> 1.9725237 | W49: =(1-Parameters!$H$7)*(C49-E49)+(1-Parameters!$H$8)*(D49+E49) -> 0.008192 | X49: =Parameters!$H$7*(C49-E49)+Parameters!$H$8*Parameters!$H$9*(D49+E49) -> 0 | Y49: =Parameters!$H$8*(1-Parameters!$H$9)*(D49+E49) -> 0.032768 | Z49: =POWER(1/(1+Parameters!$H$32),A49-1)*(M49-N49) -> 0.086032036
A50: 6 | B50: =0 -> 0 | C50: =X49+B50 -> 0 | D50: =Y49 -> 0.032768 | E50: =Parameters!$H$6*C50 -> 0 | F50: =IF(Parameters!$H$5=1,E50,0) -> 0 | G50: =Parameters!$H$27*G49+F50 -> 0 | H50: =IF(AND(Parameters!$H$5=1,Parameters!$H$26=1),SUMPRODUCT(--($A$45:A50<A50),--(MOD(A50-$A$45:A50,Parameters!$H$28)=0),$F$45:F50,POWER(Parameters!$H$27,IF(A50-$A$45:A50=0,1,A50-$A$45:A50))),0) -> 0 | I50: =Parameters!$H$23*I49+B50*Parameters!$H$22 -> 0.038689047 | J50: =E50*Parameters!$H$14*(1-Parameters!$H$15) -> 0 | K50: =H50*Parameters!$H$29 -> 0 | L50: =I50*Parameters!$H$24 -> 0.11606714 | M50: =J50+K50+L50 -> 0.11606714 | N50: =C50*Parameters!$H$17+D50*Parameters!$H$18+E50*Parameters!$H$16+I50*Parameters!$H$25+G50*Parameters!$H$30 -> 0.029174923 | O50: =0 -> 0 | P50: =M50-N50-O50 -> 0.086892217 | Q50: =0 -> 0 | R50: =P50-Q50 -> 0.086892217 | S50: =IF(A50<1+Parameters!$H$31,0,INDEX($M$45:$M$80,A50-Parameters!$H$31)) -> 0.12217594 | T50: =T49+M50-S50 -> 0.11606714 | U50: =S50-N50-O50-Q50 -> 0.093001014 | V50: =V49+U50 -> 2.0655247 | W50: =(1-Parameters!$H$7)*(C50-E50)+(1-Parameters!$H$8)*(D50+E50) -> 0.0065536 | X50: =Parameters!$H$7*(C50-E50)+Parameters!$H$8*Parameters!$H$9*(D50+E50) -> 0 | Y50: =Parameters!$H$8*(1-Parameters!$H$9)*(D50+E50) -> 0.0262144 | Z50: =POWER(1/(1+Parameters!$H$32),A50-1)*(M50-N50) -> 0.082674963
A51: 7 | B51: =0 -> 0 | C51: =X50+B51 -> 0 | D51: =Y50 -> 0.0262144 | E51: =Parameters!$H$6*C51 -> 0 | F51: =IF(Parameters!$H$5=1,E51,0) -> 0 | G51: =Parameters!$H$27*G50+F51 -> 0 | H51: =IF(AND(Parameters!$H$5=1,Parameters!$H$26=1),SUMPRODUCT(--($A$45:A51<A51),--(MOD(A51-$A$45:A51,Parameters!$H$28)=0),$F$45:F51,POWER(Parameters!$H$27,IF(A51-$A$45:A51=0,1,A51-$A$45:A51))),0) -> 0 | I51: =Parameters!$H$23*I50+B51*Parameters!$H$22 -> 0.036754595 | J51: =E51*Parameters!$H$14*(1-Parameters!$H$15) -> 0 | K51: =H51*Parameters!$H$29 -> 0 | L51: =I51*Parameters!$H$24 -> 0.11026378 | M51: =J51+K51+L51 -> 0.11026378 | N51: =C51*Parameters!$H$17+D51*Parameters!$H$18+E51*Parameters!$H$16+I51*Parameters!$H$25+G51*Parameters!$H$30 -> 0.026241617 | O51: =0 -> 0 | P51: =M51-N51-O51 -> 0.084022166 | Q51: =0 -> 0 | R51: =P51-Q51 -> 0.084022166 | S51: =IF(A51<1+Parameters!$H$31,0,INDEX($M$45:$M$80,A51-Parameters!$H$31)) -> 0.11606714 | T51: =T50+M51-S51 -> 0.11026378 | U51: =S51-N51-O51-Q51 -> 0.089825523 | V51: =V50+U51 -> 2.1553503 | W51: =(1-Parameters!$H$7)*(C51-E51)+(1-Parameters!$H$8)*(D51+E51) -> 0.00524288 | X51: =Parameters!$H$7*(C51-E51)+Parameters!$H$8*Parameters!$H$9*(D51+E51) -> 0 | Y51: =Parameters!$H$8*(1-Parameters!$H$9)*(D51+E51) -> 0.02097152 | Z51: =POWER(1/(1+Parameters!$H$32),A51-1)*(M51-N51) -> 0.079152681
A52: 8 | B52: =0 -> 0 | C52: =X51+B52 -> 0 | D52: =Y51 -> 0.02097152 | E52: =Parameters!$H$6*C52 -> 0 | F52: =IF(Parameters!$H$5=1,E52,0) -> 0 | G52: =Parameters!$H$27*G51+F52 -> 0 | H52: =IF(AND(Parameters!$H$5=1,Parameters!$H$26=1),SUMPRODUCT(--($A$45:A52<A52),--(MOD(A52-$A$45:A52,Parameters!$H$28)=0),$F$45:F52,POWER(Parameters!$H$27,IF(A52-$A$45:A52=0,1,A52-$A$45:A52))),0) -> 0 | I52: =Parameters!$H$23*I51+B52*Parameters!$H$22 -> 0.034916865 | J52: =E52*Parameters!$H$14*(1-Parameters!$H$15) -> 0 | K52: =H52*Parameters!$H$29 -> 0 | L52: =I52*Parameters!$H$24 -> 0.10475059 | M52: =J52+K52+L52 -> 0.10475059 | N52: =C52*Parameters!$H$17+D52*Parameters!$H$18+E52*Parameters!$H$16+I52*Parameters!$H$25+G52*Parameters!$H$30 -> 0.023749888 | O52: =0 -> 0 | P52: =M52-N52-O52 -> 0.081000706 | Q52: =0 -> 0 | R52: =P52-Q52 -> 0.081000706 | S52: =IF(A52<1+Parameters!$H$31,0,INDEX($M$45:$M$80,A52-Parameters!$H$31)) -> 0.11026378 | T52: =T51+M52-S52 -> 0.10475059 | U52: =S52-N52-O52-Q52 -> 0.086513895 | V52: =V51+U52 -> 2.2418642 | W52: =(1-Parameters!$H$7)*(C52-E52)+(1-Parameters!$H$8)*(D52+E52) -> 0.004194304 | X52: =Parameters!$H$7*(C52-E52)+Parameters!$H$8*Parameters!$H$9*(D52+E52) -> 0 | Y52: =Parameters!$H$8*(1-Parameters!$H$9)*(D52+E52) -> 0.016777216 | Z52: =POWER(1/(1+Parameters!$H$32),A52-1)*(M52-N52) -> 0.075550821
A53: 9 | B53: =0 -> 0 | C53: =X52+B53 -> 0 | D53: =Y52 -> 0.016777216 | E53: =Parameters!$H$6*C53 -> 0 | F53: =IF(Parameters!$H$5=1,E53,0) -> 0 | G53: =Parameters!$H$27*G52+F53 -> 0 | H53: =IF(AND(Parameters!$H$5=1,Parameters!$H$26=1),SUMPRODUCT(--($A$45:A53<A53),--(MOD(A53-$A$45:A53,Parameters!$H$28)=0),$F$45:F53,POWER(Parameters!$H$27,IF(A53-$A$45:A53=0,1,A53-$A$45:A53))),0) -> 0 | I53: =Parameters!$H$23*I52+B53*Parameters!$H$22 -> 0.033171022 | J53: =E53*Parameters!$H$14*(1-Parameters!$H$15) -> 0 | K53: =H53*Parameters!$H$29 -> 0 | L53: =I53*Parameters!$H$24 -> 0.099513065 | M53: =J53+K53+L53 -> 0.099513065 | N53: =C53*Parameters!$H$17+D53*Parameters!$H$18+E53*Parameters!$H$16+I53*Parameters!$H$25+G53*Parameters!$H$30 -> 0.021618676 | O53: =0 -> 0 | P53: =M53-N53-O53 -> 0.077894389 | Q53: =0 -> 0 | R53: =P53-Q53 -> 0.077894389 | S53: =IF(A53<1+Parameters!$H$31,0,INDEX($M$45:$M$80,A53-Parameters!$H$31)) -> 0.10475059 | T53: =T52+M53-S53 -> 0.099513065 | U53: =S53-N53-O53-Q53 -> 0.083131919 | V53: =V52+U53 -> 2.3249961 | W53: =(1-Parameters!$H$7)*(C53-E53)+(1-Parameters!$H$8)*(D53+E53) -> 0.0033554432 | X53: =Parameters!$H$7*(C53-E53)+Parameters!$H$8*Parameters!$H$9*(D53+E53) -> 0 | Y53: =Parameters!$H$8*(1-Parameters!$H$9)*(D53+E53) -> 0.013421773 | Z53: =POWER(1/(1+Parameters!$H$32),A53-1)*(M53-N53) -> 0.071934161
A54: 10 | B54: =0 -> 0 | C54: =X53+B54 -> 0 | D54: =Y53 -> 0.013421773 | E54: =Parameters!$H$6*C54 -> 0 | F54: =IF(Parameters!$H$5=1,E54,0) -> 0 | G54: =Parameters!$H$27*G53+F54 -> 0 | H54: =IF(AND(Parameters!$H$5=1,Parameters!$H$26=1),SUMPRODUCT(--($A$45:A54<A54),--(MOD(A54-$A$45:A54,Parameters!$H$28)=0),$F$45:F54,POWER(Parameters!$H$27,IF(A54-$A$45:A54=0,1,A54-$A$45:A54))),0) -> 0 | I54: =Parameters!$H$23*I53+B54*Parameters!$H$22 -> 0.03151247 | J54: =E54*Parameters!$H$14*(1-Parameters!$H$15) -> 0 | K54: =H54*Parameters!$H$29 -> 0 | L54: =I54*Parameters!$H$24 -> 0.094537411 | M54: =J54+K54+L54 -> 0.094537411 | N54: =C54*Parameters!$H$17+D54*Parameters!$H$18+E54*Parameters!$H$16+I54*Parameters!$H$25+G54*Parameters!$H$30 -> 0.019782767 | O54: =0 -> 0 | P54: =M54-N54-O54 -> 0.074754644 | Q54: =0 -> 0 | R54: =P54-Q54 -> 0.074754644 | S54: =IF(A54<1+Parameters!$H$31,0,INDEX($M$45:$M$80,A54-Parameters!$H$31)) -> 0.099513065 | T54: =T53+M54-S54 -> 0.094537411 | U54: =S54-N54-O54-Q54 -> 0.079730298 | V54: =V53+U54 -> 2.4047264 | W54: =(1-Parameters!$H$7)*(C54-E54)+(1-Parameters!$H$8)*(D54+E54) -> 0.0026843546 | X54: =Parameters!$H$7*(C54-E54)+Parameters!$H$8*Parameters!$H$9*(D54+E54) -> 0 | Y54: =Parameters!$H$8*(1-Parameters!$H$9)*(D54+E54) -> 0.010737418 | Z54: =POWER(1/(1+Parameters!$H$32),A54-1)*(M54-N54) -> 0.068351148
A55: 11 | B55: =0 -> 0 | C55: =X54+B55 -> 0 | D55: =Y54 -> 0.010737418 | E55: =Parameters!$H$6*C55 -> 0 | F55: =IF(Parameters!$H$5=1,E55,0) -> 0 | G55: =Parameters!$H$27*G54+F55 -> 0 | H55: =IF(AND(Parameters!$H$5=1,Parameters!$H$26=1),SUMPRODUCT(--($A$45:A55<A55),--(MOD(A55-$A$45:A55,Parameters!$H$28)=0),$F$45:F55,POWER(Parameters!$H$27,IF(A55-$A$45:A55=0,1,A55-$A$45:A55))),0) -> 0 | I55: =Parameters!$H$23*I54+B55*Parameters!$H$22 -> 0.029936847 | J55: =E55*Parameters!$H$14*(1-Parameters!$H$15) -> 0 | K55: =H55*Parameters!$H$29 -> 0 | L55: =I55*Parameters!$H$24 -> 0.089810541 | M55: =J55+K55+L55 -> 0.089810541 | N55: =C55*Parameters!$H$17+D55*Parameters!$H$18+E55*Parameters!$H$16+I55*Parameters!$H$25+G55*Parameters!$H$30 -> 0.018189649 | O55: =0 -> 0 | P55: =M55-N55-O55 -> 0.071620892 | Q55: =0 -> 0 | R55: =P55-Q55 -> 0.071620892 | S55: =IF(A55<1+Parameters!$H$31,0,INDEX($M$45:$M$80,A55-Parameters!$H$31)) -> 0.094537411 | T55: =T54+M55-S55 -> 0.089810541 | U55: =S55-N55-O55-Q55 -> 0.076347763 | V55: =V54+U55 -> 2.4810741 | W55: =(1-Parameters!$H$7)*(C55-E55)+(1-Parameters!$H$8)*(D55+E55) -> 0.0021474836 | X55: =Parameters!$H$7*(C55-E55)+Parameters!$H$8*Parameters!$H$9*(D55+E55) -> 0 | Y55: =Parameters!$H$8*(1-Parameters!$H$9)*(D55+E55) -> 0.0085899346 | Z55: =POWER(1/(1+Parameters!$H$32),A55-1)*(M55-N55) -> 0.064837459
A56: 12 | B56: =0 -> 0 | C56: =X55+B56 -> 0 | D56: =Y55 -> 0.0085899346 | E56: =Parameters!$H$6*C56 -> 0 | F56: =IF(Parameters!$H$5=1,E56,0) -> 0 | G56: =Parameters!$H$27*G55+F56 -> 0 | H56: =IF(AND(Parameters!$H$5=1,Parameters!$H$26=1),SUMPRODUCT(--($A$45:A56<A56),--(MOD(A56-$A$45:A56,Parameters!$H$28)=0),$F$45:F56,POWER(Parameters!$H$27,IF(A56-$A$45:A56=0,1,A56-$A$45:A56))),0) -> 0 | I56: =Parameters!$H$23*I55+B56*Parameters!$H$22 -> 0.028440005 | J56: =E56*Parameters!$H$14*(1-Parameters!$H$15) -> 0 | K56: =H56*Parameters!$H$29 -> 0 | L56: =I56*Parameters!$H$24 -> 0.085320014 | M56: =J56+K56+L56 -> 0.085320014 | N56: =C56*Parameters!$H$17+D56*Parameters!$H$18+E56*Parameters!$H$16+I56*Parameters!$H$25+G56*Parameters!$H$30 -> 0.016796983 | O56: =0 -> 0 | P56: =M56-N56-O56 -> 0.068523031 | Q56: =0 -> 0 | R56: =P56-Q56 -> 0.068523031 | S56: =IF(A56<1+Parameters!$H$31,0,INDEX($M$45:$M$80,A56-Parameters!$H$31)) -> 0.089810541 | T56: =T55+M56-S56 -> 0.085320014 | U56: =S56-N56-O56-Q56 -> 0.073013558 | V56: =V55+U56 -> 2.5540877 | W56: =(1-Parameters!$H$7)*(C56-E56)+(1-Parameters!$H$8)*(D56+E56) -> 0.0017179869 | X56: =Parameters!$H$7*(C56-E56)+Parameters!$H$8*Parameters!$H$9*(D56+E56) -> 0 | Y56: =Parameters!$H$8*(1-Parameters!$H$9)*(D56+E56) -> 0.0068719477 | Z56: =POWER(1/(1+Parameters!$H$32),A56-1)*(M56-N56) -> 0.061418818
A57: 13 | B57: =0 -> 0 | C57: =X56+B57 -> 0 | D57: =Y56 -> 0.0068719477 | E57: =Parameters!$H$6*C57 -> 0 | F57: =IF(Parameters!$H$5=1,E57,0) -> 0 | G57: =Parameters!$H$27*G56+F57 -> 0 | H57: =IF(AND(Parameters!$H$5=1,Parameters!$H$26=1),SUMPRODUCT(--($A$45:A57<A57),--(MOD(A57-$A$45:A57,Parameters!$H$28)=0),$F$45:F57,POWER(Parameters!$H$27,IF(A57-$A$45:A57=0,1,A57-$A$45:A57))),0) -> 0 | I57: =Parameters!$H$23*I56+B57*Parameters!$H$22 -> 0.027018004 | J57: =E57*Parameters!$H$14*(1-Parameters!$H$15) -> 0 | K57: =H57*Parameters!$H$29 -> 0 | L57: =I57*Parameters!$H$24 -> 0.081054013 | M57: =J57+K57+L57 -> 0.081054013 | N57: =C57*Parameters!$H$17+D57*Parameters!$H$18+E57*Parameters!$H$16+I57*Parameters!$H$25+G57*Parameters!$H$30 -> 0.015570586 | O57: =0 -> 0 | P57: =M57-N57-O57 -> 0.065483427 | Q57: =0 -> 0 | R57: =P57-Q57 -> 0.065483427 | S57: =IF(A57<1+Parameters!$H$31,0,INDEX($M$45:$M$80,A57-Parameters!$H$31)) -> 0.085320014 | T57: =T56+M57-S57 -> 0.081054013 | U57: =S57-N57-O57-Q57 -> 0.069749427 | V57: =V56+U57 -> 2.6238371 | W57: =(1-Parameters!$H$7)*(C57-E57)+(1-Parameters!$H$8)*(D57+E57) -> 0.0013743895 | X57: =Parameters!$H$7*(C57-E57)+Parameters!$H$8*Parameters!$H$9*(D57+E57) -> 0 | Y57: =Parameters!$H$8*(1-Parameters!$H$9)*(D57+E57) -> 0.0054975581 | Z57: =POWER(1/(1+Parameters!$H$32),A57-1)*(M57-N57) -> 0.058113216
... A80: 36 | B80: =0 -> 0 | C80: =X79+B80 -> 0 | D80: =Y79 -> 4.0564819e-05 | E80: =Parameters!$H$6*C80 -> 0 | F80: =IF(Parameters!$H$5=1,E80,0) -> 0 | G80: =Parameters!$H$27*G79+F80 -> 0 | H80: =IF(AND(Parameters!$H$5=1,Parameters!$H$26=1),SUMPRODUCT(--($A$45:A80<A80),--(MOD(A80-$A$45:A80,Parameters!$H$28)=0),$F$45:F80,POWER(Parameters!$H$27,IF(A80-$A$45:A80=0,1,A80-$A$45:A80))),0) -> 0 | I80: =Parameters!$H$23*I79+B80*Parameters!$H$22 -> 0.0083041692 | J80: =E80*Parameters!$H$14*(1-Parameters!$H$15) -> 0 | K80: =H80*Parameters!$H$29 -> 0 | L80: =I80*Parameters!$H$24 -> 0.024912508 | M80: =J80+K80+L80 -> 0.024912508 | N80: =C80*Parameters!$H$17+D80*Parameters!$H$18+E80*Parameters!$H$16+I80*Parameters!$H$25+G80*Parameters!$H$30 -> 0.004164254 | O80: =0 -> 0 | P80: =M80-N80-O80 -> 0.020748254 | Q80: =0 -> 0 | R80: =P80-Q80 -> 0.020748254 | S80: =IF(A80<1+Parameters!$H$31,0,INDEX($M$45:$M$80,A80-Parameters!$H$31)) -> 0.026223692 | T80: =T79+M80-S80 -> 0.024912508 | U80: =S80-N80-O80-Q80 -> 0.022059438 | V80: =V79+U80 -> 3.5606881 | W80: =(1-Parameters!$H$7)*(C80-E80)+(1-Parameters!$H$8)*(D80+E80) -> 8.1129638e-06 | X80: =Parameters!$H$7*(C80-E80)+Parameters!$H$8*Parameters!$H$9*(D80+E80) -> 0 | Y80: =Parameters!$H$8*(1-Parameters!$H$9)*(D80+E80) -> 3.2451855e-05 | Z80: =POWER(1/(1+Parameters!$H$32),A80-1)*(M80-N80) -> 0.014646487

Sheet S6
A1: S6 — Policy commission and renewal hypothesis
A2: All parameters are illustrative. Top block: calendar cohorts. Lower block: one acquired owner, no CAC/fixed cost, for customer-value calculation.
